Workbook
Name aut: #REF!
Name CamposSIS: README!$A$24:$B$131
Name ConR: #REF!
Name Cris: #REF!
Name DatosEspecies: 'BASE MAESTRA'!$B$7:$DU$208
Name DisContHab: #REF!
Name DisContSubp: #REF!
Name EB_PotLC_need_Assessment: #REF!
Name FragSev: #REF!
Name iws: 'BASE MAESTRA'!#REF!
Name orden: #REF!
Name Paula: #REF!
Name ref: #REF!
Name RL: #REF!
Name Sin: #REF!
Name SISdetails: 'SIS DETAILS'!$A$1:$I$8
Name solotipo: #REF!
Name Taxonomy: '[1]ConR +Tax'!$A$1:$M$318

Sheet README
A2: IUCN - SSC - GRUPO DE ESPECIALISTAS DE PLANTAS DE COLOMBIA INSTRUCCIONES PARA DILIGENCIAR ESTE ARCHIVO PARA EVALUACIONES DE LISTA ROJA DE PLANTAS A NIVEL NACIONAL
A4: AUTORAS DE ESTE ARCHIVO | B4: Cristina Lopez-Gallego & Paula A. Morales Morales Grupo de Especialistas de Plantas de Colombia Grupo EECO - Instituto de Biología, Universidad de Antioquia
A6: INSTRUCCIONES GENERALES | B6: "Para tener en cuenta ANTES de subir evaluaciones de especies a la plataforma "SIS connect": - Para subir información de las evaluaciones a la plataforma "SIS connect" se deben producir 14 archivos tipo .csv y compilarlos en una carpeta ".zip" Esta carpeta se sube en la plataforma SIS connect como un "working set", y desde allí automáticamente se crean archivos individuales para cada especie en la plataforma "SIS". Las evaluaciones se pueden revisar posterioremente en la plataforma "SIS", si es necesario. Para realizar todo el proceso, es necesitario contactar la Unidad de Lista Roja de la IUCN, para obtener UNA CUENTA que permite acceder (con el mismo usuario y contraseña) a las plataformas de "SIS" y "SIS connect". - ANTES de subir tu "working set" en la plataforma de "SIS connect" debes contactar al Grupo de Especialistas de Plantas de Colombia <ge.plantascolombia@gmail.com>, para coordinar la revisión de estas evaluaciones y contactar a la Unidad de Lista Roja de la IUCN para su publicación. - Es MUY IMPORTANTE establecer si las especies que se están evaluando en tu proyecto YA se han evaluado antes Y/O YA están publicadas en la plataforma web de la Lista Roja Global. También es importante determinar si existe en este momento algún otro Grupo de especialistas de la IUCN que esté realizando esas evaluaciones. Si algunas de la especies que estás evaluando ya han sido o están siendo evaluadas actualmente, se debe coordinar la situación con el Grupo de Especialistas de Plantas de Colombia y la Unidad de Lista Roja de la IUCN (para decidir unir las dos evaluaciones, reemplazar las evaluaciones viejas, u otra opción) ANTES de subir su información al "SIS connect".
B7: Procedimiento general para compilar la información para las evaluaciones: - En este archivo de excel, se usa la pestaña "BASE MAESTRA" para digitar toda la información que se obtenga para la evaluación de cada especie. La información para cada especie se consigna en difrentes campos (las columnas). El archivo tiene instrucciones detalladas de como llenar cada uno de los campos, por favor seguir esas instrucciones detalladamente (de lo contrario, podrían haber errores al subir la información a "SIS connect"). La información de cada especie está en filas, y en este archivo se puede diligenciar información para un máximo de 200 especies. Recomendamos hacer archivos de menos de 200 especies, para facilitar su ingreso a la plataforma "SIS connect". Si su proyecto tiene menos de 200 especies a evaluar, BORRE las fórmulas en las filas que no se necesitan en todas las pestañas para construir los archivos .csv - Algunos de los campos (columnas) se deben llenar con códigos y opciones específicas de la plataforma SIS connect. En las instrucciones para llenar ese campo están descritas las opciones que se pueden usar, pero en algunos casos no estan todas las opciones disponibles. Si se considera que se necesitan opciones adicionales, en las instrucciones del campo se referencia la página web de SIS connect en donde se pueden consultar. En esa página, puedes ir a la pestaña "OAuth" (pestaña amarilla arriba) y entrar con tu cuenta de google o facebook (si no tienes cuenta en el SIS de IUCN). - Este archivo de excel tiene además 14 pestañas (nombradas en minúscula) que corresponden a los archivos .csv requeridos para subir la información a la plataforma "SIS connect". Este archivo tiene fórmulas de excel (por favor no modificarlas) que permiten que a medida que la información se llena en la pestaña "BASE MAESTRA", esa misma información se va copiando en 12 de las 14 pestañas del libro de excel (todas menos la de "credits" & "references") - Las pestañas de "credits" & "references" se deben diligenciar de forma manual (ver instrucciones acá abajo). - Luego de que toda la información para la evaluación este ingresada en la BASE MAESTRA y en las 14 pestañas de los .csv, siga el procedimiento descrito acá abajo para obtener los 14 archivos .csv a subir a la plataforma "SIS connect". - Luego de subir su información al "SIS connect", la Unidad de Lista Roja de la IUCN lo contactará para confirmar que todo este bien. Con esta persona de contacto de IUCN se debe acordar como enviar los datos espaciales de ocurrencias y los mapas elaborados para la evaluaciones (y fotos si se desea).
A9: PROCEDIMIENTO PARA OBTENER LOS ARCHIVOS PARA EL SIS CONNECT | B9: Procedimiento para obtener los 14 archivos .csv necesarios para subir la información a través de "SIS Connect"
B10: 1. Llena por completo los campos de información para cada especie en la pestaña "BASE MAESTRA", según las instrucciones para cada campo. Esa información se va consigando automáticamente en las pestañas (las pestañas despues de la pestaña "BASE MAESTRA") que serán la base para crear los archivos .csv para el "SIS connect" (excepto en las pestañas de "credits" y "references", que deben ser diligenciadas de manera manual, ver instrucciones más abajo).
B11: 2. Para crear los archivos .csv a partir de las pestañas correspondientes, debes hacer algunas modificaciones ANTES de guardarlos como .csv. Primero, para cada una de las pestañas de .csv, copia y pega (opción de pegar "sólo valores") la información de CADA pestaña en un nuevo archivo de excel (que tenga el nombre de la pestaña) por separado. En cada uno de los nuevos archivos (14 en total), realiza las siguientes modificaciones: - Borra la COLUMNA A & FILA 2 (que estan en fondo cafecito y con letra roja en el archivo original), esta información en letra roja NO debe estar en el .csv final a subir al SIS connect. - Borra las filas que NO se usaron para evaluaciones de especies (si es que había menos de 200 especies con información en la pestaña "BASE MAESTRA"). - Borra el contenido de las celdas que tengan valores de N/A para que queden como celdas vacías (esas son las celdas para los que no había información original en la pestaña de la "BASE MAESTRA"), con la función buscar y reemplazar de excel.
B12: 3. Hay algunos archivos de las pestañas que requieren de trabajo adicional antes de subirlos al "SIS connect". Por favor sigue estas instrucciones detalladamente para la pestaña de "synonims" y para las siguientes pestañas con códigos del SIS: "conservationneeded", "countries", "habitats", "plantspecific", "researchneeded", "threats", "usetrade" --> En estas pestañas, hay algunos campos (columnas en la "BASE MAESTRA") que pueden tener varias opciones (separadas por comas) para una misma especie. Estas son las Columnas N (sinónimos), U (códigos usos), Y (códigos hábitos), AB (códigos países), AM (códigos hábitats), BN (códigos amenazas), CB & CC (códigos conservación & investigación requeridas). --> Para estas pestañas, luego de grabar el archivo nuevo de excel correspondiente, se debe realizar el siguiente procedimiento: En el archivo DEBE HABER UNA SÓLA FILA para cada una de las opciones del campo de opciones múltiples para una especie. Si para una especie hay opciones múltiples en alguno de los campos referenciados arriba, se debe dejar sólo una opción en la primera fila, y se deben insertar nuevas filas en el archivo, para que cada fila contenga una opción diferente para la especie (sin comas). TODAS las filas que correspondan a opciones de la misma especie DEBEN tener el mismo número único identificador de la especie ("internal_taxon-id"). Así, para las especies que tenían múltiples opciones en los campos que lo permiten (sinónimos, amenazas, etc), quedáran múltiples filas, tantas filas como opciones tenía la especie en la base de datos original (pestaña "BASE MAESTRA"). --> Finalmente, diligencia las pestañas de "credits" & "references" según las instrucciones acá abajo.
B13: 4. Cuando todos los archivos correspondientes a las 14 pestañas para el "SIS connect" estén listos, guarda cada archivo en formato .csv (separado por comas). Se DEBE usar el mismo nombre de la pestaña original para nombrar cada archivo .csv NO usar la opción .csv UTF8, esta opción genera conflictos de idioma en esta plataforma.
B14: 5. Crea una carpeta comprimida .zip con los 14 archivos .csv de tus evaluaciones. El nombre de esta carpeta lo elige el usuario, y debe ser un nombre corto y sencillo alusivo al grupo de especies evaluadas.
B15: 6. Ingresa a la plataforma web del "SIS Connect" y crea un "workingset". En este "working set" se carga la carpeta .zip con la información de las especies. Sigue en esa plataforma web todas las instrucciones…
A17: INSTRUCCIONES PARA MANEJO DE CRÉDITOS Pestaña "credits" | B17: - La pestaña "credits" se debe diligenciar manualmente. Para cada especie, se debe tener en cuenta cuántas personas participaron en la evaluación de esa especie (se pueden considerar a los Herbarios o instituciones que participen, pero se recomienda considerar a todos los Herbarios como UNA SOLA "institución contribuyente"). En esta pestaña "credits", cada especie debe tener un número de filas equivalente al número de personas que participaron en la evaluación. CADA FILA que corresponda a personas participantes en la evaluación, DEBE tener en mismo "internal_taxon_id", que es el número único que permite identificar a la especie en la pestaña "BASE MAESTRA". - Las filas que correspondan a las personas participantes de la evaluación se debe organizar de una manera específica. Se debe establecer un orden jerárquico ("order") de contribución de cada persona a la evaluación de la especie. Esta información se consiga en la Columna B ("order"). Este orden lo puede definir el equipo de trabajo del proyecto, según el grado de participación de cada persona en la evaluación. En este orden jerárquico: * Van primero los EVALUADORES (persona-s que hacen análisis de la información total y asignan la categoría de lista roja de la especie) * Van despúes los CONTRIBUYENTES (persona-s o instuciones que contribuyen con infromación de base, georreferenciación, análisis de datos, revisión de información, etc.) * Van de último los REVISORES (persona-s que revisan la evaluación de lista roja una vez a sido finalizada) - Luego de llenar la información alusiva a las personas que particiaron en la evaluación de cada especie en esta pestaña, procede a copiar y pegar la información en otra hoja de excel con la opción de "pegar solo valores", borre la Columna A y las Filas 2 a la 6 con las instrucciones de llenado y el ejemplo (filas y columnas en beige y con texto rojo). Guarde el archivo en formato .csv nombrandolo con la palabra "credits".
B18: Recomendaciones importantes para diligenciar la Pestaña "credits" - El número de filas por especie (Internal Taxon ID) debe ser igual al número de personas involucradas en la evaluación de esa especie. - Cada persona involucrada en la evaluación de una especie debe tener un NÚMERO ÚNICO asignado en la jerarquía ("order") de participación. Si dos o más personas tienen participación equivalente en la evaluación, se debe definir un orden, no pueden tener el mismo número en la jerarquía. - Si en la evaluación de alguna especie alguna función del orden jerárquico preestablecido no está cubierta por alguna persona, se obvia y se continua la numeración. - No se acepta incluir más de un email por persona. - Está bien si los créditos son idénticos para todas las especies, en cuyo caso sólo sería cuestión de diligenciar las filas de información para la primera especie y luego copiar esas filas cuantas veces sea necesario (según el número de especies evaluadas).
A20: INSTRUCCIONES PARA MANEJO DE REFERENCIAS Pestaña "references" | B20: - La pestaña "references" se debe diligenciar manualmente. Para cada especie, se debe tener en cuenta cuántos recursos bibliográficos se usaron en la evaluación. En los campos de la "BASE MAESTRA" por favor hacer las citacion lo mas simple posible (con autores y año sin comas ni puntos). En la pestaña "references", cada especie debe tener un número de filas equivalente al número de recursos bibliográficos usados en su evaluación. CADA FILA que corresponda a recurso bibliográfico usado, DEBE tener un "internal_taxon_id", que corresponde al número único que permite identificar a la especie en la pestaña "BASE MAESTRA", y así se puede identificar a cuál especie corresponde ese recurso bilbiográfico. - Luego de llenar la información alusiva a los recursos bibliográficos usados en la evaluación de cada especie en esta pestaña, procede a copiar y pegar la información en otra hoja de excel con la opción de "pegar solo valores", borre la Columna A y las Filas 2 a la 5 con las instrucciones y el ejemplo (filas y columnas en beige y con texto rojo). Guarde el archivo en formato .csv nombrandolo con la palabra "references".
B21: Recomendaciones importantes para diligenciar la Pestaña "references" - Trate de hacer las referencias bibliográficas lo más sencillas posibles, minimizando los signos de puntuación y los caracteres que sean raros en inglés (como tildes, etc.), evite el uso de puntos finales en cada campo. - Use Mayúsculas para cada palabra inicial en los títulos de las referencias, especialmente en las que son en inglés. - Si la referencia es en inglés use "and" antes del último autor, si es en español use "y", si es en portugués use "e", no use "&". - Todas las referencias deben contar con año de publicación, fecha de acceso, lugar de publicación, editorial (publisher) y tipo de publicación. - Revise que un mismo recurso bibliográfico NO esté ingresado de formas diferentes para diferentes especies. En caso de usar un mismo recurso bibliográfico para diferentes especies, solo debe variar el "internal_taxon_id" ó número único identificador de la especie entre las filas que correspondan a ese recurso.
A23: NO ELIMINE O MODIFIQUE LA INFORMACION A CONTINUACION Los códigos en las filas siguientes son usados para introducir de manera automática la información que se consigna en la pestaña "base maestra" a las pestañas correspondientes para luego crear los archivos .csv a subir a la plataforma "sis connect"
A24: Campo | B24: Numero de celda
A25: internal_taxon_id | B25: 1
A26: kingdom | B26: 2
A27: phylum | B27: 3
A28: classname | B28: 4
A29: ordername | B29: 5
A30: family | B30: 6
A31: genus | B31: 7
A32: species | B32: 8
A33: taxonomicAuthority | B33: 9
A34: GEPC | B34: 10
A35: GEPC | B35: 11
A36: GEPC | B36: 12
... A67: GEPC | B67: 43
B68: 44
A69: GEPC | B69: 45
A70: EOO.range | B70: 46
A71: AOO.range | B71: 47
A72: SubpopulationNumber.range | B72: 48
A73: LocationsNumber.range | B73: 49
A74: GEPC | B74: 50
A75: GEPC | B75: 51
A76: GEPC | B76: 52
A77: GEPC | B77: 53
A78: SevereFragmentation.isFragmented | B78: 54
A79: SevereFragmentation.justification | B79: 55
A80: HabitatContinuingDecline.isDeclining | B80: 56
... A114: RLU2020 | B114: 90
A115: GEPC | B115: 91 | D115: =IF(C115=A115,0,1) -> 1
A116: reasonforchangejustification.narrative | B116: 92
A117: RedListReasonsForChange.type | B117: 93
A118: ​RedListReasonsForChange.catCritChanges | B118: 94
A119: RedListReasonsForChange.changeReasons | B119: 95
A120: GEPC | B120: 96
A121: GEPC | B121: 97
A122: GEPC | B122: 98
A123: GEPC | B123: 99
A124: GEPC | B124: 100
A125: GEPC | B125: 101
A126: GEPC | B126: 102
A127: GEPC | B127: 103
... A131: RLU 2021 | B131: 107

Sheet SIS DETAILS
A1: Data Point | B1: unit | C1: Tab | D1: Data Point | E1: Description | F1: Data Type | G1: File | H1: ClassificationType | I1: Needed in Import
A2: Need this for all the files to link together to the taxonomy | C2: Internal Taxon ID | D2: Need this for all the files to link together to the taxonomy
A3: internal_taxon_id | D3: internal_taxon_id | E3: should be unique - hopefully the external system will have one - IS REQUIRED | F3: Short text | G3: allfields.csv | I3: YES
A4: internal_taxon_id | D4: internal_taxon_id | E4: should be unique - hopefully the external system will have one - IS REQUIRED | F4: Short text | G4: assessments.csv | I4: YES
A5: internal_taxon_id | D5: internal_taxon_id | E5: should be unique - hopefully the external system will have one - IS REQUIRED | F5: Short text | G5: commonnames.csv | I5: YES
A6: internal_taxon_id | D6: internal_taxon_id | E6: should be unique - hopefully the external system will have one - IS REQUIRED | F6: Short text | G6: conservationneeded.csv | I6: YES
A7: internal_taxon_id | D7: internal_taxon_id | E7: should be unique - hopefully the external system will have one - IS REQUIRED | F7: Short text | G7: researchneeded.csv | I7: YES
A8: internal_taxon_id | D8: internal_taxon_id | E8: should be unique - hopefully the external system will have one - IS REQUIRED | F8: Short text | G8: plantspecific.csv | I8: YES
A9: internal_taxon_id | D9: internal_taxon_id | E9: should be unique - hopefully the external system will have one - IS REQUIRED | F9: Short text | G9: countries.csv | I9: YES
A10: internal_taxon_id | D10: internal_taxon_id | E10: should be unique - hopefully the external system will have one - IS REQUIRED | F10: Short text | G10: credits.csv | I10: YES
A11: internal_taxon_id | D11: internal_taxon_id | E11: should be unique - hopefully the external system will have one - IS REQUIRED | F11: Short text | G11: habitats.csv | I11: YES
A12: internal_taxon_id | D12: internal_taxon_id | E12: should be unique - hopefully the external system will have one - IS REQUIRED | F12: Short text | G12: references.csv | I12: YES
A13: internal_taxon_id | D13: internal_taxon_id | E13: should be unique - hopefully the external system will have one - IS REQUIRED | F13: Short text | G13: synonyms.csv | I13: YES
A14: internal_taxon_id | D14: internal_taxon_id | E14: should be unique - hopefully the external system will have one - IS REQUIRED | F14: Short text | G14: taxonomy.csv | I14: YES
... A18: internal_taxon_id | D18: internal_taxon_id | E18: should be unique - hopefully the external system will have one - IS REQUIRED | F18: Short text | G18: usetrade.csv | I18: YES
B19: Distribution
C20: Geographic Range
A21: RangeDocumentation.narrative | D21: RangeDocumentation.narrative | E21: Geographic Range Information. This is required for all the assessments apart from Least Concern (LC) | F21: Long Text/Narrative | G21: assessments.csv | I21: YES
C22: AOO
A23: AOO.range | D23: AOO.range | E23: Estimated area of occupancy (AOO) – in km2 | F23: Range | G23: allfields.csv
A24: AOO.justification | D24: AOO.justification | E24: Justification | F24: Short Text | G24: allfields.csv
A25: AOODetails.breedingRange | D25: AOODetails.breedingRange | E25: Range of breeding area (AOO) | F25: Range | G25: allfields.csv
A26: AOODetails.breedingRangeJustification | D26: AOODetails.breedingRangeJustification | E26: Justification of breeding area (AOO) | F26: Short Text | G26: allfields.csv
A27: AOODetails.nonbreedingRange | D27: AOODetails.nonbreedingRange | E27: Range of non-breeding area (AOO) | F27: Range | G27: allfields.csv
A28: AOODetails.nonbreedingRangeJustification | D28: AOODetails.nonbreedingRangeJustification | E28: Justification of non-breeding area (AOO) | F28: Short Text | G28: allfields.csv
A29: AOOContinuingDecline.isInContinuingDecline | D29: AOOContinuingDecline.isInContinuingDecline | E29: Continuing decline in area of occupancy (AOO). This field can take the following values: "1" (meaning true), "0" (meaning false), or "U" (meaning “unknown”) | F29: Boolean Range | G29: allfields.csv
A30: AOOContinuingDecline.qualifier | D30: AOOContinuingDecline.qualifier | E30: Qualifier | F30: Single Select | G30: allfields.csv
A31: AOOContinuingDecline.justification | D31: AOOContinuingDecline.justification | E31: Justification | F31: Short Text | G31: allfields.csv
A32: AOOExtremeFluctuation.isFluctuating | D32: AOOExtremeFluctuation.isFluctuating | E32: Extreme fluctuations in area of occupancy (AOO). This field can take the following values: "1" (meaning true), "0" (meaning false), or "U" (meaning “unknown”) | F32: Boolean Range | G32: allfields.csv
A33: AOOExtremeFluctuation.justification | D33: AOOExtremeFluctuation.justification | E33: Justification | F33: Short Text | G33: allfields.csv
C34: EOO
A35: EOO.range | D35: EOO.range | E35: Estimated extent of occurrence (EOO)- in km2 | F35: Range | G35: allfields.csv
A36: EOO.justification | D36: EOO.justification | E36: Justification | F36: Short Text | G36: allfields.csv
A37: EOOContinuingDecline.isContinuingDecline | D37: EOOContinuingDecline.isContinuingDecline | E37: Continuing decline in extent of occurrence (EOO). This field can take the following values: "1" (meaning true), "0" (meaning false), or "U" (meaning “unknown”) | F37: Boolean Range | G37: allfields.csv
A38: EOOContinuingDecline.qualifier | D38: EOOContinuingDecline.qualifier | E38: Qualifier | F38: Single Select | G38: allfields.csv
A39: EOOContinuingDecline.justification | D39: EOOContinuingDecline.justification | E39: Justification | F39: Short Text | G39: allfields.csv
A40: EOOExtremeFluctuation.isFluctuating | D40: EOOExtremeFluctuation.isFluctuating | E40: Extreme fluctuations in extent of occurrence (EOO). This field can take the following values: "1" (meaning true), "0" (meaning false), or "U" (meaning “unknown”) | F40: Boolean Range | G40: allfields.csv
A41: EOOExtremeFluctuation.justification | D41: EOOExtremeFluctuation.justification | E41: Justification | F41: Short Text | G41: allfields.csv
A42: EOODetails.breedingRange | D42: EOODetails.breedingRange | E42: Estimated extent of occurrence (EOO) for the breeding range- in km2 (relevant to breeding species) | F42: Range | G42: allfields.csv
A43: EOODetails.nonbreedingRange | D43: EOODetails.nonbreedingRange | E43: Estimated extent of occurrence (EOO) for the non-breeding range- in km2 | F43: Range | G43: allfields.csv
C44: Locations
A45: LocationsNumber.range | D45: LocationsNumber.range | E45: Number of Locations | F45: Range | G45: allfields.csv
A46: LocationsNumber.justification | D46: LocationsNumber.justification | E46: Justification | F46: Short Text | G46: allfields.csv
A47: LocationContinuingDecline.inDecline | D47: LocationContinuingDecline.inDecline | E47: Continuing decline in number of locations. This field can take the following values: "1" (meaning true), "0" (meaning false), or "U" (meaning “unknown”) | F47: Boolean Range | G47: allfields.csv
A48: LocationContinuingDecline.qualifier | D48: LocationContinuingDecline.qualifier | E48: Qualifier | F48: Single Select | G48: allfields.csv
A49: LocationContinuingDecline.justification | D49: LocationContinuingDecline.justification | E49: Justification | F49: Short Text | G49: allfields.csv
A50: LocationExtremeFluctuation.isFluctuating | D50: LocationExtremeFluctuation.isFluctuating | E50: Extreme fluctuations in the number of locations. This field can take the following values: "1" (meaning true), "0" (meaning false), or "U" (meaning “unknown”) | F50: Boolean Range | G50: allfields.csv
A51: LocationExtremeFluctuation.justification | D51: LocationExtremeFluctuation.justification | E51: Justification | F51: Short Text | G51: allfields.csv
C52: Very Restricted
A53: AreaRestricted.isRestricted | D53: AreaRestricted.isRestricted | E53: Very restricted in area of occupancy (AOO) and/or # of locations. This field can take the following values: "1" (meaning true), "0" (meaning false), or "U" (meaning “unknown”) | F53: Boolean Range | G53: allfields.csv
A54: AreaRestricted.justification | D54: AreaRestricted.justification | E54: Justification | F54: Short Text | G54: allfields.csv
C55: Elevation/Depth
A56: ElevationLower.limit | D56: ElevationLower.limit | E56: Elevation Lower Limit (in metres above sea level) | F56: Numeric | G56: allfields.csv | I56: RECOMMENDED
A57: ElevationUpper.limit | D57: ElevationUpper.limit | E57: Elevation Upper Limit (in metres above sea level) | F57: Numeric | G57: allfields.csv | I57: RECOMMENDED
A58: DepthLower.limit | D58: DepthLower.limit | E58: Depth Lower Limit (in metres below sea level) | F58: Numeric | G58: allfields.csv | I58: RECOMMENDED
A59: DepthUpper.limit | D59: DepthUpper.limit | E59: Depth Upper Limit (in metres below sea level) | F59: Numeric | G59: allfields.csv | I59: RECOMMENDED
A60: DepthZone.depthZone | D60: DepthZone.depthZone | E60: Depth Zone | F60: Multiple Select | G60: allfields.csv | I60: RECOMMENDED
C61: Map Status
A62: MapStatus.status | D62: MapStatus.status | E62: Map Status | F62: Single Select | G62: assessments.csv | I62: YES
C63: Biogeographic Realms
A64: BiogeographicRealm.realm | D64: BiogeographicRealm.realm | E64: Biogeographic Realm (separated by pipes ("|") if multiple) | F64: Multiple Select | G64: assessments.csv | I64: CONDITIONAL
B65: Occurrence
C66: Countries | H66: YES
A67: CountryOccurrence.CountryOccurrenceSubfield.CountryOccurrenceLookup | D67: CountryOccurrence.CountryOccurrenceSubfield.CountryOccurrenceLookup | E67: Selected Coding Option (provide ISO), e.g. JP | F67: Single Select | G67: countries.csv | I67: YES
A68: CountryOccurrence.CountryOccurrenceSubfield.CountryOccurrenceName | D68: CountryOccurrence.CountryOccurrenceSubfield.CountryOccurrenceName | E68: Country Name, e.g. Japan | F68: Short Text | G68: countries.csv | I68: CONDITIONAL
A69: CountryOccurrence.CountryOccurrenceSubfield.presence | D69: CountryOccurrence.CountryOccurrenceSubfield.presence | E69: Presence | F69: Single Select | G69: countries.csv | I69: YES
A70: CountryOccurrence.CountryOccurrenceSubfield.formerlyBred | D70: CountryOccurrence.CountryOccurrenceSubfield.formerlyBred | E70: Formerly Bred. This field can take the following values: 1 (meaning "Yes"), 2 (meaning "No"), or 3 (meaning "Unknown") | F70: Boolean Unknown | G70: countries.csv
A71: CountryOccurrence.CountryOccurrenceSubfield.origin | D71: CountryOccurrence.CountryOccurrenceSubfield.origin | E71: Origin | F71: Single Select | G71: countries.csv | I71: YES
A72: CountryOccurrence.CountryOccurrenceSubfield.seasonality | D72: CountryOccurrence.CountryOccurrenceSubfield.seasonality | E72: Seasonality | F72: Multiple Select | G72: countries.csv
C73: LME | E73: LME's are only required for Marine species | H73: YES
A74: LargeMarineEcosystems.LargeMarineEcosystemsSubfield.LargeMarineEcosystemsLookup | D74: LargeMarineEcosystems.LargeMarineEcosystemsSubfield.LargeMarineEcosystemsLookup | E74: Selected Coding Option, e.g. 2.1.1; | F74: Single Select | G74: lme.csv | I74: CONDITIONAL
A75: LargeMarineEcosystems.LargeMarineEcosystemsSubfield.LargeMarineEcosystemsName | D75: LargeMarineEcosystems.LargeMarineEcosystemsSubfield.LargeMarineEcosystemsName | E75: Large Marine Ecosystem Name, e.g. Mediterranean Sea | F75: Short Text | G75: lme.csv | I75: CONDITIONAL
A76: LargeMarineEcosystems.LargeMarineEcosystemsSubfield.presence | D76: LargeMarineEcosystems.LargeMarineEcosystemsSubfield.presence | E76: Presence | F76: Single Select | G76: lme.csv
A77: LargeMarineEcosystems.LargeMarineEcosystemsSubfield.formerlyBred | D77: LargeMarineEcosystems.LargeMarineEcosystemsSubfield.formerlyBred | E77: Formerly Bred. This field can take the following values: 1 (meaning "Yes"), 2 (meaning "No"), or 3 (meaning "Unknown") | F77: Boolean Unknown | G77: lme.csv
A78: LargeMarineEcosystems.LargeMarineEcosystemsSubfield.origin | D78: LargeMarineEcosystems.LargeMarineEcosystemsSubfield.origin | E78: Origin | F78: Single Select | G78: lme.csv
A79: LargeMarineEcosystems.LargeMarineEcosystemsSubfield.seasonality | D79: LargeMarineEcosystems.LargeMarineEcosystemsSubfield.seasonality | E79: Seasonality | F79: Multiple Select | G79: lme.csv
C80: FAO | E80: FAO's are only required for Marine species | H80: YES
A81: FAOOccurrence.FAOOccurrenceSubfield.FAOOccurrenceLookup | D81: FAOOccurrence.FAOOccurrenceSubfield.FAOOccurrenceLookup | E81: Selected Coding Option, e.g. 18 | F81: Single Select | G81: fao.csv | I81: CONDITIONAL
A82: FAOOccurrence.FAOOccurrenceSubfield.FAOOccurrenceName | D82: FAOOccurrence.FAOOccurrenceSubfield.FAOOccurrenceName | E82: FAO Occurance Name, e.g. Arctic Sea | F82: Short Text | G82: fao.csv | I82: CONDITIONAL
A83: FAOOccurrence.FAOOccurrenceSubfield.presence | D83: FAOOccurrence.FAOOccurrenceSubfield.presence | E83: Presence | F83: Single Select | G83: fao.csv | I83: CONDITIONAL
A84: FAOOccurrence.FAOOccurrenceSubfield.formerlyBred | D84: FAOOccurrence.FAOOccurrenceSubfield.formerlyBred | E84: Formerly Bred. This field can take the following values: 1 (meaning "Yes"), 2 (meaning "No"), or 3 (meaning "Unknown") | F84: Boolean Unknown | G84: fao.csv
A85: FAOOccurrence.FAOOccurrenceSubfield.origin | D85: FAOOccurrence.FAOOccurrenceSubfield.origin | E85: Origin | F85: Single Select | G85: fao.csv | I85: CONDITIONAL
A86: FAOOccurrence.FAOOccurrenceSubfield.seasonality | D86: FAOOccurrence.FAOOccurrenceSubfield.seasonality | E86: Seasonality | F86: Multiple Select | G86: fao.csv
B87: Population
C88: Documentation
A89: PopulationDocumentation.narrative | D89: PopulationDocumentation.narrative | E89: Population Information.This is required for all the assessments apart from Least Concern (LC) | F89: Long Text/Narrative | G89: assessments.csv | I89: YES
C90: Population
A91: PopulationTrend.value | D91: PopulationTrend.value | E91: Current Population Trend - only if not EX, Ew | F91: Single Select | G91: assessments.csv | I91: YES
A92: PopulationSize.range | D92: PopulationSize.range | E92: Population Size (mature individuals) | F92: Range | G92: allfields.csv
A93: CurrentTrendDataDerivation.value | D93: CurrentTrendDataDerivation.value | E93: Source or origin of current trend data | F93: Single Select | G93: allfields.csv | I93: RECOMMENDED
A94: YearOfPopulationEstimate.value | D94: YearOfPopulationEstimate.value | E94: Year of Population Estimate | F94: Float | G94: allfields.csv
A95: PopulationExtremeFluctuation.isFluctuating | D95: PopulationExtremeFluctuation.isFluctuating | E95: Extreme fluctuations? (in # of mature individuals). This field can take the following values: "1" (meaning true), "0" (meaning false), or "U" (meaning “unknown”) | F95: Boolean Range | G95: allfields.csv
A96: PopulationExtremeFluctuation.justification | D96: PopulationExtremeFluctuation.justification | E96: Justification | F96: Short Text | G96: allfields.csv
A97: SevereFragmentation.isFragmented | D97: SevereFragmentation.isFragmented | E97: Severely fragmented? This field can take the following values: "1" (meaning true), "0" (meaning false), or "U" (meaning “unknown”) | F97: Boolean Range | G97: allfields.csv
A98: SevereFragmentation.justification | D98: SevereFragmentation.justification | E98: Justification | F98: Short Text | G98: allfields.csv
A99: PopulationContinuingDecline.isDeclining | D99: PopulationContinuingDecline.isDeclining | E99: Continuing decline in mature individuals? This field can take the following values: "1" (meaning true), "0" (meaning false), or "U" (meaning “unknown”) | F99: Boolean Range | G99: allfields.csv
A100: PopulationContinuingDecline.qualifier | D100: PopulationContinuingDecline.qualifier | E100: Qualifier | F100: Single Select | G100: allfields.csv
A101: PopulationContinuingDecline.justification | D101: PopulationContinuingDecline.justification | E101: Justification | F101: Short Text | G101: allfields.csv
A102: PopulationDeclineGenerations1.range | D102: PopulationDeclineGenerations1.range | E102: Continuing decline % in mature individuals within 1 generation or 3 years, whichever is longer, note to not go 100 years in future | G102: allfields.csv
A103: PopulationDeclineGenerations1.qualifier | D103: PopulationDeclineGenerations1.qualifier | E103: Qualifier | F103: Single Select | G103: allfields.csv
...

Sheet BASE MAESTRA
A1: Encargad@ | B1: Número interno del taxón "internal_taxon_id" | C1: REINO | D1: PHYLLUM | E1: CLASE | F1: ORDEN | G1: FAMILIA | H1: GÉNERO | I1: ESPECIE | J1: AUTOR | K1: NOMBRE CIENTÍFICO sin autor | L1: REFERENCIA DEL TIPO | M1: LISTA DE SINÓNIMOS con autor | N1: GÉNERO DE SINÓNIMOS | O1: EPÍTETO DE SINONIMOS | P1: AUTORES DE SINÓNIMOS | Q1: NOMBRE COMÚN PRINCIPAL | R1: CÓDIGO SIS LENGUAJE DEL NOMBRE COMÚN PRINCIPAL | S1: REPORTE DE NOMBRE COMÚN PRINCIPAL SIS | T1: CÓDIGO SIS USOS | U1: REPORTE DE NO USO SIS | V1: DESCRIPCIÓN DE USOS Y COMERCIO | W1: REPORTE USO INDIRECTO SIS | X1: CÓDIGOS SIS HÁBITO | Y1: CÓDIGO SIS HABITO TEXTO | Z1: DESCRIPCIÓN MORFOLÓGICA | AA1: CÓDIGO SIS PAÍS | AB1: CÓDIGO SIS PAÍS TEXTO | AC1: CÓDIGO SIS ORIGEN | AD1: CÓDIGO SIS PRESENCIA | AE1: LÍMITE INFERIOR RANGO ALTITUDINAL | AF1: LÍMITE SUPERIOR RANGO ALTITUDINAL | AG1: CÓDIGO SIS REGIÓN BIOGEOGRÁFICA | AH1: DESCRIPCIÓN DISTRIBUCIÓN GEOGRÁFICA | AI1: CÓDIGO SIS MAPA | AJ1: CÓDIGO SIS TERRESTRE O ACUÁTICA | AK1: CÓDIGO SIS CALIDAD DEL HÁBITAT | AL1: CÓDIGO SIS TIPO DE HÁBITAT | AM1: DESCRIPCIÓN HÁBITAT GENERAL | AN1: DESCRIPCIÓN ECOLOGÍA GENERAL | AO1: RESUMEN HABITAT Y ECOLOGÍA | AP1: TIPO DISPERSION | AQ1: OBSERVACIONES A DISPERSIÓN | AR1: DISTANCIA MÁXIMA DE DISPERSIÓN | AS1: UMBRAL PARCHE PEQUEÑO | AT1: NOMBRE CIENTÍFICO sin autor | AU1: EOO (S RedList) | AV1: AOO (S RedList) | AW1: EOO (km2) | AX1: AOO (km2) | AY1: # SUBPOBLACIONES | AZ1: # LOCALIDADES "locations" | BA1: % OCURRENCIAS EN AREAS PROTEGIDAS | BB1: % PARCHES PEQUEÑOS Y AISLADOS | BC1: % HUELLA HUMANA EN LA AOO | BD1: REPORTE SUBPOBLACIONES DESAPARECIDAS | BE1: CÓDIGO SIS FRAGMENTACIÓN | BF1: DESCRIPCIÓN DE FRAGMENTACIÓN SIS | BG1: CÓDIGO SIS DISMINUCIÓN CONTINUA HÁBITAT | BH1: DESCRIPCIÓN DE DISMINUCIÓN CONTINUA HÁBITAT SIS | BI1: CÓDIGO SIS FUENTE DE LA DISM. CONTINUA HÁBITAT | BJ1: CÓDIGO SIS DISMINUCIÓN CONTINUA SUBPOBLACIONES | BK1: DESCRIPCIÓN DE DISMINUCIÓN CONTINUA SUBPOBLACIONES SIS | BL1: CÓDIGO SIS FUENTE DE LA DISM. CONTINUA SUBPOBLACIONES | BM1: DESCRIPCIÓN TAMAÑO POBLACIONAL Y DEMOGRAFÍA | BN1: DESCRIPCIÓN AMENAZAS | BO1: CÓDIGO SIS AMENAZAS | BP1: CÓDIGO SIS TIEMPO DE LAS AMENAZAS | BQ1: CÓDIGO SIS ALCANCE DE LAS AMENAZAS | BR1: CÓDIGO SIS SEVERIDAD DE LAS AMENAZAS | BS1: CÓDIGO SIS PRESIONES RESULTADO DE AMENAZAS | BT1: REPORTE DE "NO AMENAZAS" SIS | BU1: REPORTE DE "AMENAZAS DESCONOCIDAS" SIS | BV1: CÓDIGO SIS TENDENCIA POBLACIONAL | BW1: CÓDIGO SIS FUENTE DE LA TENDENCIA POBLACIONAL | BX1: DESCRIPCIÓN ACCIONES DE CONSERVACIÓN | BY1: REPORTE DE PRESENCIA EN AREAS PROTEGIDAS | BZ1: LISTADO DE AREAS PROTEGIDAS CON OCURRENCIAS | CA1: REPORTE DE CONSERVACION EXSITU | CB1: LISTADO DE COLECCIONES EXSITU CON INDIVIDUOS | CC1: CÓDIGO SIS CONSERVACIÓN REQUERIDA | CD1: CÓDIGO SIS INVESTIGACION REQUERIDA | CE1: CÓDIGO SIS CATEGORÍA LISTA ROJA | CF1: LISTA DE CRITERIOS Y SUBCRITERIOS SIS | CG1: REPORTE DE CRITERIOS ingreso manual | CH1: REPORTE DE VERSIÓN DE CRITERIOS | CI1: REPORTE RAZÓN CATEGORIA DD | CJ1: REPORTE CATEGORIA EX | CK1: DESCRIPICIÓN JUSTIFICACION EVALUACIÓN DE LISTA ROJA | CL1: FECHA DE EVALUACIÓN | CM1: CÓDIGO SIS LENGUAJE DE LA EVALUACIÓN | CN1: REPORTE DE EVALUACIONES PREVIAS | CO1: JUSTIFICACIONES DE EVALUACIONES PREVIAS | CP1: REPORTE EVALUACIÓN PREVIA DE LR OFICIAL | CQ1: RAZONES DE CAMBIO DE CATEGORÍA | CR1: CÓDIGO SIS TIPO DE CAMBIO DE CATEGORÍA | CS1: CÓDIGO SIS NO CAMBIO DE CATEGORÍA | CT1: CÓDIGO SIS CAMBIOS GENUINOS Y NO-GENUINOS | CU1: LISTA DE CONTRIBUYENTES: PERSONAS | CV1: LISTA DE CONTRIBUYENTES: INSTITUCIONES | CW1: LISTA DE EVALUADORES | CX1: LISTA DE REVISORES | CY1: LISTA DE EXPERTOS TAXÓNOMOS | CZ1: COMENTARIOS DE LA REVISIÓN POR EXPERTOS | DA1: REFERENCIAS BIBLIOGRÁFICAS | DB1: OBSERVACIONES ADICIONALES
A2: Persona quien recopila y diligencia la información sobre la especie en este archivo. | B2: Número interno del proyecto asignado para la especie (DEBE ser este consecutivo del 1 al 200 que ya está diligenciado para esta columna, NO lo cambies, pues si lo cambias no funcionarán las fórmulas en las pestañas para los archivos .csv). Todas los archivos .CSV incluyen esta columna con este CÓDIGO ÚNICO (# interno del taxón) para una especie = debe ser igual siempre en todos los archivos para poder reconocer la especie! | C2: Nombre del taxón, que debe seguir la clasificación de "World Flora Online". El nombre debe inicar con mayúscula seguida de minúsculas. Para plantas la opción es: Plantae | D2: Nombre del taxón, que debe seguir la clasificación de "World Flora Online". Para plantas las opciones son: Tracheophyta, Briophyta, Marchantiophyta, Anthoceratophyta Para algas las opciones son: Charophyta, Rhodophyta, Chlorophyta | E2: Nombre del taxón, que debe seguir la clasificación de "World Flora Online". Para plantas vasculares las opcione son: Magnoliopsida, Liliopsida, Polypodiopsida, Pinopsida, Cycadopsida, Lycopodiopsida, Gnetopsida, Ginkgoopsida | F2: Nombre del taxón, que debe seguir la clasificación de "World Flora Online" | G2: Nombre del taxón, que debe seguir la clasificación de "World Flora Online" | H2: Nombre del Género | I2: Epíteto de la especie | J2: Autor(es) del nombre científico de acuerdo con IPNI (International Plant Name Index) | K2: Nombre de la especie, sin el autor (para poderla ubicar fácilmente en el archivo) | L2: Vinculo web al protólogo, especimen tipo o donde aparece publicado el tipo de la especie. Si no esta disponible llenar la celda con N/A | M2: Nombre científico de todos los sinónimos reportados para la especie, con autor (siguiendo IPNI). Si son varios sinónimos, separar por coma y espacio. No usar punto final a menos que lo incluya el nombre de autor. Si la especie no tiene sinónimos reportados, rellenar con N/A | N2: Género de sinónimos. Si son varios, separarlos por coma y espacio. Si es el mismo género para varios sinónimos, repetir la palabra cuantas veces sea necesario. Si la especie no tiene sinónimos reportados, rellenar con N/A | O2: Epíteto especifico de sinónimos. Si son varios, separarlos por coma y espacio. Si son varios sinónimos, se debe seguir el orden de sus géneros correspondientes en la columna anterior. Si la especie no tiene sinónimos reportados, rellenar con N/A | P2: Autor de sinónimos (siguiendo IPNI). Si son varios, separar por coma y espacio. No usar punto final a menos que lo incluya el nombre de autor. Si son varios, se debe conservar el mismo orden que en la columna anterior de forma que corresponda a los epiptetos y géneros de las columnas. Si la especie no tiene sinónimos reportados, rellenar con N/A | Q2: Nombre común PRINCIPAL reportado para la especie. Si son varios nombres comunes, SOLO reportar UNO, el que se considere el más utilizado (de lo contrario se complica mucho este campo). Si la especie tiene otros nombres comunes, se pueden reportar en el texto de la columna "Descripción del uso y comercio de la especie" más adelante. Poner el nombre común principal con la letra inicial en mayúscula. Si la especie no tiene nombre común reportado, llenar la celda con N/A | R2: Declarar (según las opciones del SIS, en inglés, tal cual como aparecen acá abajo) el lenguaje del nombre común principal. Si la especie no tiene nombre común reportado, llenar la celda con N/A Opciones= Spanish; Castilian : se debe poner así, con las dos palabras separadas por el signo de punto y coma Chibcha Quechua South American Indian (Other) : se usa para cualquier lengua indígena que no sea Chibcha o Quechua, se debe poner tal cual con el paréntesis. Portuguese English Para ver otras opciones de lenguajes ir a http://connect.iucnredlist.org/sis_lookups/3705/findvalues | S2: Declarar (según las opciones del SIS de TRUE/FALSE) que el nombre común reportado es el principal. Si la especie NO tiene nombre común reportado, llenar la celda con N/A Opciones= TRUE : significa que el nombre común reportado es el principal (esta siempre será la opción en nuestro caso, si se reporto algún nombre común) NO : si el nombre reportado NO es el principal (nosotros no usamos esta opcion) | T2: Código SIS (sólo el número) para reportar los usos de la especie (para los humanos). Si son varios usos, enumerar en ascendentemente y separar por coma y espacio. Si no se conocen usos para la especie, rellenar con N/A (y usar el campo de "Reporte de NO USO SIS") Opciones= 1 - Food-human: uso alimenticio para humanos. 2 - Food-animal: uso alimenticio para animales domésticos. 3 - Medicine-human & veterinary: uso medicinal. 4 - Poisons: uso como veneno. 5 - Manufacturing chemicals: uso en la industria química. 6 - Other chemicals: uso como químico en otras actividades no industriales. 7 - Fuels: uso como combustibles, leña, etc. 8 - Fibre: uso como fibras. 9 - Construction or structural materials: uso en construcción, como madera o de otra manera. 10 - Wearing apparel, accesories: uso para ropa o accesorios. 11 - Other household goods: uso en hogares (diferentes a los ya mencionados). 12 - Handicrafts, jewellery, etc.: uso en artesanías, joyería, etc. 13 - Pets/display animals, horticulture: uso como mascotas o como plantas ornamentales. 14 - Research: uso en investigación. 15 - Sport hunting/specimen collecting: uso en actividades deportivas o de colección. 16 - Establishing ex-situ production: uso para establecer colecciones exsitu. 17 - Other (free text): otros usos no mencionados 18 - Unknown: la especie SI SE USA, pero NO SE SABE cual es el uso concreto segun estos codigos. Estas son todas las opciones disponibles. | U2: Declarar (según las opciones del SIS de TRUE/FALSE) que NO se conocen usos para la especie. Opciones= TRUE : significa que la especie NO tiene usos (la celda en la columna anterior debe tener N/A) FALSE : significa que la especie SI ES USADA, y se debio reportar su tipo de uso en la columna anterior N/A: En el caso de especies declaradas DD | V2: Descripción general de los usos (o no uso) de la especie. Por favor especificar si el uso es de subsistencia o si es a mayor escala, y si existe comercialización de los individuos o de productos derivados del uso de la especie. Campo de texto libre! Seguir el siguiente formato (incluyendo las citas o fuentes de información) e incluir un punto final: - Si la especie SI es usada: La especie es usada como [maderable / alimenticia / medicinal / etc.] por comunidades [campesinas / afroamericanas / indigenas ? / otras / en la región de ?, si se sabe esto]. [Describir cómo se usa la especie de manera breve, si se sabe]. [Describir si la especie es sobre-explotada o no, y si usa para subsistencia y/o se comercializa]. [Si se desean reportar varios nombres comunes o agregar otra información etnobotánica se puede hacer acá]. - Si la especie NO es usada: No se han reportado usos para la especie. | W2: Declarar (según las opciones del SIS de TRUE//FALSE) si la especie tiene "uso de no consumo". "Uso de no consumo" es un uso indirecto (como usos culturales), diferentes a usos directos (como maderable, medicinal, alimento, etc). Para llenar esta casilla debe haber un uso reportado en la columna "CODIGO SIS USOS". Opciones= TRUE : si la especie es usada de manera indirecta para practicas culturales, ecoturismo, etc. NO : si la especie NO es usada de manera indirecta (aunque podría tener usos directos) O NO es usada para nada | X2: Código SIS (solamente la sigla de una o dos letras en mayúsculas) para el hábito de la especie. Solo reportar varios hábitos de crecimiento si la especie realmente tiene muchos individuos de cada hábito (no si solo se han obervado unos pocos individuos excepcionales con otro hábito distinto al principal). Si la especie tiene varios hábitos de crecimiento, separar por coma y espacio. Opciones= T - Tree - size unknown : Arbol para el que no se conoce la altura maxima TL - Tree - large : Arbol grande (altura maxima > 15m) TS - Tree - small : Arbol pequeño (altura maxima < 15m) S - Shrub - size unknown : Arbusto para el que no se conoce la altura maxima SL - Shrub - large: Arbusto grande (altura maxima > 1m) SS - Shrub - small: Arbusto pequeño (altura maxima < 1m) F - Forb or Herb : Hierba A - Annual: plantas anuales GR - Graminoid : Graminea o similar G - Geophyte: plantas con bulbos subterráneos, cormos, rizomas PT - Fern: Helecho C - Cycad : Cycada M - Fungus: Hongo B - Moss : Briofita LC - Lichen : Liquen V - Vines : Liana, OJO: requiere declarar también un "hábito de formas únicas" de entre las opciones anteriores (de "T" hasta "LC") H - Hydrophyte: Acuática, OJO: requiere declarar también un "hábito de formas únicas" de entre las opciones anteriores (de "T" hasta "LC") P - Parasite : Parásita, OJO: requiere declarar también un "hábito de formas únicas" de entre las opciones anteriores (de "T" hasta "LC") E - Epiphyte : Epifita, OJO: requiere declarar también un "hábito de formas únicas" de entre las opciones anteriores (de "T" hasta "LC") L - Lithophyte : Rupicola, OJO: requiere declarar también un "hábito de formas únicas" de entre las opciones anteriores (de "T" hasta "LC") SA - Succulent - annual: Suculenta anual SH - Succulent - shrub : Suculenta arbustiva, incluyendo cactus arborescentes ST - Succulent - tree: Árbol suculento con altura maxima > 1m Para ver otros códigos de hábitos ir a http://connect.iucnredlist.org/sis_classifications/135/findvalues | Y2: Código SIS (según las opciones del SIS, en inglés, tal cual como estan acá abajo) con el nombre completo del hábito (sin sigla, como esta escrito acá abajo incluyendo guión medio si lo tiene), que debe corresponder al mismo hábito que se asignó en el campo anterior. Si la especie tiene varios hábitos, separar por coma y espacio. Opciones= T = Tree - size unknown TL = Tree - large TS = Tree - small S = Shrub - size unknown SL = Shrub - large SS = Shrub - small F = Forb or Herb A = Annual GR = Graminoid G = Geophyte PT = Fern C = Cycad M = Fungus B = Moss LC = Lichen V = Vine H = Hydrophyte P = Parasite E = Epiphyte L = Lithophyte SA = Succulent - annual SH = Succulent - shrub ST = Succulent - tree | Z2: Descripción morfológica BREVE de la especie. Evitar demasiada prosa, jerga botánica y el uso de medidas de tamaños (excepto por la altura máxima). Esta NO es una descripción taxonómica formal, sólo es un párrafo para ilustrar la apariencia de la especie en la ficha de la evaluación de lista roja. En el texto reportar los números de 1 a 10 como palabras (no números), excepto cuando se estan citando las alturas. Campo de texto libre! Seguir el siguiente formato (incluyendo las citas o fuentes de información) e incluir un punto final: [Árbol / Arbusto / Hierba / otro tipo de hábito, si son varios repórtelos] de hasta X m de altura. Hojas [simples / compuestas], [alternas / opuestas / verticiladas]. [Flores solitarias / Inflorescencia en racimo / panícula / otro tipo], flores [color]. Fruto [baya / cápsula / otro tipo], [color]. Semillas [color, forma y descripción de arilo si lo presenta]. | AA2: Código SIS (sólo la sigla en mayúsculas) de los países donde la especie ocurre. Si son varios países, separar por coma y espacio. Opciones= CO : Colombia PA : Panama VE : Venezuela BR : Brazil PE : Peru EC : Ecuador Para ver otros códigos de países ir a http://connect.iucnredlist.org/sis_classifications/128/findvalues | AB2: Código SIS (según las opciones del SIS, en inglés, tal cual como aparecen acá abajo) del nombre completo del paíes (sin sigla y sin tildes) en donde ocurre la especie. Si hay varios países, separar por coma y espacio. Opciones= CO : Colombia PA : Panama VE : Venezuela BR : Brazil PE : Peru EC : Ecuador Para ver otros códigos de países ir a http://connect.iucnredlist.org/sis_classifications/128/findvalues | AC2: Código SIS (según las opciones del SIS, en inglés, tal cual como aparecen acá abajo) sobre si la especie es nativa o introducida. Opciones= Native : la especie es nativa en el país (es la opción usada casi siempre) Reintroduced : reintroducida luego de extinción en la distribución (no usamos mucho esta opción) Introduced : introdución en sitios nuevos donde no se distribuia la especie (no usamos mucho esta opción) Origin Uncertain : no se conoce el origen de la especie (no usamos mucho esta opción) | AD2: Código SIS (según las opciones del SIS, en inglés, tal cual como aparecen aca abajo) sobre si la especie está extinta o no. Opciones= Extant: la especie sobrevive actualmente, esta debe ser la opción en nuestras evaluaciones Possibly Extinct: la especie podría estar extinta en hábitats naturales Presence Uncertain : no se sabe si la especie está extinta o no | AE2: Valor numérico de la elevación mínima donde se ha reportado la especie. Expresar el valor en metros (numero entero sin decimales), y emplear un número redondeado a cientos de metros (no usar espacios, ni el simbolo de metros). NO usar PUNTOS (ni comas) para indicar miles. Obtener este valor de la base de datos de goerreferenciacion de especimenes. Si no se cuentan con especímenes de la especie, usar el rango reportado en el Catálogo de Plantas de Colombia o una revisión taxonómica reciente. Si la especie solo se conoce de una sola ocurrencia, usar este campo para la elevacion conocida (redondeada a decenas de metros). Si no se tiene información del rango altitudinal para la especies, llenar la celda con N/A | AF2: Valor numérico de la elevación máxima donde se ha reportado la especie. Expresar el valor en metros (numero entero sin decimales), y emplear un número redondeado a cientos de metros (no usar espacios, ni el simbolo de metros). NO Usar PUNTOS (ni comas) para indicar miles. Obtener este valor de la base de datos de goerreferenciacion de especimenes. Si no se cuentan con especímenes de la especie, usar el rango reportado en el Catálogo de Plantas de Colombia o una revisión taxonómica reciente. Si la especie solo se conoce de una sola ocurrencia o si no se tiene informacion de su rango altitudinal, llenar la celda con N/A (El valor único conocido para elevación va en la columna anterior). | AG2: Código SIS (según las opciones del SIS, en inglés, tal cual como aparecen aca abajo) de la región biogeográfica a nivel global donde ocurre la especie. Opciones= Neotropical : es la opción para todas las especies en Colombia y alrededores Para ver otras opciones ir a http://connect.iucnredlist.org/sis_lookups/3502/findvalues | AH2: Descripción general de la distribución de la especie en Colombia (y en países vecinos si aplica). Basar esta descripción en el mapa producido por ConR (NO en el Catalogo de Plantas de Colombia, pues esta desactualizado). Campo de texto libre! Seguir el siguiente formato, incluyendo un punto final: [La especie es endémica de Colombia / La especie está presente en Colombia y en X, Z]. Se distribuye en la(s) región(es) X, Y, y Z [ de los Andes / de los Valles interandinos / del Pacífico / del Caribe / de la Amazonia / de la Orinoquia ]. Se ha registrado en el(los) departamento(s) de X, Y, Z. [Añadir más detalles si se conocen, por ejemplo que la especie es exclusiva de una cuenca, o de una región particular como el Darien o la Sierra Nevada de Santa Marta]. | AI2: Código SIS (según las opciones del SIS, en inglés, tal cual como aparecen aca abajo) sobre el mapa de distribución de la especie. Opciones= Done : esta debe ser la opcion para nuestras especies, ya que se hacen mapas para todas con ConR Missing : no hay mapa Incomplete : hay mapa incompleto Not possible : no se puede hacer mapa (esta opcion podria usarse en algunas de las especies declaradas DD) | AJ2: Código SIS (según las opciones del SIS, en inglés, tal cual como aparecen aca abajo) sobre si la especie es terrestre o acuática. Opciones= Terrestrial : la especie es terrestre Freshwater: la especie de es agua dulce Marine: la especie es marina | AK2: Código SIS (según las opciones del SIS, en inglés, tal cual como aparecen aca abajo) que describe si el hábitat reportado para la especie es un hábitat en donde las poblaciones biológicas se pueden establecer adecuadamente (diseñado sobretodo para animales). Opciones= Suitable : si el habitat que se le asignó a la especie es donde crecen la mayoría de sus subpoblaciones viables, debe ser nuestra opción para plantas Marginal : solo en casos en los que la especie sólo esté reportada en un hábitat en donde sus subpoblaciones no son viables Unknown : no se sabe si el hábitat reportado para la especie es adecuado o no para su establecieminto | AL2: Código SIS (sólo el número, entero o decimal) del hábitat de la especie (en caso de usar las opciones con decimales, usar el PUNTO como separador). Si la especie ocurre en varios hábitats, enumerar en ascendentemente y separar por coma y espacio. Por favor tener MUCHO cuidado con el uso de puntos y comas en este campo. No usar punto y coma. Opciones= 1.5 - Forest-Subtropical/Tropical Dry : para bosques secos 1.6 - Forest-Subtropical/Tropical Moist Lowland: para bosques humedos de tierras bajas (elevación < 1000 msnm) 1.7 - Forest - Subtropical/Tropical Mangrove Vegetation: para bosques de manglares 1.8 - Forest - Subtropical/Tropical Swamp: para bosques inundables (como cativales, etc) 1.9 - Forest - Subtropical/Tropical Moist Montane: para bosques de tierras altas (elevación > 1000 msnm) 2.1 - Savanna - Dry : para sabanas secas 2.2 -Savanna - Moist : para sabanas humedas 3.5 - Shrubland - Subtropical/Tropical Dry : para arbustales secos, zonas xericas 3 - Shrubland - Subtropical/Tropical Moist : para arbustales húmedos 3.7 - Shrubland - Subtropical/Tropical High Altitude : para arbustales en altitud (elevación > 1000 msnm) 4.5 - Grassland - Subtropical/Tropical Dry : para pastizales naturales secos (no pastos de ganadería) 4.6 - Grassland - Subtropical/Tropical Seasonally Wet/Flooded : para pastizales naturales húmedos (no pastos de ganadería) 4.7 - Grassland - Subtropical/Tropical High Altitude : para pastizales naturales de alta elevación, incluyendo páramos 6 - Rocky areas : para afloramientos rocosos, karsticos, tepuyes, etc. 8 - Desert : para desiertos 18 - Unknown : si no se sabe nada el hábitat Para otras opciones de hábitats ir a http://connect.iucnredlist.org/sis_classifications/131/findvalues | AM2: Descripción específica del hábitat principal de la especie. Campo de texto libre! Seguir el siguiente formato (incluyendo las citas o fuentes de información) e incluir un punto final: La especie ocurre en hábitats de [bosques humedos / bosques secos / paramos / sabanas / otro tipo de ecosistema general] en tierras [bajas (elevación menor a 1.000 m snm) / altas (elevación mayor a 1.000 m snm) / omitir esto si es paramos]. [agregar detalles conocidos, como si crece al borde de quebradas, en claros y borde de bosque, etc.]] | AN2: Descripción general de la información ecológica disponible para la especie. NO incluir acá información de abundancia o dinámica poblacional, esa información va en el campo del "Estado Poblacional" Campo de texto libre! Seguir el siguiente formato (incluyendo las citas o fuentes de información) e incluir un punto final: La especie es posiblemente polinizada por [insectos / vertebrados / viento] y dispersada por [gravedad / viento / insectos / vertebrados]. [Describir cualquier información que se reporte en literatura sobre la ecología de la especie, como asociaciones con microorganismos, fenología, etc.]. - Si no se puede decir nada de lo anterior para la especie, solo usar la siguiente oracion: No se cuenta con información publicada sobre la ecología de la especie. | AO2: Descripción combinada del hábitat y ecología de la especie. Campo de texto libre! Este campo se construye CONCATENANDO (funcion de excel) la información incluída en los campos de "Hábitat General" y "Ecología" (ya que en el SIS estos dos campos están unidos). | AP2: Definir el o los vectores de dispersión de semillas, según la información de literatura o expertos recopilada. Si son varios vectores, separar por coma y espacio. Si no se puede determinar el tipo de dispersion (pero se debe intentar!), llenar la ceda con N/A Opciones= Gravedad : dispersión principal por gravedad. Viento con corta dispersión : dispersión por viento limitadas (menos de 10 metros), como para muchas orquídeas Invertebrados : dispersión principal por insectos u otros invertebrados. Vertebrados de poca movilidad : dispersión principal por animales que no vuelan. Vertebrados de gran movilidad : dispersión principal por animales que vuelan (aves, murciélagos, etc.) Viento : dispersión principal por viento a grandes distancias. | AQ2: Comentarios a la dispersión. Campo de texto libre. Describir la fuente de donde se obtuvo el tipo de vector de dispersión, o decir si el tipo de dispersión fue inferida, y describir detalles conocidos de la dispersión. | AR2: Asignar la distancia MAXIMA de dispersión de la especie (sólo el valor numérico entero, que son km), según los vectores que se reportaron. Este valor se usará para determinar si existe "fragmentación severa" para el hábitat (con el % de parches de hábitat que son pequeños y aislados). Si no se puede determinar el tipo de dispersion (pero se debe intentar!), llenar la ceda con N/A Opciones: 5 : Si la dispersión es por GRAVEDAD 10 : Si la dispersión es por INVERTEBRADOS o VIENTO DE CORTA DISPERSIÓN 15 : Si la dispersión es por VERTEBRADOS DE POCA MOVILIDAD (como mamíferos pequeños no voladores) 25 : Si la dispersión es por VERTEBRADOS DE GRAN MOVILIDAD (como aves, murciélagos, mamiferos grandes) 50 : Si la dispersión es por VIENTO | AS2: Asignar el tamaño MAXIMO de un parche de hábitat que se considera PEQUEÑO para la especie (sólo el valor numérico entero, que son hectáreas), según lo que se discuta con expertos. Este valor se usará para determinar si existe "fragmentación severa" para el hábitat (con el % de parches de hábitat que son pequeños y aislados) Opciones: 500 : para especies de árboles y arbustos 150 : para especies de hierbas, epífitas, o plantas pequeñas. | AT2: Nombre de la especie, sin el autor (para poderla ubicar fácilmente en el archivo). | AW2: Estimado de ConR (valor numérico entero, sin decimales). No usar puntos ni comas para indicar miles. Si no se calculó (porque hay menos de tres ocurrencias o alguna otra razón) llenar la celda con N/A | AX2: Estimado de ConR (valor numérico entero, sin decimales). No usar puntos ni comas para indicar miles. SI se decide que para la evaluación el AOO NO se va a utilizar, entonces ignorar el estimado de ConR y llenar la celda con N/A | AY2: Estimado de ConR (valor numérico entero, sin decimales). Si no se cuenta con esta información, llenar la celda con N/A | AZ2: Estimado de ConR (valor numérico entero, sin decimales). SI la especie NO presenta amenazas (NO hay disminución continua en el hábitat), entonces NO se deben definir localidades, se debe ignorar el estimado de ConR y llenar la celda con N/A Si por alguna otra razón no se cuenta con esta información, llenar la celda con N/A | BA2: Estimado de ConR (valor numérico entero, sin decimales). NO poner el signo "%" Si no se cuenta con esta información, llenar la celda con N/A | BB2: Estimado del Código R del GEPC (valor numérico entero, sin decimales). NO poner el signo "%" Si no se cuenta con esta información, llenar la celda con N/A | BC2: Estimado del Código R del GEPC (valor numérico entero, sin decimales). NO poner el signo "%" Si no se cuenta con esta información, llenar la celda con N/A | BD2: Estimado del Código R del GEPC, el reporte debe ser SI ó NO, según si se proponen subpoblaciones desaparecidas. | BE2: Código SIS (según las opciones del SIS de YES/NO/Unknown) para reportar si la especie presenta "fragmentación severa". Se declará una especie con fragmentación severa si el % subpoblaciones en parches de hábitat pequeños y aislados es mayor al 50% (este porcentaje es según los lineamientos de la IUCN, no se puede cambiar), según los análisis de hábitat realizados con el Código R del GEPC. Opciones= YES : si hay fragmentación severa NO : no hay fragmentación severa Unknown : no se sabe si hay fragmentación severa | BF2: Si el Código R del GEPC determina que SI hay fragmentación severa en el hábitat, llenar esta celda. Si no hay fragmentación severa en el hábitat, llenar la celda con N/A SI hay fragmentación severa en el hábitat, seguir el siguiente formato para describirla: El [X]% de parches de hábitat donde se encuentra la especie son pequeños y aislados. Estos parches se encuentran en el/los Municipio(s) de [X] (departamento de [Y]) y [W] (departamento de [Z]). | BG2: Código SIS (según las opciones del SIS de YES/NO/Unknown) para reportar si la especie tiene "disminución continua" ESPECÍFICAMENTE por disminución de la cantidad/calidad del HÁBITAT. Se declara una especie con "disminución continua en el hábitat" si el % de huella humana es mayor o igual al 40% (o el porcentaje que defina el equipo del proyecto), según los análisis de hábitat realizados con el Código R del GEPC. Opciones= YES : si hay disminución continua en la calidad del hábitat NO : no hay disminución continua en la calidad del hábitat Unknown: no se sabe si hay disminución continua en la calidad del hábitat | BH2: Si se declaró en la columna anteror que SI hay disminución continua en el hábitat, llenar esta celda. Si no hay disminución continua en el hábitat, llenar la celda con N/A Si la especie no alcanza el umbral pero tiene amenazas en algunas subpoblaciones, incluir esta información en la columna de observaciones y llenar la celda con N/A SI hay disminución continua en el hábitat, seguir el siguiente formato para describirla: [X= número o en letras si son entre 1 y 10] subpoblaciones de la especie se encuentran en paisajes con destrucción y degradación de su hábitat. Estas subpoblaciones se encuentran en el/los Municipio(s) de [X] (departamento de [Y]) y W (departamento de [Z]). | BI2: Código SIS para reportar de donde se obtuvo la información para declarar disminución continua en hábitat. Si no existe dismincuión continua en el habitat, llenar la celda con N/A Opciones= -Inferred : cuando se infirió la disminución continua con base en analisis espaciales del habitat (que es lo que hacemos con el código del GEPC). Esta es la opción que usaremos siempre, a menos de que exista un estudio publicado que haga lo que se describe en las siguientes opciones -Observed : cuando la información es basada directamente en observaciones de las subpoblaciones -Estimated : cuando la information es basada sobre cálculos estadísticos a partir de muestreos o supuestos biológicos entre la relación previamente observada entre una variable observada (abundancia) y una variable de interés (e.g., numero de individuos maduros). -Projected : similar a "estimated”, pero la variable de interés es extrapolada o proyectada en tiempo y espacio hacia el futuro. Los métodos de extrapolación deben discutirse y justificarse | BJ2: Código SIS (según las opciones del SIS de YES/NO/Unknown) para reportar si la especie tiene "disminución continua" ESPECÍFICAMENTE por disminución del # SUBPOBLACIONES. Se declara una especie con "disminución continua en el # subpoblaciones", si según los análisis de hábitat realizados con el Código R del GEPC se determinó que al menos una subpoblación ya desapareció por destrucción completa de tu hábitat. Opciones= YES : si hay disminución continua en # subpoblaciones NO : no hay disminución continua en # subpoblaciones Unknown: no se sabe si hay disminución continua en # subpoblaciones | BK2: Si se declaró en la columna anteror que SI hay disminución continua en el # subpoblaciones, llenar esta celda. Si no hay disminución continua en el # subpoblaciones, llenar la celda con N/A SI hay disminución continua en el # subpoblaciones, seguir el siguiente formato para describirla: Es posible que la(s) subpoblación(es) de la(s) localidad(es) [W] del/de los Municipio(s) de [X] (departamento de [Y]) haya(n) desaparecido por la destrucción de su hábitat. | BL2: Código SIS para reportar de donde se obtuvo la informacion para la disminucion continua en # subpoblaciones. Si no existe disminucion continua en las subpoblaciones llenar la celda con N/A. Opciones= -Inferred : cuando se infirió la disminución continua con base en analisis espaciales del habitat (que es lo que hacemos con el código del GEPC). Esta es la opción que usaremos siempre, a menos de que exista un estudio publicado que haga lo que se describe en las siguientes opciones -Observed : cuando la información es basada directamente en observaciones de las subpoblaciones -Estimated : cuando la information es basada sobre cálculos estadísticos a partir de muestreos o supuestos biológicos entre la relación previamente observada entre una variable observada (abundancia) y una variable de interés (e.g., numero de individuos maduros). -Projected : similar a "estimated”, pero la variable de interés es extrapolada o proyectada en tiempo y espacio hacia el futuro. Los métodos de extrapolación deben discutirse y justificarse | BM2: Descripción del tamaño poblacional y lo que se conozca de la demografía de la especie. Campo de texto libre! Seguir el siguiente formato (incluyendo las citas o fuentes de información) e incluir un punto final: - SI para la especie se conoce algo sobre demografía, es decir parámetros de abundancia de adultos, estructura poblacional (% de plántulas, juveniles, adultos) y/o dinámica de la población (tasa de crecimiento poblacional): La especie tiene registradas hasta el momento [X= número o en letras si son entre 1 y 10] subpoblaciones. [Describir con detalle lo que se conoce sobre la especie, con citas]. - SI para la especie no hay literatura sobre demografía, entonces usar el siguiente formato (según parámetros estimados con ConR): La especie tiene registradas hasta el momento [X= número o en letras si son entre 1 y 10] subpoblaciones. No se conoce nada sobre la abundancia o tendencia poblacional de la especie. | BN2: Descripción detallada de las amenazas actuales (en el presente o en los últimos 10 años, o hasta 25 años para especies muy longevas) sobre las subpoblaciones de la especie y sus hábitats. Si se conoce de amenazas que ocurrieron en el pasado (hace mas de 10-25 años) y que ya no son vigentes, se debe especificar cuando ocurrieron esas amenazas y que ya no existen (esto sería si se tiene reportes de literatura o expertos). Si existe evidencia concreta de que puede haber una amenaza en el futuro cercano (próximos 10 años), especifique que es una potencial amenaza en el futuro (por ejemplo si se sabe que se va a construir un embalse o un centro poblado se está expandiendo al hábitat donde está una subpoblación). Para describir las causas de la destrucción y degradación del hábitat, especificar la actividad humana. Por ejemplo, si la causa es la "ampliación de la frontera agropecuaria", especificar si es para ganadería y/o para cultivos, sin demasidado detalles (no es necesario decir que tipo de cultivos, a menos que sea un fenómeno muy relevante como cultivos de palma de aceite a gran escala). En otros ejemplos, si la causa es la "minería", especificar si es minería de metales o de hidrocarburos; si la causa es la "construcción de infraestructura", especificar sin es la construcción/ampliación de centros poblados, de vías, etc. Campo de texto libre! Seguir el siguiente formato (incluyendo las citas o fuentes de información) e incluir un punto final: - Si la especie SI tiene disminución continua en el hábitat: [X de las Y= números o en letras sin son entre 1 y 10 / Todas las] subpoblaciones conocidas de la especie se encuentran en sitios con destrucción y degradación de su hábitat. Las alteraciones del hábitat se deben principalmente a [la ampliación de la frontera agropecuaria (para ganaderia y/o para cultivos) / la mineria (de metales y/o de hidrocarburos) / la construcción de infraestructura (embalses, vias, centros poblados) / las plantaciones forestales / otra causa]. - Si la especie es sobreexplotada (para comercialización, pues normalmente usos de subsistencia no son tan drásticos como para representar amenazas), usar o agregar la siguiente oración: Las subpoblaciones conocidas de la especie están amenazadas por la extracción no sostenible de individuos por su uso como [maderable / medicinal / ornamental / otro]. - Si la especie NO tiene disminución continua en el hábitat y por tanto no tiene amenazas importantes (a menos de que sea sobrexplotada): Las subpoblaciones conocidas de la especie se encuentran en hábitats poco perturbados por actividades humanas. -Si la especie es categorizada como DD: No existe información disponible sobre amenazas para esta especie. | BO2: Código SIS (sólo el número decimal) de las amenazas para la especie (usar el PUNTO como separador del decimal). Si la especie tiene varias amenazas, separar por COMA y espacio. Por favor tener mucho cuidado con el uso de puntos y comas en este campo. Si la especie NO tiene amenazas, llenar la celda con N/A Opciones= 1.1 - Housing & urban areas : destrucción de hábitat por urbanización. 1.2 - Commercial & industrial areas : destrucción de hábitat por actividades industriales urbanas. 1.3 - Tourism & recreation areas : destrucción de hábitat por actividades de recreación. 2.1.4 - Annual & perennial non-timber crops / Scale unrecorded : destrucción de hábitat por cultivos. 2.2.3 - Wood & pulp plantations / Scale unrecorded : destrucción de hábitat por plantaciones forestales. 2.3.4 - Livestock farming & ranching / Scale unrecorded : destrucción de hábitat por ganadería. 3.1 - Oil & gas drilling : destrucción de hábitat por minería de hidrocarburos (petróleo y/o gas). 3.2 - Mining & quarrying : destrucción de hábitat por minería de metales y/o piedras. 4.1 -Roads & railroads : destrucción de hábitat por construcción de vías (carreteras, ferrocarriles, etc). 5.2.1 - Gathering terrestrial plants / Intentional use : sobreexplotación por uso directo de los individuos o sus partes. 5.2.2. - Gathering terrestrial plants / Unintentional effects : sobreexplotación producto de actividades no dirigidas a la especie. 5.3.2 - Logging & wood harvesting / Intentional use at large scale : sobreexplotación por uso directo como maderable, leña o pulpa. 7.2.11 - Dams & water management/use / Dams size unknown : destrucción de hábitat por construcción de embalses. 8.1.1 - Invasive non-native/alien species/diseases / Unspecified species : degradación por especies invasoras o exóticas. 9.1.3 - Domestic & urban waste water / Unknown : contaminación por aguas negras domésticas o urbanas. 9.2.3 - Industrial & military effluents / Unknown : contaminación por efluentes industriales. 9.3.4 - Agricultural & forestry effluents / Unknown : contaminación por agroquímicos. 9.4 - Garbage & solid waste : contaminación por residuos sólidos. 11.1 - Climate change / Habitat shifting and alteration : cambios en la distribución o alteraciones del hábitat por efectos directos de cambio climático. 11.2 - Climate change / Droughts : degradación directa de los individuos por sequía producida directamente por cambio climático. 12.1 - Other threats : otras amenazas que no se puedan describir con los codigos disponibles. Para ver otros códigos de amenazas ir a http://connect.iucnredlist.org/sis_classifications/139/findvalues | BP2: Código SIS (según las opciones del SIS, en inglés, tal cual como aparecen aca abajo) para reportar el TIEMPO en que ocurren cada una de las amenazas. Si la especie presenta "disminución continua del hábitat" (según el estimado del % de huella humana), asumimos que las amenazas son actuales. Para declarar que una amenaza es pasada o futura debemos tener literatura a citar para respaldar esto. DEBE haber un código (palabra) para CADA UNA de las amenazas declaradas (cómo números) para la especie. Los códigos (palabras) en este campo se separan por comas. Si la especie NO tiene amenazas declaradas, llenar la celda con N/A Opciones= Ongoing : amenazas en el presente, esta debe ser la opción si la especie SI presenta disminución continua del hábitat Past, Unlikely to return : si se conocen amenazas que en el pasado afectaron la especie y no pueden recurrir Past, Likely to return : si se conocen amenazas que en el pasado afectaron la especie y pueden recurrir Future : si se conocen amenazas que podrían afectar a la especie en un futuro cercano (próximos 10 años o una generación) Unknown : NO se conoce si las amenazas son pasadas o están ocurriendo en el presente | BQ2: Código SIS (según las opciones del SIS, en inglés, tal cual como aparecen aca abajo) para reportar el ALCANCE de cada una de las amenazas. Para determinar el alcance de la amenaza, usar el análisis realizado para llenar el campo de descripción de la "disminución continua del hábitat", en donde se especfica cuantas subpoblaciones están afectadas por destrucción y degradación del hábitat. Si la especie sufre de la amenaza de sobreexplotación, se debe hacer un estimado de cuantas o si todas las subpoblaciones de la especie son explotadas. DEBE haber un código (palabra) para CADA UNA de las amenazas declaradas (cómo números) para la especie. Los códigos (palabras) en este campo se separan por comas. Si la especie NO tiene amenazas declaradas, llenar la celda con N/A Opciones= Whole (>90%): más del 90% de las subpoblaciones sufren de esta amenaza Majority (50-90%) : entre el 50 y el 90% de las subpoblaciones sufren de esta amenaza Minority (<50%) : menos del 50% de las subpoblaciones sufren de esta amenaza Unknown : NO se conoce el alcance de las amenazas | BR2: Código SIS (según las opciones del SIS, en inglés, tal cual como aparecen aca abajo) para reportar la SEVERIDAD de cada una de las amenazas. Si la especie presenta "disminución continua del hábitat", asumimos que las amenazas son muy severas ("Very rapid declines"), pues lo adultos desaparecen al destruir o degradar drásticamente el hábitat. Si la especie presenta sobreexplotación, se puede asumir que la severidad es menor ("Rapid declines"), pues generalmente no se extraen todos los adultos de una subpoblación (a menos de que haya evidencia de lo contrario). DEBE haber un código (palabra) para CADA UNA de las amenazas declaradas (cómo números) para la especie. Los códigos (palabras) en este campo se separan por comas. Si la especie NO tiene amenazas declaradas, llenar la celda con N/A. En el caso de amenazas por sobreexplotación se requiere información sobre el número de individuos adultos y la frecuencia si no se tiene esta información usar la opción "unknown". Opciones= Very rapid declines : la amenaza causa declives muy rápidos en el # adultos de las subpoblaciones (esta opción es la más común para nosotros). Rapid declines: la amenaza causa declives rápidos en el # adultos de las subpoblaciones. Slow, Significant declines: la amenaza causa declives en el # adultos en las subpoblaciones de manera drástica, pero lenta Causing/Could cause fluctuations : la amenaza causa fluctuaciones en el # adultos en las subpoblaciones Negligible declines : la amenaza causa declives leves en el # adultos en las subpoblaciones No decline : la amenaza no causa desaparición de adultos en las subpoblaciones Unknown : NO se conoce las amenazas | BS2: Código SIS (sólo el número decimal) de las PRESIONES de cada amenaza para la especie (usar el PUNTO como separador del decimal). Las presiones son los procesos ecológicos que resultan de las acciones humanas (que son las amenazas) y que afectan de manera negativa las subpoblaciones de la especie. OJO: una amenaza puede generar VARIAS presiones y las presiones se deben repotar en estricto orden para cada amenaza declarada en campo "Código SIS Amenazas". Para las especies con "disminución continua del hábitat", las amenazas corresponden con destrucción/degradación del hábitat y siempre se deben usar los siguientes códigos de las presiones: 1.1 | 1.2 | 2.1 | 2.2 Si la especie sólo presenta amenaza por sobreexplotación siempre se deben usar los siguientes códigos de las presiones: 2.1 | 2.2 Si existen otras amenazas (reportadas por expertos o la literatura) se podrían usar otros códigos de las presiones. Si la especie NO tiene amenazas declaradas, llenar la celda con N/A OJO: cada amenaza puede tener una o varias presiones. Si una amenaza tiene mas de una presión, los códigos de presiones se separan con una barra vertical "|" La o las presiones de cada amenaza se separan usando una doble barra diagnoal "//" Por ejemplo, si la especie tienen dos amenazas reportadas, la primera con cuatro presiones y la segunda con dos presiones el campo quedaría así: 1.1 | 1.2 | 2.1 | 2.2 // 2.1 | 2.2 Opciones= 1.1 = Ecosystem conversion = Destrucción de hábitats 1.2 = Ecosystem degradation = Degradación de hábitats 1.3 = Indirect ecosystem effects = otros efectos indirectos (esta opción no la usamos) 2.1 = Species mortality = Mortalidad de adultos en las subpoblaciones 2.2 = Species disturbance = Cambios en fenologia, disminución de supervivencia y/o fecundidad, etc. en las subpoblaciones 2.3.1 = Indirect effects-Hybridisation = degradación de subpoblaciones por hibridación con otras especies 2.3.2 = Indirect effects-Competition = degradación de subpoblaciones por competencia con otras especies 2.3.3 = Indirect effects-Loss of mutualism = degradación de subpoblaciones por pérdida de especies mutualistas 2.3.4 = Indirect effects-Loss of pollinator = degradación de subpoblaciones por pérdida de polinizadores específicamente 2.3.5 = Indirect effects-Inbreeding = degradación de subpoblaciones por efectos de la depresión por endogamia 2.3.6 = Indirect effects-Skewed sex ratios = degradación de subpoblaciones por sesgos en la relación de sexos 2.3.7 = Indirect effects-Reduced reproductive success = degradación de subpoblaciones por pérdida de fecunidad por causas concretas | BT2: Declarar (según las opciones del SIS de TRUE/FALSE) si la especie parece NO tener amenazas. Opciones= TRUE : Si para la especie NO se conoce ninguna amenaza (NO tenia disminución continua del hábitat o sobreexplotación) FALSE : SI se conocen amenazas para la especie, y fueron declaradas en el campo de "Código SIS Amenazas". | BU2: Declarar (según las opciones del SIS de TRUE/FALSE) si la especie SI tiene amenazas PERO NO SE SABE cuales son estas amenazas. Si la especie NO tiene amenazas, llenar la celda con N/A Opciones= TRUE : Si se asume que la especie SI tiene amenazas PERO NO SE SABE NADA sobre estas amenazas. FALSE : SI se conocen las amenazas para la especie, y fueron declaradas en el campo de "Código SIS Amenazas". | BV2: Código SIS (según las opciones del SIS, en inglés, tal cual como aparecen aca abajo) sobre la tendencia actual en el tamaño de la población total (puede ser inferida de "disminución continua del hábitat"). No diligenciar en casos de especies con categorias EX ó EW Opciones= Stable : si la especie NO tiene disminución continua y NO tiene otras amenazas (no debe ser una especie amenazada) Decreasing : si la especie SI tiene disminución continua en el hábitat, ó si hay reportes de que la población está disminuyendo por sobreexplotación u otra causa Increasing : sólo si existe información el la literatura de que la especie está incrementando su tamaño poblacional Unknown : si no se pudo realizar análisis de hábitat o no se sabe nada para la especie | BW2: Código SIS (según las opciones del SIS, en inglés, tal cual como aparecen aca abajo) para reportar si la tendencia en la población fué inferida, observada, etc. Opciones= Unknown : si la tendencia de la población la declaramos desconocida en el campo anterior Inferred : si inferimos la tendencia según la presencia de disminución continua en el hábitat (u otra variable proxy de la abundancia poblacional). Será la opcion en nuestras evalaciones (a menos de ya haya literatura para soportar alguna de las opciones siguientes) Observed : si para la especie hay reportes de expertos o literatura sobre la tendencia poblacional Estimated : sólo si se tiene modelos estadísticos para la tendencia poblacional Suspected : sólo si un experto dio su opinión pero no hay evidencia concreta Not Applicable : si no se sabe cómo se obtuvo la información de la tendencia poblacional | BX2: Describir las acciones de conservación conocidas para la especie en la actualidad (no incluir acciones que fueron ejecutadas hace más de 10 años, pues es posible que no tengan impacto sobre la especie en este momento). Estas pueden ser acciones de conservación in-situ (según el análisis de ConR de presencia en áreas protegidas), conservación ex-situ (si se tiene registro de que la especie esta en colecciones), o acciones de restauración (reintroducciones, etc), programas de uso sostenible, educación, etc. que estén reportadas por expertos o en literatura. Si para la especie no existe nada reportado en es tema en literatura, por lo menos se puede describir su presencia o no en áreas protegidas. En cuanto a presencia en áreas protegidas, hay que tener en cuenta que la especie si esta bien protegida si tiene subpoblaciones en figuras fuertes (que con Parques Nacionales y Regionales, Santuarios y otros pocos). Si la especie tiene presencia en áreas protegidas, pero TODAS las áreas son de figuras débiles, eso lo vamos a resaltar (las áreas con figuras débiles son los Distritos de Manejo Integrado, Reservas Forestales, Areas de Conservacion de Suelos, sean nacionales o regionales): Campo de texto libre! Seguir el siguiente formato (incluyendo las citas o fuentes de información) e incluir un punto final: - Si la especie SI tiene subpoblaciones dentro de áreas protegidas (en al menos un PNN o figura fuerte de conservación): La especie está presente en áreas del "Sistema Nacional de Áreas Protegidas". [Si las hay, listar las acciones de presencia en colecciones vivas, planes de manejo para uso sostenible, etc.]. No se conocen otras acciones de conservación para la especie. Tener en cuenta las siguientes variaciones: - Si el 100% de las ocurrencias de la especie están dentro de áreas protegidas con figuras fuertes: Todas las subpoblaciones conocidas de la especie están dentro de áreas del "Sistema Nacional de Áreas Protegidas". [Si las hay, listar las acciones de presencia en colecciones vivas, planes de manejo para uso sostenible, etc.]. No se conocen otras acciones de conservación para la especie. - Si TODAS las subpoblaciones que están en áreas protegidas están en áreas con figuras débiles de protección: [La especie / Todas las subpoblaciones conocidas de la especie] está(n) presente(s) en áreas del "Sistema Nacional de Áreas Protegidas"; sin embargo, las subpoblaciones se encuentran en áreas bajo figuras legales que son poco efectivas para la conservación de la biodiversidad. [Si las hay, listar las acciones de presencia en colecciones vivas, planes de manejo para uso sostenible, etc.]. No se conocen otras acciones de conservación para la especie. - Si la especie NO tiene subpoblaciones dentro de áreas protegidas: La especie no está presente en áreas del "Sistema Nacional de Áreas Protegidas". [Si las hay, listar las acciones de presencia en colecciones vivas, planes de manejo para uso sostenible, etc.]. [No se conocen acciones de conservación para la especie / No se conocen otras acciones de conservación para la especie - si tenia acciones de presencia en colecciones u otras-]. | BY2: Declarar (según las opciones del SIS de YES/NO/Unknown) si la especie está presente en áreas protegidas (según lo consignado en el campo de "Descripción de acciones de conservación"). Opciones= YES : la especie SI está presente dentro de áreas protegidas NO : la especie NO está presente dentro de áreas protegidas Unknown : no se sabe si la especie está presente dentro de áreas protegidas | BZ2: Listar las áreas protegidas públicas (no reservas privadas) de nivel nacional o regional donde haya ocurrencias de la especie. Si no se sabe si la especies está dentro de áreas protegidas, llenar la celda con N/A Campo de texto libre! Si la especie si tiene ocurrencias en áreas protegidas, listas las áreas con su nombre completo y su correspondiente categoría sin siglas (por ejemplo, Parque Nacional Natural [X]). Las áreas se deben separar por coma y espacio. La lista debe ir desde las figuras de área protegida más importante a la menos importante (primero las nacionales y luego las regionales, y primero los PNN, SFF, etc. y luego los DMI, Reservas Forestales, etc.) | CA2: Declarar (según las opciones del SIS de YES/NO/Unknown) si la especie está presente en colecciones vivas (según lo consignado en el campo de "Descripción de acciones de conservación"). Opciones= YES : la especie SI está presente en colecciones exsitu NO : la especie NO está presente en colecciones exsitu Unknown : no se sabe si la especie está presente en colecciones exsitu | CB2: Listar las colecciones vivas (jardines botánicos y otras) de nivel nacional o regional donde haya individuos de la especie. Si no se sabe si la especies está en colecciones vivas, llenar la celda con N/A Campo de texto libre! Si la especie está en colecciones, cada colección debe citarce con su nombre completo y su correspondiente categoría sin siglas (por ejemplo, Jardin Botánico [X]). Las distintas colecciones se deben separar por coma y un espacio. | CC2: Códigos SIS (los números decimales, usando PUNTO como separador) para declarar si se necesitan acciones de conservación para la especie. Si se necesitan varias acciones, separar por COMA y espacio. Por favor tener mucho cuidado con el uso de puntos y comas en este campo. SI la especie no tiene disminución continua en el hábitat y por ende NO está amenazada, entonces la especie NO necesita acciones de conservación y se llena esta celda con N/A Si la especie SI presenta disminución continua en el hábitat y SI está amenazada, entonces se declaran acciones de conservación requeridas. Se deben declarar siempre las opciones 1.1, 3.4.2, 4.3 y usar otras opciones según las recomendaciones a continuación. Opciones= 1.1 - Site/area protection : usar esta opción siempre si la especie está amenazada y las áreas protegidas donde tiene presencia la especie tienen figuras de áreas de conservación débiles i.e: DRMI 2.2 - Invasive/problematic species control : usar esta opción sólo si la especie está amenazada por la acción de especies invasoras o problemáticas 2.3 - Hábitat and natural process restoration : usar esta opción si la especie requiere de resturación de su hábitat, ya que está demasiado degradado (huella humana superior al 90%) 3.3.1 - Reintroduction : usar esta opción si se sabe que la especie está amenazada y tiene subpoblaciones muy pequeñas (menos de 250 adultos) 3.4.2 - Ex-situ conservation / Banco genético : usar esta opción siempre, si la especie está amenazada 4.3 - Awareness and communication : usar esta opción siempre, si la especie está amenazada Para ver otros códigos de acciones de conservación ir a http://connect.iucnredlist.org/sis_classifications/127/findvalues | CD2: Códigos SIS (los números decimales, usando PUNTO como separador) para declarar si se necesitan acciones de investigación para la especie. Si se necesitan varias acciones, separar por COMA y espacio. Por favor tener mucho cuidado con el uso de puntos y comas en este campo. SI la especie no tiene disminución continua en el hábitat y por ende NO está amenazada, entonces la especie NO necesita acciones de investigación y se llena esta celda con N/A Si la especie SI presenta disminución continua en el hábitat y SI está amenazada, entonces se declaran acciones de investigación requeridas. SI la especie está amenazada por destrucción/degradación de hábitat usar: 1.2, 1.3, 1.5, 1.6, 2.2, 3.1, 3.4 SI la especie tiene sobrexplotación ademas de la destrucción/degradación de hábitat, usar: 1.2, 1.3, 1.4, 1.5, 1.6, 2.1, 2.2, 2.3, 3.1, 3.2, 3.3, 3.4 SI la especie sólo tienen sobreexplotación y ninguna otra amenaza, usar: 1.4, 2.1, 2.3, 3.2, 3.3 Si la especie fue declarada DD, usar 1.2, 1.3, 1.5, 1.6 Opciones= 1.1 - Taxonomy : taxonomía (usar sólo si se sabe que la especie tiene problemas taxonómicos, no nomenclaturales) 1.2 - Population size, distribution & trends : tendencias en la distibución y abundancia de poblaciones 1.3 - Life history & ecology : ecología 1.4 - Harvest, use & livelihoods : uso de la especie 1.5 - Threats : amenazas, si no se sabe muy bien sobre ellas 1.6 - Actions : acciones de conservación, si no se sabe muy bien sobre ellas 2.1 - Species Action/Recovery Plan : plan de manejo para recuperar la especie 2.2 - Area-based Management Plan : plan de manejo de áreas donde la especie ocurre 2.3 - Harvest & Trade Management Plan : plan de manejo si la especie es usada 3.1 - Monitoring Population trends : monitoreo de tendencias poblacionales 3.2 - Monitoring Harvest & Trade Management Plan : monitoreo de plan de manejo 3.3 - Monitoring Trade trends : monitoreo de tendencias de uso 3.4 - Monitoring Habitat trends : monitoreo de tendencias en el hábitat Estas son todas las opciones para acciones de investigación. | CE2: Código SIS (sigla en mayúsculas) de la categoría de riesgo de extinción de la especie, que asignamos según los análisis realizados. Opciones= CR : En Peligro Crítico EN : En Peligro VU : Vulnerable NT : Casi amenzada LC : En Preocupación menor DD : Datos deficientes | CF2: SI la especie está amenazada o casi amenazada (categorías de CR/EN/VU/NT), entonces llenar esta celda, de lo contrario llenar la celda con N/A Códigos SIS (grupo de letras mayúsculas, minúsculas y números romanos) para la lista de los criterios, subcriterios y umbrales usados que la especie cumple para definir la categoría. Si son varios criterios se debe citar cada uno y separar por COMA (SIN espacio) y con sus respectivos subcrierios y umbrales. NO se deben usar paréntesis. Ejemplo: B1a,B1biii,B1biv Ejemplos B1a : si cumple con los valores de B1 y ademas la espeie tiene fragmenacion severa y/o menos de 10 localidades B1biii : si cumple con los valores de B1 y ademas la especie tiene disminucion continua en el habitat B1biv : si cumple con los valores de B1 y ademas la especie tiene disminucion continua en el # subpoblaciones | CG2: Declarar (según la opción del SIS) que se proporcionan los criterios de manera manual. Opciones= TRUE : siempre usar esta opción | CH2: Declarar (según las opciones del SIS) la version usada de los criterios de la IUCN. Usar PUNTO para el número decimal que se reporta. Opciones= 3.1 : siempre usar esta opción | CI2: SÓLO aplica para especies categorizadas en DD! Declarar la razón para categorizar las especie en DD. Si la especie no es DD, llenar la celda con N/A Opciones= -Provenance : Cuando la especie no se puede evaluar porque solo se conoce de uno o mas especímenes con extrema incertidumbre de la información de la localidad -Taxonomic : Cuando la especie no se puede evaluar porque no se sabe bien cuales son sus subpoblaciones por incertidumbre taxonómica. Esta opción no incluye taxones con problemas nomenclaturales, estos problemas se deben resolver según las indicaciones del GEPC. | CJ2: SÓLO para especies candidatas a EX! Declarar (según opciones del SIS de TRUE/NO) si la especie está extinta. Si la especie no es EX, llenar la celda con N/A Opciones= TRUE : la especie podria estar extinta NO : la especie no esta extinta | CK2: Descripción general de la justificación para la categorización de la especie. Acá se resumen todos los análisis que se realizaron para la especie, que son la evidencia que respalda la categoría asignada. Campo de texto libre! Seguir el siguiente formato (SIN incluir citas) e incluir un punto final: - Si la especie SI está amenazada: [Nombre de la especie] [es endémica de Colombia / se distribuye en Colombia, paisX y paisY]. La especie tiene [X= número o en letras si está entre 1 y 10] subpoblaciones registradas actualmente, [con una distribución geográfica restringida (EOO = X km2) -o no reportar esto si no tiene EOO-]. [X=número o en letras si está entre 1 y 10] de las [Y=número o en letras si está entre 1 y 10] subpoblaciones conocidas persisten en paisajes con destrucción y degradación de sus hábitats, principalmente por actividades de [X, Y y Z -citar las amenazas de manera general, sin sus causas-]. La especie exhibe [fragmentación severa / disminución continua de la cantidad y calidad del hábitat / disminución continua del número de subpoblaciones]. [Además, la especie es sobrexplotada para su uso como X -si aplica lo de sobreexplotación-]. [La especie tiene registros dentro de áreas protegidas / La especie no tiene registros dentro de áreas protegidas] y [tiene individuos en colecciones vivas / no tiene individuos en colecciones vivas]. Se considera que esta especie está en la categoría de ["en peligro crítico" / "en peligro" / "vulnerable"]. - Si la especie NO esta amenazada: [Nombre de la especie] [es endémica de Colombia / se distribuye en Colombia, paisX y paisY]. La especie tiene [X= número o en letras si está entre 1 y 10] subpoblaciones registradas actualmente, [con una distribución geográfica amplia (EOO = X km2) -o no reportar esto si no tiene EOO-]. Las subpoblaciones se encuentran en paisajes con poca perturbación por actividades humanas. [La especie tiene registros dentro de áreas protegidas / La especie no tiene registros dentro de áreas protegidas] y [tiene individuos en colecciones vivas / no tiene individuos en colecciones vivas]. Se considera que esta especie está en la categoría de ["casi amenazada" / "preocupación menor"]. [-Si la especie esta en NT, agregar la oracion- Se recomienda hacer monitoreo de las subpoblaciones para determinar si existe declive drástico de su abundancia poblacional]. - Si la especie es DD: [Nombre de la especie] [es endémica de Colombia / se distribuye en Colombia, paisX y paisY]. No existe información confiable de la distibución o la abundancia poblacional de la especie, por lo cual no se pueden estimar parámetros de riesgo de extinción. Se considera que esta especie está en la categoría de "deficiente de datos". | CL2: Fecha es que se realizó la evaluación (es decir cuando se asignó la categoría de riesgo): Formato: día/mes/año. Por ejemplo: 01/12/2020 | CM2: Código SIS (según las opciones del SIS, en inglés, tal cual como aparecen aca abajo) el lenguaje en que se redacta la evaluación. Opciones= Spanish; Castilian : se debe poner así, con las dos palabras separadas por el signo de punto y coma English French Portuguese | CN2: Listar las evaluaciones o sugerencias de evaluaciones (en artículos por ejemplo) de lista roja ya disponibles para la especie y la fuente. Si son varias evaluaciones, separarla por comas, citando la categoría, el año, los criterios y la fuente. Si no existen evaluaciones previas para la especie, llenar la celda con N/A | CO2: Explicación detallada de la justificación para las evaluaciones previas conocidas para la especie, descritas en el campo anterior. Campo de texto libre! Si no existen evaluaciones previas para la especie, llenar la celda con N/A | CP2: Declarar si la especie ya tiene una evaluación previa Y PUBLICADA en la pagina web de la Lista Roja Global. Si la espeice NO tienen evaluación ya publicada en esta página web, llenar la celda con N/A Campo de texto libre! Seguir el siguiente formato e incluir un punto final. | CQ2: SOLO si la especie tiene una evaluación publicada en la página web de la Lista Roja Global: Describir si la especie permanece en la misma categoría (al comparar con la evaluación de este proyecto) o si cambia de categoría. Si cambia de categoría, describir las razones del cambio (si se tiene información adicional de subpoblaciones, se conocen mejor las amenazas o aparecieron nuevas amenazas, etc.) Si la especie NO ha sido publicada en la Lista Roja Globa, llenar la celda con N/A Este es un campo de texto libre! Seguir el siguiente formato e incluir un punto final: La especie fue evaluada como [sigla de la categoria] en el año [XXXX] por [autor(es)]. En esta evaluación se usaron los criterios [incluir criterios] de la versión 3.1 [o la versión que usaron] de los lineamientos de la UICN. La especie [cambió / no cambió] de categoría de riesgo de extinción porque [explicación de la razones del cambio]. | CR2: SOLO si la especie tiene una evaluación publicada en la página web de la Lista Roja Global: usar el Código SIS (según las opciones del SIS, en inglés, tal cual como aparecen aca abajo) para el tipo de cambio en la categorización. Si la especie NO ha sido publicada en la Lista Roja Globa, llenar la celda con N/A Opciones= -Genuine Change : la especie cambio de categoria debido al efecto real de cambio en las amenazas o acciones de conservación -Non Genuine Change : la especie cambio de categoria por cambios taxonómicos o aumento en la información disponible (no por amenazas o acciones de conservación) -No Change : la especie no cambió de categoria | CS2: SOLO si la especie tiene una evaluación publicada en la página web de la Lista Roja Global y ADEMÁS en el campo de "Código SIS Tipo de cambio de categoría" se declaró "No Cambio" ("No Change"): Código SIS (según las opciones del SIS, en inglés, tal cual como aparecen aca abajo) de las razones de NO CAMBIO de la categoría. Si la especie NO ha sido publicada en la Lista Roja Globa o si no se declaró la opción de "No Change" en el campo anterior, llenar la celda con N/A Opciones = - Same category and criteria : los criterios son iguales entre las dos evaluaciones (y de la version 3.1!) - Same category but change in criteria : los criterios cambiaron (aunque la especie quedo en la misma categoria) | CT2: SOLO si la especie tiene una evaluación publicada en la página web de la Lista Roja Global y ADEMÁS en el campo de "Código SIS Tipo de cambio de categoría" se declaró que hubo cambios "genuinos" o "no genuinos": Código SIS (según las opciones del SIS, en inglés, tal cual como aparecen aca abajo) de las razones de CAMBIO de la categoría. Si la especie NO ha sido publicada en la Lista Roja Globa o si se declaro con la opcion "No Change", llenar la celda con N/A - Para "Cambios No Genuinos" ("Non Genuine Change") las opciones son: New information, Knowledge of criteria, Incorrect data used previously, Taxonomy, Criteria revision, Other - Para "Cambios Genuinos" ("Genuine Change") las opciones son: Recent, Since first assessment | CU2: Nombres y Apellidos de las personas que participaron activamente en la recolección de información y/o estimación de parámetros de la evaluación (si la persona sólo se contrató para georreferenciar o alguna tarea técnica y no participó en ningún otro aspecto de la evaluación NO se debe incluir). Los nombres y apellidos deben ir SIN PUNTOS (como la persona quiere ser citada) y las personas deben ir separadas por COMAS y espacio. Si no hay personas contribuyentes, llenar la celda con N/A MIRAR LAS INSTRUCCIONES EN LA PESTAÑA "README" SOBRE MANEJO DE LOS CONTRIBUYENTES/EVALUADORES/REVISORES. | CV2: Lista de los Herbarios que contribuyen con información para la evaluación de la especie. TODOS los herbarios quedarán en una sóla entrada (como si fueran un solo contribuyente), y se usaran sus SIGLAS (no los nombres completos). NO deben ir COMAS entre las siglas de los Herbarios. Si no hay Herbarios contribuyentes, llenar la celda con N/A Es un campo de texto libre! Se debe usar el formato "Herbarios X Y Z" MIRAR LAS INSTRUCCIONES EN LA PESTAÑA "README" SOBRE MANEJO DE LOS CONTRIBUYENTES/EVALUADORES/REVISORES. | CW2: Nombres y Apellidos de las personas que participaron activamente en la evaluación y finalmente determinaron la categoria de Lista Roja para la especie. Los nombres y apellidos deben ir SIN PUNTOS (como la persona quiere ser citada) y las personas deben ir separadas por COMAS y espacio. Siempre debe haber por lo menos una persona evaluadora. MIRAR LAS INSTRUCCIONES EN LA PESTAÑA "README" SOBRE MANEJO DE LOS CONTRIBUYENTES/EVALUADORES/REVISORES. | CX2: Nombres y Apellidos de las personas que participaron activamente en REVISIÓN de la evaluación (estos revisores son asignados por el GEPC y/o la UICN). Los nombres y apellidos deben ir SIN PUNTOS (como la persona quiere ser citada) y las personas deben ir separadas por COMAS y espacio. Simpre debe haber por lo menos una persona revisora. MIRAR LAS INSTRUCCIONES EN LA PESTAÑA "README" SOBRE MANEJO DE LOS CONTRIBUYENTES/EVALUADORES/REVISORES. | CY2: Nombres y Apellidos de las personas que participaron activamente como "expertos de la especie" (taxónom@s, ecólog@s, etc.) y que realizaron sugerencias importantes para la evaluación (como revisión de las ocurrencias, revisión de los mapas con EOO, AOO, aportes a las amenazas, etc.). Los nombres y apellidos deben ir SIN PUNTOS (como la persona quiere ser citada) y las personas deben ir separadas por COMAS y espacio. Si no hay expertos que revisaron las evaluaciones, llenar la celda con N/A MIRAR LAS INSTRUCCIONES EN LA PESTAÑA "README" SOBRE MANEJO DE LOS CONTRIBUYENTES/EVALUADORES/REVISORES. | CZ2: Descripción detallada de los comentarios que los expertos hagan sobre la evaluación de la especie. Si no hay comentarios, llenar la celda con N/A Campo de texto libre! | DA2: MIRAR LAS INSTRUCCIONES EN LA PESTAÑA "README" SOBRE MANEJO DE LAS REFERENCIAS BIBLOGRÁFICAS. | DB2: Información adicional sobre la especie o sobre la evaluación de lista roja.
A3: GEPC | B3: internal_taxon_id | C3: kingdom | D3: phylum | E3: classname | F3: ordername | G3: family | H3: genus | I3: species | J3: taxonomicAuthority | K3: GEPC | L3: GEPC | M3: GEPC | N3: name | O3: speciesName | P3: speciesAuthor | Q3: name | R3: language | S3: primary | T3: UTEndUse.UTEndUseSubfield.UTEndUseLookup | U3: NotUtilized.isNotUtilized | V3: UseTradeDocumentation.value | W3: NonConsumptiveUse.isNonConsumptiveUse | X3: PlantGrowthForms.PlantGrowthFormsSubfield.PlantGrowthFormsLookup | Y3: Plantgrowthforms.plantgrowthformssubfield.plantgrowthformsname | Z3: IdentificationDescription.text | AA3: CountryOccurrence.CountryOccurrenceSubfield.CountryOccurrenceLookup | AB3: CountryOccurrence.CountryOccurrenceSubfield.CountryOccurrenceName | AC3: CountryOccurrence.CountryOccurrenceSubfield.origin | AD3: CountryOccurrence.CountryOccurrenceSubfield.presence | AE3: ElevationLower.limit | AF3: ElevationUpper.limit | AG3: BiogeographicRealm.realm | AH3: RangeDocumentation.narrative | AI3: MapStatus.status | AJ3: System.value | AK3: GeneralHabitats.GeneralHabitatsSubfield.suitability | AL3: GeneralHabitats.GeneralHabitatsSubfield.GeneralHabitatsLookup | AM3: GEPC | AN3: GEPC | AO3: HabitatDocumentation.narrative | AP3: GEPC | AQ3: GEPC | AR3: GEPC | AS3: GEPC | AT3: GEPC | AW3: EOO.range | AX3: AOO.range | AY3: SubpopulationNumber.range | AZ3: LocationsNumber.range | BA3: GEPC | BB3: GEPC | BC3: GEPC | BD3: GEPC | BE3: SevereFragmentation.isFragmented | BF3: SevereFragmentation.justification | BG3: HabitatContinuingDecline.isDeclining | BH3: HabitatContinuingDecline.justification | BI3: HabitatContinuingDecline.qualifier | BJ3: SubpopulationContinuingDecline.isDeclining | BK3: SubpopulationContinuingDecline.justification | BL3: SubpopulationContinuingDecline.qualifier | BM3: PopulationDocumentation.narrative | BN3: ThreatsDocumentation.value | BO3: Threats.ThreatsSubfield.ThreatsLookup | BP3: Threats.ThreatsSubfield.timing | BQ3: Threats.ThreatsSubfield.scope | BR3: Threats.ThreatsSubfield.severity | BS3: Threats.ThreatsSubfield.StressesSubfield.stress | BT3: NoThreats.noThreats | BU3: ThreatsUnknown.value | BV3: PopulationTrend.value | BW3: CurrentTrendDataDerivation.value | BX3: ConservationActionsDocumentation.narrative | BY3: InPlaceLandWaterProtectionInPA.value | BZ3: InPlaceLandWaterProtectionInPA.note | CA3: InPlaceSpeciesManagementExSitu.value | CB3: InPlaceSpeciesManagementExSitu.note | CC3: ConservationActions.ConservationActionsSubfield.ConservationActionsLookup | CD3: Research.ResearchSubfield.ResearchLookup | CE3: RedListCriteria.manualCategory | CF3: RedListCriteria.manualCriteria | CG3: RedListCriteria.isManual | CH3: RedListCriteria.critVersion | CI3: RedListCriteria.dataDeficientReason | CJ3: RedListCriteria.possiblyExtinctCandidate | CK3: RedListRationale.value | CL3: RedListAssessmentDate.value | CM3: language.value | CN3: GEPC | CO3: GEPC | CP3: GEPC | CQ3: reasonforchangejustification.narrative | CR3: RedListReasonsForChange.type | CS3: ​RedListReasonsForChange.catCritChanges | CT3: RedListReasonsForChange.changeReasons | CU3: GEPC | CV3: GEPC | CW3: GEPC | CX3: GEPC | CY3: GEPC | CZ3: GEPC | DA3: GEPC | DB3: GEPC
A4: NINGUNO | B4: Este campo va en todos los .csv para reconocer la especie | C4: taxonomy | D4: taxonomy | E4: taxonomy | F4: taxonomy | G4: taxonomy | H4: taxonomy | I4: taxonomy | J4: taxonomy | K4: NINGUNO | L4: NINGUNO | M4: NINGUNO | N4: synonyms | O4: synonyms | P4: synonyms | Q4: commonnames | R4: commonnames | S4: commonnames | T4: usetrade | U4: allfields | V4: assessments | W4: allfields | X4: plantspecific | Y4: plantspecific | Z4: allfields | AA4: countries | AB4: countries | AC4: countries | AD4: countries | AE4: allfields | AF4: allfields | AG4: assessments | AH4: assessments | AI4: assessments | AJ4: assessments | AK4: habitats | AL4: habitats | AM4: NINGUNO | AN4: NINGUNO | AO4: assessments | AP4: NINGUNO | AQ4: NINGUNO | AR4: NINGUNO | AS4: NINGUNO | AT4: NINGUNO | AW4: allfields | AX4: allfields | AY4: allfields | AZ4: allfields | BA4: NINGUNO | BB4: NINGUNO | BC4: NINGUNO | BD4: NINGUNO | BE4: allfields | BF4: allfields | BG4: allfields | BH4: allfields | BI4: allfields | BJ4: allfields | BK4: allfields | BL4: allfields | BM4: assessments | BN4: assessments | BO4: threats | BP4: threats | BQ4: threats | BR4: threats | BS4: threats | BT4: allfields | BU4: allfields | BV4: assessments | BW4: allfields | BX4: assessments | BY4: allfields | BZ4: allfields | CA4: allfields | CB4: allfields | CC4: conservationneeded | CD4: researchneeded | CE4: assessments | CF4: assessments | CG4: assessments | CH4: assessments | CI4: assessments | CJ4: assessments | CK4: assessments | CL4: assessments | CM4: assessments | CN4: NINGUNO | CO4: NINGUNO | CP4: NINGUNO | CQ4: assessments | CR4: assessments | CS4: assessments | CT4: assessments | CU4: NINGUNO | CV4: NINGUNO | CW4: NINGUNO | CX4: NINGUNO | CY4: NINGUNO | CZ4: NINGUNO | DA4: NINGUNO | DB4: NINGUNO
A5: Verónica Bedoya Calle | B5: 1 | C5: Plantae | D5: Tracheophyta | E5: Equisetopsida | F5: Polypodiales | G5: Polypodiaceae | H5: Serpocaulon | I5: adnatum | J5: (Kunze ex Klotzsch) ARSm. | K5: Serpocaulon adnatum | L5: Taxon 55: 927 (2006) | M5: Goniophlebium adnatum (Kunze ex Klotzsch) T.Moore, Goniophlebium meniscifolium var. adnatum Farw., Polypodium adnatum Kunze ex Klotzsch, Polypodium fraxinifolium var. adnatum (Kunze ex Klotzsch) Baker | N5: Goniophlebium, Goniophlebium, Polypodium, Polypodium | O5: meniscifolium, fraxinifolium | P5: (Kunze ex Klotzsch) T.Moore, Farw, Kunze ex Klotzsch, (Kunze ex Klotzsch) Baker | Q5: N/A | R5: N/A | S5: N/A | T5: N/A | U5: TRUE | V5: No se han reportado usos para la especie. | W5: NO | X5: F, PT, E, L | Y5: Forb, Fern, Epiphyte, Lithophyte | Z5: Plantas hemiepífitas, epífitas, terrestres o, en raras ocasiones, rupícolas. Rizomas largos y rastreros, de color marrón oscuro a rojizo, pruinosos; filopodios separados entre 1,7 y siete cm. Escamas del rizoma densas, redondeadas, de forma ovada a elíptica, adpresas, peltadas y bicoloras. Frondas de 35–155 cm de largo. Pecíolos de 17–65 cm de largo, subcilíndricos en la parte proximal, ligeramente sulcados en la distal, de color marrón claro a marrón oscuro. (Sanín et al. 2023). | AA5: CO | AB5: Colombia | AC5: Native | AD5: Extant | AE5: 350 | AF5: 3700 | AG5: Neotropical | AH5: En Colombia, la especie se distribuye en las regiones de los Andes. Se ha registrado en los departamentos Antioquia, Boyacá, Caldas, Caquetá, Cauca, Chocó, Cundinamarca, Huila, Nariño, Putumayo, Quindío, Risaralda, Santander, Tolima y Valle del Cauca. | AI5: Done | AJ5: Terrestrial | AK5: Suitable | AL5: 1.6, 1.9 | AM5: La especie ocurre en hábitats de bosques húmedos en tierras bajas (elevación menor a 1.000 msnm), y en bosques de tierras altas (elevación mayor a 1000 msnm) (Sanín et at. 2023). | AN5: La especie está fertil todo el año (Sanín et at. 2023), y posiblemente es dispersada por viento. No se cuenta con información publicada sobre la ecología de la especie. El área de hábitat calculada tiene un valor de 124.866 km2. | AO5: =CONCATENATE(AM5," ",AN5) -> La especie ocurre en hábitats de bosques húmedos en tierras bajas (elevación menor a 1.000 msnm), y en bosques de tierras altas (elevación mayor a 1000 msnm) (Sanín et at. 2023). La especie está fertil todo el año (Sanín et at. 2023), y posiblemente es dispersada por viento. No se cuenta con información publicada sobre la ecología de la especie. El área de hábitat calculada tiene un valor de 124.866 km2. | AP5: Viento | AQ5: Las especies de la familia tienen dispersión a largas distancias (long distance dispersal) (Moran y Smith, 2001). | AR5: 5000 | AS5: 0.1 | AT5: Serpocaulon adnatum | AU5: 215215 | AV5: 368 | AW5: 216517 | AX5: 340 | AY5: 52 | AZ5: 69 | BH5: XXXX subpoblaciones de la especie se encuentran en paisajes con destrucción y degradación de su hábitat. Estas subpoblaciones se encuentran en los municipios de Frontino (departamento de Antioquia) y Quibdó y Lloró (departamento de Chocó). | BI5: Inferred | BJ5: YES | BK5: Es posible que la subpoblación de la localidad de Murrí del Municipio de Frontino (departamento de Antioquia) haya desaparecido por la destrucción de su hábitat. | BL5: Inferred | BM5: La especie tiene registradas hasta el momento cuatro subpoblaciones. Una de las subpoblaciones posiblemente desapareción por la destrucción y otras dos suppoblaciones tienen un bajo número de adultos (menos de 1000 individuos). Para una subpoblación se tiene información de un tamaño poblacional grande (más de 2500 adultos) y su estructura poblacional sugiere que la subpoblación es viable en términos demográficos (alto porcentaje de plántulas y juveniles). No se tiene información sobre fenología, dinámica poblacional y otros aspectos de la demografía de la especie (Lopez-Gallego et al 2015). | BN5: Tres de las cuatro subpoblaciones conocidas de la especie se encuentran en sitios con destrucción y degradación de su hábitat. Las alteraciones del hábitat se deben principalmente a la ampliación de la frontera agropecuaria (para ganaderia y para cultivos), la mineria (de metales) y la construcción de infraestructura (vias, centros poblados]. Además, las subpoblaciones conocidas de la especie están amenazadas por la extracción no sostenible de individuos por su uso como ornamentales. | BO5: 1.1, 2.1.4, 2.3.4, 3.2, 4.1, 5.2.1 | BP5: Ongoing, Ongoing, Ongoing, Ongoing, Ongoing, Ongoing | BQ5: Majority. Majority, Majority, Minority, Majority, Whole | BR5: Very rapid declines, Very rapid declines, Very rapid declines, Very rapid declines, Very rapid declines, Rapid declines | BS5: 1.1 | 1.2 | 2.1 | 2.2 // 1.1 | 1.2 | 2.1 | 2.2 // 1.1 | 1.2 | 2.1 | 2.2 // 1.1 | 1.2 | 2.1 | 2.2 // 1.1 | 1.2 | 2.1 | 2.2 // 2.1 | 2.2 | BT5: FALSE | BU5: FALSE | BV5: Decreasing | BW5: Inferred | BX5: XXX subpoblaciones conocidas de la especie están presentes en áreas del "Sistema Nacional de Áreas Protegidas"; sin embargo, las subpoblaciones se encuentran en áreas bajo figuras legales que son poco efectivas para la conservación de la biodiversidad. La especie tiene algunos individuos en colecciones vivas en Colombia. No se conocen otras acciones de conservación para la especie. | BY5: YES | BZ5: Parque Nacional Natural Cordillera de los Picachos, Santuario de Fauna y Flora Otún Quimbaya, Distrito de Conservacion de Suelos Barbas Bremen, Reserva Forestal Protectora Nacional Río Nare, Reserva Forestal Protectora Nacional La Planada, Distrito Regional de Manejo Integrado de la Cuenca Alta del Rio Quindio de Salento, Distrito Regional de Manejo Integrado Cuchilla Jardín Támesis, Distrito Regional de Manejo Integrado Planes de San Rafael, Distrito Regional de Manejo Integrado Serranía de Peñas Blancas | CA5: NO | CB5: N/A | CC5: 1.1, 3.4.2, 4.3 | CD5: 1.2, 1.3, 1.4, 1.5, 1.6, 2.1, 2.2, 2.3, 3.1, 3.2, 3.3, 3.4 | CE5: EN | CF5: B1a,B1biii,B1biv | CG5: TRUE | CH5: 3.1 | CI5: N/A | CJ5: N/A | CK5: Zamia xxxx es endémica de Colombia. La especie tiene cuatro subpoblaciones registradas actualmente, con una distribución geográfica restringida (EOO = 2569 km2). Tres de las cuatro subpoblaciones conocidas persisten en paisajes con destrucción y degradación de sus hábitats, principalmente por actividades de ampliación de la frontera agropecuaria, minería y construcción de infraestructura. La especie exhibe fragmentación severa, disminución continua de la cantidad y calidad del hábitat y disminución continua del número de subpoblaciones. Además, la especie es sobrexplotada para su uso como ornamental. La especie no tiene registros dentro de áreas protegidas y no tiene individuos en colecciones vivas. Se considera que esta especie está en la categoría de "en peligro". | CL5: 01/12/2020 | CM5: Spanish; Castilian | CN5: CR 2005 B1ab(iii) en Libros Rojos de Plantas de Colombia VolX, EN 2015 B1ab(iii) en Plan Nacional de Conservación de Zamias de Colombia | CO5: En las dos evaluaciones anteriores la especie se declaró como CR porque solo se conocia una subpoblación en sitios con destrucción/degradación de su hábitat. | CP5: Una de las evaluaciones realizadas para la especie (la del Plan de Conservación para las Zamias de Colombia) está publicada en el portal web de la Lista Roja Global de la UICN. | CQ5: La especie fue evaluada como CR en el año 2015 por Lopez-Gallego. En esta evaluación se usaron los criterios B1ab(iii) de la versión 3.1 de los lineamientos de la UICN. La especie [cambió de categoría de riesgo de extinción porque en la evaluación del 2015 la especie se conocía de una única subpoblación, pero actualmente se conoce de al menos cuatro subpoblaciones. | CR5: Non Genuine Change | CS5: N/A | CT5: New information | CU5: Jonatan Castro. David Taborda | CV5: Herbarios COL HUA JAUM | CW5: Paula A Morales | CX5: Carolina Castellanos | CY5: Alvaro Idarraga | CZ5: El experto aportó información sobre las amenazas para la especie y conformó las subpoblaciones conocidas. | DA5: Diligenciadas en la pestaña de referencias | DB5: ninguna
A6: Verónica Bedoya Calle | B6: 2 | C6: Plantae | D6: Tracheophyta | E6: Equisetopsida | F6: Polypodiales | G6: Polypodiaceae | H6: Serpocaulon | I6: antioquianum | J6: D. Sanín | K6: Serpocaulon antioquianum | L6: Fl. Colombia 32: 43 (2018) | M6: N/A | N6: N/A | O6: N/A | P6: N/A | Q6: N/A | R6: N/A | S6: N/A | T6: N/A | U6: TRUE | V6: No se han reportado usos para la especie. | W6: NO | X6: PT, E | Y6: Fern, Epiphyte | Z6: Plantas epífitas. Rizomas largos y rastreros, de color marrón oscuro a rojizo, no pruinosos; filopodios separados entre dos y tres cm. Escamas del rizoma densas, de forma ovada a redondeada, adpresas, peltadas, bicoloras, de color salmón en los márgenes y marrón oscuro hacia el centro, con la base y el ápice redondeados a obtusos y adpresos, y los márgenes dentados y superpuestos a las escamas adyacentes. Frondas de 34–107 cm de largo. Pecíolos de 10–47 cm de largo. | AA6: CO | AB6: Colombia | AC6: Native | AD6: Extant | AE6: 400 | AF6: 900 | AG6: Neotropical | AH6: La especie es endémica de Colombia, se distribuye en la vertiente oriental de la Cordillera Central Andina, en la cuenca media del río Magdalena. Se ha registrado en los departamentos Antioquia y Caldas. | AI6: Done | AJ6: Terrestrial | AK6: Suitable | AL6: 1.6 | AM6: La especie ocurre en hábitats de bosques húmedos en tierras bajas (elevación menor a 1.000 msnm). | AN6: La especie está fértil en enero, marzo, abril, julio, octubre y diciembre (Sanín et at. 2023), y posiblemente es dispersada por viento. No se cuenta con información publicada sobre la ecología de la especie. El área de hábitat calculada tiene un valor de 664 km2. | AO6: =CONCATENATE(AM6," ",AN6) -> La especie ocurre en hábitats de bosques húmedos en tierras bajas (elevación menor a 1.000 msnm). La especie está fértil en enero, marzo, abril, julio, octubre y diciembre (Sanín et at. 2023), y posiblemente es dispersada por viento. No se cuenta con información publicada sobre la ecología de la especie. El área de hábitat calculada tiene un valor de 664 km2. | AP6: Viento | AR6: 50 | AS6: 150 | AT6: Serpocaulon antioquianum | AU6: 3200 | AV6: 36 | AW6: 3200 | AX6: 36 | AY6: 6 | AZ6: 6 | BA6: 33 | BB6: 0 | BC6: 53 | BD6: NO | BE6: NO | BF6: N/A | BG6: YES | BH6: Las dos subpoblaciones de la especie se encuentran en paisajes con destrucción y degradación de su hábitat. Estas subpoblaciones se encuentran en los municipios de Anorí y San Luis (departamento de Antioquia) y Florencia (departamento de Caldas). | BI6: Inferred | BJ6: NO | BK6: N/A | BL6: N/A | BM6: La especie tiene registradas hasta el momento 2 subpoblaciones. No se conoce nada sobre la abundancia o tendencia poblacional de la especie. | BN6: Las dos subpoblaciones conocidas de la especie se encuentran en sitios con destrucción y degradación de su hábitat. Las alteraciones del hábitat se deben principalmente a la ampliación de la frontera agropecuaria (para ganaderia y para cultivos), la mineria (de metales) y la construcción de infraestructura (vias, centros poblados]. Además, las subpoblaciones conocidas de la especie están amenazadas por la extracción no sostenible de individuos por su uso como ornamentales. | BO6: N/A | BP6: N/A | BQ6: N/A | BR6: N/A | BS6: N/A | BT6: TRUE | BU6: N/A | BV6: Stable | BW6: Inferred | BX6: Todas las subpoblaciones conocidas de la especie están presentes en áreas del "Sistema Nacional de Áreas Protegidas"; sin embargo, las subpoblaciones se encuentran en áreas bajo figuras legales que son poco efectivas para la conservación de la biodiversidad. La especie tiene algunos individuos en colecciones vivas en Colombia. No se conocen otras acciones de conservación para la especie. | BY6: YES | BZ6: Distrito Regional de Manejo Integrado Bosques, Marmoles, y Pantagoras, Distrito Regional de Manejo Integrado Bajo Cauca Nechí | CA6: YES | CB6: Jardín Botánico de Medellín, Jardín Botánico del Quindío | CC6: N/A | CD6: N/A | CE6: VU | CF6: B1biii | CG6: TRUE | CH6: 3.1 | CI6: N/A | CJ6: N/A | CK6: Zamia yyyy se distribuye en Colombia y Panamá. La especie tiene 16 subpoblaciones registradas actualmente en Colombia, con una distribución geográfica amplia (EOO = 32470 km2). Las subpoblaciones se encuentran en paisajes con poca perturbación por actividades humanas. La especie tiene registros dentro de áreas protegidas y tiene individuos en colecciones vivas. Se considera que esta especie está en la categoría de "preocupación menor". | CL6: 01/12/2020 | CM6: Spanish; Castilian | CN6: N/A | CO6: N/A | CP6: N/A | CQ6: N/A | CR6: N/A | CS6: N/A | CT6: N/A | CU6: Jonatan Castro. David Taborda | CV6: Herbarios COL HUA JAUM | CW6: Paula A Morales | CX6: Carolina Castellanos | CY6: N/A | CZ6: N/A | DA6: Diligenciadas en la pestaña de referencias | DB6: ninguna
A7: Verónica Bedoya Calle | B7: 3 | C7: Plantae | D7: Tracheophyta | E7: Equisetopsida | F7: Polypodiales | G7: Polypodiaceae | H7: Serpocaulon | I7: articulatum | J7: (C.Presl) Schwartsb. & ARSm. | K7: Serpocaulon articulatum | L7: J. Bot. Res. Inst. Texas 7: 85 (2013) | M7: Goniophlebium articulatum (Desv.) Presl, Polypodium articulatum Desv., Polypodium adnatum var. glaucescens Mille, Polypodium caceresii Sodiro, Polypodium fraxinifolium var. articulatum C.Chr., Polypodium fraxinifolium subsp. luridum Christ, Serpocaulon caceresii (Sodiro) ARSm. | N7: Goniophlebium, Polypodium, Polypodium, Polypodium, Polypodium, Polypodium, Serpocaulon | O7: articulatum, articulatum, adnatum var. glaucescens, caceresii, fraxinifolium var. articulatum, fraxinifolium subsp. luridum, caceresii | P7: (Desv.) Presl, Desv., Mille, Sodiro, C. Chr, Christ, (Sodiro) ARSm. | Q7: N/A | R7: N/A | S7: N/A | T7: N/A | U7: TRUE | V7: En Perú se utiliza para infecciones renales, hepáticas y uterinas (D. Sanín 2023) | W7: NO | X7: F, PT, E | Y7: Forb, Fern, Epiphyte | Z7: Plantas hemiepífitas, epífitas o terrestres. Rizomas largos y rastreros, de color marrón oscuro, a menudo pruinosos; filopodios separados entre 1 y 12 cm. Escamas del rizoma densas, lanceoladas, bicoloras, de color marrón claro a rojizo en los márgenes con células paralelas, y marrón oscuro hacia el centro; bases peltadas, redondeadas; ápices acuminados a caudados. Frondas de 32–102 cm de largo. Pecíolos de 10–40 cm de largo. | AA7: CO | AB7: Colombia | AC7: Native | AD7: Extant | AE7: 5 | AF7: 2050 | AG7: Neotropical | AH7: En Colombia, la especie se ha registrado en los departamentos Caquetá, Chocó y la Amazonía. | AI7: Done | AJ7: Terrestrial | AK7: Suitable | AL7: 1.6, 1.9 | AM7: La especie ocurre en hábitats de bosques húmedos en tierras bajas (elevación menor a 1.000 msnm), y en bosques de tierras altas (elevación mayor a 1000 msnm) (Sanín et at. 2023). | AN7: La especie está fertil todo el año (Sanín et at. 2023), y posiblemente es dispersada por viento. No se cuenta con información publicada sobre la ecología de la especie. El área de hábitat calculada tiene un valor de 160.527 km2. | AO7: =CONCATENATE(AM7," ",AN7) -> La especie ocurre en hábitats de bosques húmedos en tierras bajas (elevación menor a 1.000 msnm), y en bosques de tierras altas (elevación mayor a 1000 msnm) (Sanín et at. 2023). La especie está fertil todo el año (Sanín et at. 2023), y posiblemente es dispersada por viento. No se cuenta con información publicada sobre la ecología de la especie. El área de hábitat calculada tiene un valor de 160.527 km2. | AP7: Viento | AR7: 50 | AS7: 150 | AT7: Serpocaulon articulatum | AU7: 365587 | AV7: 60 | AW7: 362947 | AX7: 56 | AY7: 14 | AZ7: 14 | BM7: La especie tiene registradas hasta el momento 14 subpoblaciones. No se conoce nada sobre la abundancia o tendencia poblacional de la especie. | BY7: YES | BZ7: Parque Nacional Natural Serrania de los Churumbelos Auka Wasi, Reserva Forestal Protectora Nacional Carauta, Reserva Forestal Protectora Nacional Río Anchicayá
A8: Verónica Bedoya Calle | B8: 4 | C8: Plantae | D8: Tracheophyta | E8: Equisetopsida | F8: Polypodiales | G8: Polypodiaceae | H8: Serpocaulon | I8: attenuatum | J8: (Humb. & Bonpl. ex Willd.) A.R.Sm. | K8: Serpocaulon attenuatum | L8: Taxon 55(4): 927 (-928) (2006) | M8: Polypodium attenuatum Humb. & Bonpl. ex Willd., Polypodium brasiliense var. attenuatum (Humb. & Bonpl. ex Willd.) Baker, Goniophlebium attenuatum C.Presl, Goniophlebium kuhnii (E.Fourn.) Pic.Serm., Goniophlebium oleandrifolium T.Moore, Marginaria oleandrifolia C.Presl, Polypodium kuhnii E.Fourn., Polypodium pycnosorum Link | N8: Goniophlebium, Marginaria, Polypodium, Goniophlebium, Polypodium, Goniophlebium, Polypodium, Polypodium, Polypodium | O8: attenuatum, brasiliense var. attenuatum, attenuatum, kuhnii, oleandrifolium, oleaodrifolia, kuhnii, pycnosorum | P8: Humb. & Bonpl. ex Willd., (Humb. & Bonpl. ex Willd.) Baker, C.Presl, (E.Fourn.) Pic.Serm., T. Moore, C. Presl, E.Fourn, Link | Q8: Avento in Pernambuco, Brazil (Fonseca 20343, UFP). | R8: Portuguese | S8: TRUE | T8: N/A | U8: TRUE | V8: Lengua de ciervo in Lambayeque, Peru (Esposto s.n., USM). No se han reportado usos para la especie. | W8: NO | X8: F, PT, E, L | Y8: Forb, Fern, Epiphyte, Lithophyte | Z8: Plantas epífitas, terrestres y rupícolas. Rizomas cortos y rastreros, de color marrón oscuro a rojizo, sin pruina o con una pruina muy tenue; filopodios separados entre 0,5 y 1,5 cm. Escamas del rizoma densas, de forma ovado-lanceolada a lanceolada, de un solo color, de color marrón claro a naranja, con la base redondeada y el ápice agudo. Frondas de 20-155 cm de largo. Pecíolos de 7-45 cm de largo, subcilíndricos en la parte proximal, ligeramente sulcados en la distal, con un pequeño ala, de color marrón claro a marrón oscuro. | AA8: CO | AB8: Colombia | AC8: Native | AD8: Extant | AE8: 0 | AF8: 2450 | AG8: Neotropical | AH8: En Colombia, la especie se ha registrado en los departametos Magdalena, Meta y Guaviare, principalmente en zonas expuestas de las tierras bajas, en bosques que van de húmedos a secos. | AI8: Done | AJ8: Terrestrial | AK8: Suitable | AL8: 1.6, 1.9 | AM8: La especie ocurre en hábitats de bosques húmedos en tierras bajas (elevación menor a 1.000 msnm), y en bosques de tierras altas (elevación mayor a 1000 msnm) (Sanín et at. 2023). | AN8: La especie está fertil todo el año (Sanín et at. 2023), y posiblemente es dispersada por viento. No se cuenta con información publicada sobre la ecología de la especie. El área de hábitat calculada tiene un valor de 6.141 km2. | AO8: =CONCATENATE(AM8," ",AN8) -> La especie ocurre en hábitats de bosques húmedos en tierras bajas (elevación menor a 1.000 msnm), y en bosques de tierras altas (elevación mayor a 1000 msnm) (Sanín et at. 2023). La especie está fertil todo el año (Sanín et at. 2023), y posiblemente es dispersada por viento. No se cuenta con información publicada sobre la ecología de la especie. El área de hábitat calculada tiene un valor de 6.141 km2. | AP8: Viento | AR8: 50 | AS8: 150 | AT8: Serpocaulon attenuatum | AU8: 11112 | AV8: 20 | AW8: 10727 | AX8: 20 | AY8: 4 | AZ8: 4 | BA8: 50 | BB8: 0?? | BC8: 33 | BD8: NO | BG8: NO | BH8: Las dos subpoblaciones de la especie se encuentran en paisajes con destrucción y degradación de su hábitat. Estas subpoblaciones se encuentran en los municipios de Anorí y San Luis (departamento de Antioquia) y Florencia (departamento de Caldas). | BI8: N/A | BJ8: NO | BK8: N/A | BL8: N/A | BM8: La especie tiene registradas hasta el momento 3 subpoblaciones. No se conoce nada sobre la abundancia o tendencia poblacional de la especie. | BN8: Las tres subpoblaciones conocidas de la especie se encuentran en sitios con destrucción y degradación de su hábitat. Las alteraciones del hábitat se deben principalmente a la ampliación de la frontera agropecuaria (para ganaderia y para cultivos), la mineria (de metales) y la construcción de infraestructura (vias, centros poblados]. Además, las subpoblaciones conocidas de la especie están amenazadas por la extracción no sostenible de individuos por su uso como ornamentales. | BZ8: Parque Nacional Natural Sierra de La Macarena, Reserva Forestal Protectora Nacional Serrania La Lindosa - Angosturas II
A9: Verónica Bedoya Calle | B9: 5 | C9: Plantae | D9: Tracheophyta | E9: Equisetopsida | F9: Polypodiales | G9: Polypodiaceae | H9: Serpocaulon | I9: biauriculatum | J9: D. Sanín & Testo | K9: Serpocaulon biauriculatum | L9: Brittonia 77, 411–418 (2025) | M9: N/A | N9: N/A | O9: N/A | P9: N/A | Q9: N/A | R9: N/A | S9: N/A | T9: N/A | U9: TRUE | V9: No se han reportado usos para la especie. | W9: NO | X9: F, PT | Y9: Forb, Fern | Z9: Plantas terrestres en su fase juvenil, terrestres y trepadoras en su madurez. Rizomas largos y rastreros, superficie no pruinosa, de color verde en plantas vivas y marrón oscuro cuando secas, densamente escamosos; filopodios separados entre 4 y 8 cm, del mismo color que el rizoma. Escamas del rizoma extendidas, lineares-lanceoladas, reticuladas, con márgenes enteros, del mismo color, de color marrón pálido, base truncada a redondeada y ápice largamente atenuado. Frondas de 60-115 × 30–45 cm. Pecíolos de aprox. 1/2–1/5 de la longitud de la fronda, de color pajizo a marrón brillante, redondeados en el envés, sulcados en el haz, con tonos dorado oscuro. | AA9: CO | AB9: Colombia | AC9: Native | AD9: Extant | AE9: 1401 | AF9: 1900 | AG9: Neotropical | AH9: La especie es endémica de Colombia. Se ha registrado en la vertiente occidental de la Serranía de Los Yariguíes, en los municipios de Carmen del Chucurí y San Vicente del Chucurí, Santander. En bosques nubosos premontanos y montanos. | AI9: Done | AJ9: Terrestrial | AK9: Suitable | AL9: 1.9 | AM9: La especie ocurre en hábitats de bosques húmedos en tierras altas (elevación mayor a 1000 msnm) (Sanín et at. 2023). | AN9: No se cuenta con información publicada sobre la ecología de la especie. El área de hábitat calculada tiene un valor de 22 km2. | AO9: =CONCATENATE(AM9," ",AN9) -> La especie ocurre en hábitats de bosques húmedos en tierras altas (elevación mayor a 1000 msnm) (Sanín et at. 2023). No se cuenta con información publicada sobre la ecología de la especie. El área de hábitat calculada tiene un valor de 22 km2. | AP9: Viento | AR9: 50 | AS9: 150 | AT9: Serpocaulon biauriculatum | AU9: 36 | AV9: 12 | AW9: 20* | AX9: 12* | AY9: 2 | AZ9: 2* | BA9: 100 | BB9: 0 | BC9: 31 | BD9: NO | BE9: NO | BF9: N/A | BG9: NO | BJ9: NO | BK9: N/A | BL9: N/A | BM9: La especie tiene registradas hasta el momento 2 subpoblaciones. No se conoce nada sobre la abundancia o tendencia poblacional de la especie. | BY9: YES | BZ9: Parque Nacional Natural Serranía de los Yariguíes
A10: Verónica Bedoya Calle | B10: 6 | C10: Plantae | D10: Tracheophyta | E10: Equisetopsida | F10: Polypodiales | G10: Polypodiaceae | H10: Serpocaulon | I10: concolorum | J10: (M.Kessler & A.R.Sm.) A.R.Sm. | K10: Serpocaulon concolorum | L10: Taxon 55: 928 (2006) | M10: Polypodium concolorum M.Kessler & A.R.Sm., Polypodium loriceum var. obscurum Rosenst., Polypodium loriceum var. squamuligerum Rosenst., Serpocaulon obscurinervium D.Sanín | N10: Polypodium, Polypodium, Polypodium, Serpocaulon | O10: concolorum, loriceum var. obscurum, loriceum var. squamuligerum, obscurinervium | P10: M.Kessler & A.R.Sm., Rosenst, Rosenst, D. Sanín | Q10: N/A | R10: N/A | S10: N/A | T10: N/A | U10: TRUE | V10: No se han reportado usos para la especie. | W10: NO | X10: F, PT | Y10: Forb, Fern | Z10: Plantas hemiepífitas o terrestres. Rizomas largos y rastreros, de color naranja a rojizo en los ápices, marrón amarillento en la base, pruinosos; filopodios separados entre dos y cuatro cm. Escamas del rizoma densas, lanceoladas a estrechamente lanceoladas, de un solo color, de color naranja oscuro, iridiscentes y con la base redondeada. Frondas de 54-61 cm de largo. Pecíolos de 25-28 cm de largo, subcilíndricos en la parte proximal, triangulares en la distal, de color pajizo a marrón. | AA10: CO | AB10: Colombia | AC10: Native | AD10: Extant | AE10: 1820 | AF10: 3000 | AG10: Neotropical | AH10: En Colombia, la especie se distribuye en las regiones de los Andes. Se ha registrado en los departamentos Caquetá, Chocó, Huila y Nariño. | AI10: Done | AJ10: Terrestrial | AK10: Suitable | AL10: 1.9 | AM10: La especie ocurre en hábitats de bosques húmedos en tierras altas (elevación mayor a 1000 msnm) (Sanín et at. 2023). | AN10: La especie está fértil en enero, marzo, mayo, julio, agosto, septiembre y noviembre (Sanín et at. 2023), y posiblemente es dispersada por viento. No se cuenta con información publicada sobre la ecología de la especie. El área de hábitat calculada tiene un valor de 17.325 km2. | AO10: =_xlfn.CONCAT(AM10,"",AN10) -> La especie ocurre en hábitats de bosques húmedos en tierras altas (elevación mayor a 1000 msnm) (Sanín et at. 2023).La especie está fértil en enero, marzo, mayo, julio, agosto, septiembre y noviembre (Sanín et at. 2023), y posiblemente es dispersada por viento. No se cuenta con información publicada sobre la ecología de la especie. El área de hábitat calculada tiene un valor de 17.325 km2. | AP10: Viento | AR10: 50 | AS10: 150 | AT10: Serpocaulon concolorum | AU10: 52105 | AV10: 20 | AW10: 52337* | AX10: 20 | AY10: 5 | AZ10: 5 | BA10: 20 | BB10: 0 | BC10: 42 | BD10: NO | BE10: NO | BF10: N/A | BG10: YES | BI10: N/A | BJ10: NO | BK10: N/A | BL10: N/A | BZ10: Reserva Forestal Protectora Nacional La Planada
A11: Verónica Bedoya Calle | B11: 7 | C11: Plantae | D11: Tracheophyta | E11: Equisetopsida | F11: Polypodiales | G11: Polypodiaceae | H11: Serpocaulon | I11: dissimile | J11: (L.) A.R.Sm. | K11: Serpocaulon dissimile | L11: Taxon 55: 928 (2006) | M11: Goniophlebium dissimile (L.) J.Sm., Polypodium dissimile L., Goniophlebium assimile Lodd., Goniophlebium chnoodes (Spreng.) Fée, Marginaria chnoodes (Spreng.) C.Presl, Polypodium assimile Kunze, Polypodium chnoodes Spreng., Polypodium chnoodes var. minus Christ, Polypodium falciforme Siebold, Polypodium loriceum var. umbraticum Christ, Polypodium retrofractum Desv. | N11: Goniophlebium, Polypodium, Goniophlebium, Goniophlebium, Marginaria, Polypodium, Polypodium, Polypodium, Polypodium, Polypodium, Polypodium | O11: dissimile, dissimile, assimile, chnoodes, chnoodes, assimile, chnoodes, chnoodes, falciforme, loriceum var. Umbraticum, retrofractum | P11: (L.) J.Sm., L., Lodd., (Spreng.) Fée, (Spreng.) C.Presl, Kunze, Spreng., Christ, Siebold, Christ, Desv. | Q11: Kalahuala in Guatemala (Williams et al. 40250, F). | R11: N/A | S11: TRUE | T11: N/A | U11: TRUE | V11: En Guatemala, el rizoma se utiliza para tratar los dolores de cabeza, aplicando en la frente la infusión realizada con este | W11: NO | X11: F, PT, E, L | Y11: Forb, Fern, Epiphyte, Lithophyte | Z11: Plantas epífitas, terrestres o rupícolas. Rizomas cortos y rastreros, de color marrón oscuro a rojizo, pruinosos; filopodios separados entre 0,4 y 2,5 cm. Escamas del rizoma densas, lanceoladas a aciculolanceoladas, de un solo color, marrón oscuro, iridiscentes, con la base redondeada, el ápice largamente acuminado, patentes y los márgenes dentados. Frondas de 20–146 cm de largo. Pecíolos de 4,5–35 cm de largo, subcilíndricos, de color marrón claro a oscuro. | AA11: CO | AB11: Colombia | AC11: Native | AD11: Extant | AE11: 5 | AF11: 1950 | AG11: Neotropical | AH11: En Colombia, la especie se ha registrado en los departamentos Antioquia, Caldas, Cauca, Chocó, Cundinamarca, Huila, Nariño, Quindío y Valle del Cauca; principalmente como epífita en bosques alterados de las tierras bajas y en bosques húmedos. | AI11: Done | AJ11: Terrestrial | AK11: Suitable | AL11: 1.6, 1.9 | AM11: La especie ocurre en hábitats de bosques húmedos en tierras bajas (elevación menor a 1.000 msnm), y en bosques de tierras altas (elevación mayor a 1000 msnm) (Sanín et at. 2023). | AN11: La especie está fertil todo el año (Sanín et at. 2023), y posiblemente es dispersada por viento. No se cuenta con información publicada sobre la ecología de la especie. El área de hábitat calculada tiene un valor de 93.249 km2. | AO11: =CONCATENATE(AM11," ",AN11) -> La especie ocurre en hábitats de bosques húmedos en tierras bajas (elevación menor a 1.000 msnm), y en bosques de tierras altas (elevación mayor a 1000 msnm) (Sanín et at. 2023). La especie está fertil todo el año (Sanín et at. 2023), y posiblemente es dispersada por viento. No se cuenta con información publicada sobre la ecología de la especie. El área de hábitat calculada tiene un valor de 93.249 km2. | AP11: Viento | AR11: 50 | AS11: 150 | AT11: Serpocaulon dissimile | AU11: 164197 | AV11: 72 | AW11: 164922 | AX11: 72 | AY11: 17 | AZ11: 17 | BZ11: Parque Nacional Natural Las Orquídeas, Distrito Regional de Manejo Integrado de la Cuenca Alta del Rio Quindio de Salento
A12: Verónica Bedoya Calle | B12: 8 | C12: Plantae | D12: Tracheophyta | E12: Equisetopsida | F12: Polypodiales | G12: Polypodiaceae | H12: Serpocaulon | I12: eleutherophlebium | J12: (Fée) A.R.Sm. | K12: Serpocaulon eleutherophlebium | L12: Taxon 55: 928 (2006) | M12: Goniophlebium eleutherophlebium Fée, Polypodium eleutherophlebium (Fée) Mett., Goniophlebium chondrocheilon Fée, Polypodium chondrocheilon (Fée) C.Chr., Polypodium mindense Sodiro, Polypodium punctulatum Hook., Polypodium vagans Mett., Polypodium wiesbaurii Sodiro | N12: Goniophlebium, Polypodium, Goniophlebium, Goniophlebium, Polypodium, Polypodium, Polypodium, Polypodium, Polypodium | O12: eleutherophlebium, eleutherophlebium, chondrocheilon, chondrocheilon, mindense, punctulatum, vagans, wiesbaurii | P12: Fée, (Fée) Mett., Fée, (Fée) C.Chr., Sodiro, Hook., Mett., Sodiro | Q12: N/A | R12: N/A | S12: N/A | T12: N/A | U12: TRUE | V12: No se han reportado usos para la especie. | W12: NO | X12: F, PT, E, L | Y12: Forb, Fern, Epiphyte, Lithophyte | Z12: Plantas epífitas, hemiepífitas, terrestres o, en raras ocasiones, rupícolas. Rizomas largos y rastreros, de color marrón claro a oscuro, pruinosos; filopodios separados entre 1 y 5,5 cm. Escamas del rizoma densas, principalmente en el ápice del rizoma y en los filopodios, peltadas, de un solo color, de color marrón oscuro a rojizo, con la base redondeada, el ápice acicular y extendido, y los márgenes ciliados. Frondas de 8–42 cm de largo. Pecíolos de 3,4–25 cm de largo, subcilíndricos en la parte proximal, ligeramente sulcados en la distal, de color marrón claro a rojizo o verdoso. | AA12: CO | AB12: Colombia | AC12: Native | AD12: Extant | AE12: 2430 | AF12: 3950 | AG12: Neotropical | AH12: En Colombia, la especie se ha registrado en los departamentos de Antioquia, Caldas, Cauca, Cundinamarca, Huila, Nariño, Norte de Santander, Putumayo, Quindío, Risaralda, Santander y Tolima; en bosques de alta montaña y subpáramos. | AI12: Done | AJ12: Terrestrial | AK12: Suitable | AL12: 1.9 | AM12: La especie ocurre en hábitats de bosques húmedos en tierras altas (elevación mayor a 1000 msnm) (Sanín et at. 2023). | AN12: La especie está fertil todo el año (Sanín et at. 2023), y posiblemente es dispersada por viento. No se cuenta con información publicada sobre la ecología de la especie. El área de hábitat calculada tiene un valor de 35.614 km2. | AO12: =CONCATENATE(AM12," ",AN12) -> La especie ocurre en hábitats de bosques húmedos en tierras altas (elevación mayor a 1000 msnm) (Sanín et at. 2023). La especie está fertil todo el año (Sanín et at. 2023), y posiblemente es dispersada por viento. No se cuenta con información publicada sobre la ecología de la especie. El área de hábitat calculada tiene un valor de 35.614 km2. | AP12: Viento | AR12: 50 | AS12: 150 | AT12: Serpocaulon eleutherophlebium | AU12: 177568 | AV12: 196 | AW12: 187541 | AX12: 204 | AY12: 28 | AZ12: 42 | BZ12: Parque Nacional Natural Los Nevados, Parque Nacional Natural Puracé, Parque Nacional Natural Sumapaz, Parque Nacional Natural Tatamá, Reserva Forestal Protectora Nacional de Urrao, Reserva Forestal Protectora Nacional Río Blanco y Quebrada Olivares, Reserva Forestal Protectora Nacional Páramo Grande, Reserva Forestal Protectora Nacional Bosque Oriental de Bogotá, Distrito Regional de Manejo Integrado de la Cuenca Alta del Rio Quindio de Salento, Distrito Regional de Manejo Integrado Paramo de Guargua y Laguna Verde, Distrito Regional de Manejo Integrado Sistema de Paramos y Bosques Altoandinos del Noroccidente Medio Antioqueño, Reserva Forestal Protectora Regional Torre Cuatro, Reserva Forestal Protectora Regional Bosques de la CHEC
A13: Verónica Bedoya Calle | B13: 9 | C13: Plantae | D13: Tracheophyta | E13: Equisetopsida | F13: Polypodiales | G13: Polypodiaceae | H13: Serpocaulon | I13: fraxinifolium | J13: (Jacq.) A.R.Sm. | K13: Serpocaulon fraxinifolium | L13: Taxon 55: 928 (2006) | M13: Polypodium fraxinifolium Jacq., Goniophlebium deflexum T.Moore & Houlston, Goniophlebium distans J.Sm., Goniophlebium fraxinifolium T.Moore, Goniophlebium ornatum Fée, Goniophlebium rhizocaulon C.Presl, Marginaria distans C.Presl, Polypodium cymatodes Kunze, Polypodium deflexum E.J.Lowe, Polypodium fraxinifolium var. fraxinellum Christ, Polypodium fraxinifolium subsp. ornatum (Klotzsch) Christ, Polypodium fraxinifolium var. rhizocaulon Rosenst., Polypodium mutabile Kunze, Polypodium ornatum Klotzsch, Polypodium rhizocaulon Willd., Polypodium scutulatum Sodiro | N13: Polypodium, Goniophlebium, Goniophlebium, Goniophlebium, Goniophlebium, Goniophlebium, Marginaria, Polypodium, Polypodium, Polypodium, Polypodium, Polypodium, Polypodium, Polypodium, Polypodium, Polypodium | O13: fraxinifolium, deflexum, distans, fraxinifolium, ornatum, rhizocaulon, distans, cymatodes, deflexum, fraxinifolium var. fraxinellum, fraxinifolium subsp. ornatum, fraxinifolium var. rhizocaulon, mutabile, ornatum, rhizocaulon, scutulatum | P13: Jacq., T.Moore & Houlston, J.Sm., T.Moore, Fée, C.Presl, C.Presl, Kunze, E.J.Lowe, Christ, Klotzsch) Christ, Rosenst., Kunze, Klotzsch, Willd., Sodiro | Q13: Jé yei remedio tape (Cayapa language) (Kvist & Asanza 40798, QCA). | R13: South American Indian (Other) | S13: TRUE | T13: N/A | U13: TRUE | V13: La cultura cayapa de Ecuador utilizaba esta especie para eliminar la mucosidad de la nariz y la garganta, hirviendo la planta y bebiendo la decocción (Kvist & Asanza 40798, QCA). En Ecuador, el Serpocaulon fraxinifolium se utiliza para prevenir trastornos del sistema respiratorio (Navarrete et al., 2006). | W13: NO | X13: F, PT, E, L | Y13: Forb, Fern, Epiphyte, Lithophyte | Z13: Plantas epífitas, terrestres, rupícolas o hemiepífitas. Rizomas largos y rastreros, de color marrón claro a verdoso, pruinosos; filopodios separados entre 0,6 y 10 cm. Escamas del rizoma dispersas o densas, redondeadas, de forma ovada a elíptica (nunca largamente acuminadas), adpresas, peltadas, bicoloras, de color marrón claro en los márgenes y marrón oscuro hacia el centro. Frondas de 21–111 cm de largo. Pecíolos de 4–29 cm de largo, subcilíndricos en la parte proximal, ligeramente sulcados en la distal, de color marrón claro a oscuro. | AA13: CO | AB13: Colombia | AC13: Native | AD13: Extant | AE13: 75 | AF13: 3700 | AG13: Neotropical | AH13: En Colombia, la especie se ha registrado en los departamentos Antioquia, Boyacá, Caldas, Cauca, Cesar, Chocó, Cundinamarca, Huila, Magdalena, Meta, Nariño, Putumayo, Quindío, Risaralda, Santander, Tolima y Valle del Cauca; desde las tierras bajas hasta los bosques premontanos, en bosques húmedos. | AI13: Done | AJ13: Terrestrial | AK13: Suitable | AL13: 1.6, 1.9 | AM13: La especie ocurre en hábitats de bosques húmedos en tierras bajas (elevación menor a 1.000 msnm), y en bosques de tierras altas (elevación mayor a 1000 msnm) (Sanín et at. 2023). | AN13: La especie está fertil todo el año (Sanín et at. 2023), y posiblemente es dispersada por viento. No se cuenta con información publicada sobre la ecología de la especie. El área de hábitat calculada tiene un valor de 175.282 km2. | AO13: =CONCATENATE(AM13," ",AN13) -> La especie ocurre en hábitats de bosques húmedos en tierras bajas (elevación menor a 1.000 msnm), y en bosques de tierras altas (elevación mayor a 1000 msnm) (Sanín et at. 2023). La especie está fertil todo el año (Sanín et at. 2023), y posiblemente es dispersada por viento. No se cuenta con información publicada sobre la ecología de la especie. El área de hábitat calculada tiene un valor de 175.282 km2. | AP13: Viento | AR13: 50 | AS13: 150 | AT13: Serpocaulon fraxinifolium | AU13: 318075 | AV13: 460 | AW13: 319959 | AX13: 448 | AY13: 66 | AZ13: 91 | BZ13: Parque Nacional Natural Sierra de la Macarena, Parque Nacional Natural Sierra Nevada de Santa Marta, Parque Nacional Natural Farallones de Cali, Parque Nacional Natural Las Orquídeas, Parque Nacional Natural Tatamá, Parque Nacional Natural Selva de Florencia, Parque Natural Regional del Nima, Parque Regional Natural Ucumari, Santuario de Fauna y Flora Iguaque, Santuario de Fauna y Flora Guanenta Alto Rio Fonce, Santuario de Fauna y Flora Otun Quimbaya, Distrito de Conservacion de Suelos Campoalegre, Distrito de Conservacion de Suelos Barbas Bremen, Reserva Forestal Protectora Nacional Carauta, Reserva Forestal Protectora Nacional Rio Nare, Reserva Forestal Protectora Nacional Cuenca Alta del Rio Cali, Reserva Forestal Protectora Nacional Paramo Grande, Reserva Forestal Protectora Nacional Rio Anchicaya, Reserva Forestal Protectora Regional Cerro Bravo, Distrito Regional de Manejo Integrado De la Cuenca Alta del Rio Quindio de Salento, Distrito Regional de Manejo Integrado Sistema de Paramos y Bosques Altoandinos del Noroccidente Medio Antioqueño, Distrito Regional de Manejo Integrado Serrania de los Yariguies, Distrito Regional de Manejo Integrado Embalse el Penol y Cuenca Alta del Rio Guatape, Distrito Regional de Manejo Integrado Sector Salto del Tequendama y Cerro Manjui, Distrito Regional de Manejo Integrado Divisoria Valle de Aburra Rio Cauca, Distrito Regional de Manejo Integrado Serrania de Peñas Blancas, Distrito Regional de Manejo Integrado Paramo de Vida Maitama - Sonson, Reserva Forestal Protectora Regional Farallones del Citara, Distrito Regional de Manejo Integrado Cuenca Alta del Rio Atrato, Distrito Regional de Manejo Integrado Cacica Noria
A14: Verónica Bedoya Calle | B14: 10 | C14: Plantae | D14: Tracheophyta | E14: Equisetopsida | F14: Polypodiales | G14: Polypodiaceae | H14: Serpocaulon | I14: funckii | J14: (Mett.) A.R.Sm. | K14: Serpocaulon funckii | L14: Taxon 55: 928 (2006) | M14: Polypodium funckii Mett. | N14: Polypodium | O14: funckii | P14: Mett. | Q14: N/A | R14: N/A | S14: N/A | T14: N/A | U14: TRUE | V14: No se han reportado usos para la especie. | W14: NO | X14: PT, E | Y14: Fern, Epiphyte | Z14: Plantas epífitas o hemiepífitas. Rizomas largos y rastreros, de color marrón oscuro a rojizo, pruinosos; filopodios separados entre 1,5 y 7 cm. Escamas del rizoma dispersas, elípticas, adpresas, peltadas, bicolores, de color marrón claro en los márgenes y marrón oscuro hacia el centro, con la base y el ápice obtusos a redondeados, y los márgenes dentados. Frondas de 16–42 cm de largo. Pecíolos de 2,5–14 cm de largo, subcilíndricos en la parte proximal, sulcados en la distal, de color marrón claro a oscuro. | AA14: CO | AB14: Colombia | AC14: Native | AD14: Extant | AE14: 1240 | AF14: 3000 | AG14: Neotropical | AH14: En Colombia, la especie se ha registrado en los departamentos de Antioquia, Barbosa, Boyacá, Cauca, Chocó, Cundinamarca, Norte de Santander y Risaralda; principalmente en las regiones andinas, en bosques de niebla. | AI14: Done | AJ14: Terrestrial | AK14: Suitable | AL14: 1.9 | AM14: La especie ocurre en hábitats de bosques húmedos en tierras altas (elevación mayor a 1000 msnm) (Sanín et at. 2023). | AN14: La especie está fértil casi todo el año, excepto en junio y agosto (Sanín et at. 2023), y posiblemente es dispersada por viento. No se cuenta con información publicada sobre la ecología de la especie. El área de hábitat calculada tiene un valor de 54.650 km2. | AO14: =CONCATENATE(AM14," ",AN14) -> La especie ocurre en hábitats de bosques húmedos en tierras altas (elevación mayor a 1000 msnm) (Sanín et at. 2023). La especie está fértil casi todo el año, excepto en junio y agosto (Sanín et at. 2023), y posiblemente es dispersada por viento. No se cuenta con información publicada sobre la ecología de la especie. El área de hábitat calculada tiene un valor de 54.650 km2. | AP14: Viento | AR14: 50 | AS14: 150 | AT14: Serpocaulon funckii | AU14: 137734 | AV14: 120 | AW14: 138336 | AX14: 120 | AY14: 18 | AZ14: 25 | BZ14: Parque Nacional Natural Las Orquideas, Parque Natural Regional Paramo de Rabanal, Reserva Forestal Protectora Nacional Carauta, Reserva Forestal Protector Nacional Rio Nare, Reserva Forestal Protectora Nacional De Urrao, Distrito Regional de Manejo Integrado Embalse el Peñol y Cuenca Alta del Rio Guatape, Distrito Regional de Manejo Integrado Divisoria Valle de Aburra Rio Cauca, Distrito Regional de Manejo Integrado Paramo de Vida Maitama - Sonson, Distrito Regional de Manejo Integrado Cacica Noria
A15: Verónica Bedoya Calle | B15: 11 | C15: Plantae | D15: Tracheophyta | E15: Equisetopsida | F15: Polypodiales | G15: Polypodiaceae | H15: Serpocaulon | I15: lasiopus | J15: (Klotzsch) A.R.Sm. | K15: Serpocaulon lasiopus | L15: Taxon 55: 928 (2006) | M15: Polypodium lasiopus Klotzsch, Goniophlebium lasiopus T.Moore, Goniophlebium pubescens T.Moore, Polypodium argyrolepis Sodiro, Polypodium gilliesii C.Chr., Polypodium loriceum var. hirto-pubescens Hieron., Polypodium pubescens Gillies ex Hook. & Grev., Serpocaulon gilliesii (C.Chr.) A.R.Sm. | N15: Polypodium, Goniophlebium, Goniophlebium, Polypodium, Polypodium, Polypodium, Polypodium, Serpocaulon | O15: lasiopus, lasiopus, pubescens, argyrolepis, gilliesii, loriceum var. hirto-pubescens, pubescens, gilliesii | P15: Klotzsch, T. Moore, T. Moore, Sodiro, Hieron, Gillies ex Hook. & Grev., (C.Chr.) A.R.Sm. | Q15: Calaguala by the Saraguro in Ecuador (Ellemann 66815, QCA). | R15: South American Indian (Other) | S15: TRUE | T15: N/A | U15: TRUE | V15: No se han reportado usos para la especie. | W15: NO | X15: F, PT, E, L | Y15: Forb, Fern, Epiphyte, Lithophyte | Z15: Plantas epífitas, rupícolas o, en raras ocasiones, terrestres. Rizomas cortos y rastreros, de color marrón a rojizo oscuro, pruinosos o no; filopodios separados entre 1 y 2,5 cm. Escamas del rizoma densas, ovado-lanceoladas, lanceoladas a ligeramente subuladas, bicoloras o, en raras ocasiones, ligeramente concoloras (marrón claro en los márgenes y marrón oscuro hacia el centro), con la base redondeada y el ápice largamente acuminado. Frondas de 6–56 cm de largo. Pecíolos de 1–23 cm de largo, subcilíndricos, de color marrón claro. | AA15: CO | AB15: Colombia | AC15: Native | AD15: Extant | AE15: 250 | AF15: 3210 | AG15: Neotropical | AH15: En Colombia, la especie se ha registrado en Antioquia, Cauca y Cundinamarca, principalmente en altitudes medias. | AI15: Done | AJ15: Terrestrial | AK15: Suitable | AL15: 1.6, 1.9 | AM15: La especie ocurre en hábitats de bosques húmedos en tierras bajas (elevación menor a 1.000 msnm), y en bosques de tierras altas (elevación mayor a 1000 msnm) (Sanín et at. 2023). | AN15: La especie está fertil todo el año (Sanín et at. 2023), y posiblemente es dispersada por viento. No se cuenta con información publicada sobre la ecología de la especie. El área de hábitat calculada tiene un valor de 30.966 km2. | AO15: =CONCATENATE(AM15," ",AN15) -> La especie ocurre en hábitats de bosques húmedos en tierras bajas (elevación menor a 1.000 msnm), y en bosques de tierras altas (elevación mayor a 1000 msnm) (Sanín et at. 2023). La especie está fertil todo el año (Sanín et at. 2023), y posiblemente es dispersada por viento. No se cuenta con información publicada sobre la ecología de la especie. El área de hábitat calculada tiene un valor de 30.966 km2. | AP15: Viento | AR15: 50 | AS15: 150 | AT15: Serpocaulon lasiopus | AU15: 58599 | AV15: 48 | AW15: 58858 | AX15: 48 | AY15: 10 | AZ15: 11 | BA15: 9 | BC15: 88 | BD15: 0 | BZ15: Reserva Forestal Protectora Nacional Rio Nare
A16: Verónica Bedoya Calle | B16: 12 | C16: Plantae | D16: Tracheophyta | E16: Equisetopsida | F16: Polypodiales | G16: Polypodiaceae | H16: Serpocaulon | I16: latissimum | J16: (R.C.Moran & B.Øllg.) A.R.Sm. | K16: Serpocaulon latissimum | L16: Taxon 55: 928 (2006) | M16: Polypodium latissimum R.C.Moran & B.Øllg. | N16: Polypodium | O16: latissimum | P16: R.C.Moran & B.Øllg. | Q16: N/A | R16: N/A | S16: N/A | T16: N/A | U16: TRUE | V16: No se han reportado usos para la especie. | W16: NO | X16: F, PT, E, L | Y16: Forb, Fern, Epiphyte, Lithophyte | Z16: Plantas hemiepífitas, epífitas, terrestres o, en raras ocasiones, rupícolas. Rizomas largos y rastreros, de color marrón oscuro, sin pruina; filopodios separados entre 3,5 y 8 cm. Escamas del rizoma densas o dispersas, redondeadas, adpresas, peltadas, bicoloras, de color marrón claro en los márgenes y marrón oscuro hacia el centro. Frondas de 49-110 cm de largo. Pecíolos de 14-41 cm de largo, subcilíndricos en la parte proximal, ligeramente sulcados en la distal, de color marrón claro en la base y a menudo se oscurecen en la parte distal. | AA16: CO | AB16: Colombia | AC16: Native | AD16: Extant | AE16: 0 | AF16: 2080 | AG16: Neotropical | AH16: En Colombia, la especie se ha registrado en los departamentos Amazonas, Antioquia, Cauca, Chocó, Huila, Nariño, Putumayo, Santander y Valle del Cauca; principalmente en bosques húmedos. | AI16: Done | AJ16: Terrestrial | AK16: Suitable | AL16: 1.6, 1.9 | AM16: La especie ocurre en hábitats de bosques húmedos en tierras bajas (elevación menor a 1.000 msnm), y en bosques de tierras altas (elevación mayor a 1000 msnm) (Sanín et at. 2023). | AN16: La especie está fértil casi todo el año, excepto en marzo y diciembre (Sanín et at. 2023), y posiblemente es dispersada por viento. No se cuenta con información publicada sobre la ecología de la especie. El área de hábitat calculada tiene un valor de 361.052 km2. | AO16: =CONCATENATE(AM16," ",AN16) -> La especie ocurre en hábitats de bosques húmedos en tierras bajas (elevación menor a 1.000 msnm), y en bosques de tierras altas (elevación mayor a 1000 msnm) (Sanín et at. 2023). La especie está fértil casi todo el año, excepto en marzo y diciembre (Sanín et at. 2023), y posiblemente es dispersada por viento. No se cuenta con información publicada sobre la ecología de la especie. El área de hábitat calculada tiene un valor de 361.052 km2. | AP16: Viento | AR16: 50 | AS16: 150 | AT16: Serpocaulon latissimum | AU16: 517891 | AV16: 128 | AW16: 520184 | AX16: 124 | AY16: 27 | AZ16: 28 | BZ16: Parque Nacional Natural Las Orquideas, Reserva Forestal Protectora Nacional Darien, Parque Nacional Natural Utria, Parque Nacional Natural Serrania de los Churumbelos Auka Wasi
A17: Verónica Bedoya Calle | B17: 13 | C17: Plantae | D17: Tracheophyta | E17: Equisetopsida | F17: Polypodiales | G17: Polypodiaceae | H17: Serpocaulon | I17: levigatum | J17: (Cav.) A.R.Sm. | K17: Serpocaulon levigatum | L17: Taxon 55: 928 (2006) | M17: Campyloneurum levigatum (Cav.) C.Presl, Goniophlebium levigatum (Cav.) Conz., Polypodium levigatum Cav., Goniophlebium glaucophyllum (Kunze ex Klotzsch) Fée, Polypodium glaucophyllum Kunze ex Klotzsch | N17: Campyloneurum, Goniophlebium, Polypodium, Goniophlebium, Polypodium | O17: levigatum, levigatum, levigatum, glaucophyllum, glaucophyllum | P17: (Cav.) C.Presl, (Cav.) Conz., Cav., (Kunze ex Klotzsch) Fée, Kunze ex Klotzsch | Q17: Jala wala in Quechua from Peru (Morales Huamán 7, Herbarium of University of San Cristóbal de Huamanga, Ayacucho). | R17: South American Indian (Other) | S17: TRUE | T17: N/A | U17: TRUE | V17: Catchi panga in Quechua from Ecuador (Shemluck & Ness 203, F); Calaguala (Acosta Solis 14385, F). In the Peruvian department of Ayacucho, it is used to cure kidney sickness (Morales Huamán 7, Herbarium of University of San Cristóbal de Huamanga, Ayacucho). In Ecuador, the leaves are said to be very sweet and used as a flavoring for monkey meat and to prevent blood coagulation (Shemluck & Ness 203, F). In Bolivia, the leaves are chewed by natives, have a sweet flavor like coconut, and may contain an alkaloid (A. Quesada 7, F). | W17: NO | X17: F, PT, E, L | Y17: Forb, Fern, Epiphyte, Lithophyte | Z17: Plantas hemiepífitas, epífitas, terrestres o rupícolas. Rizomas largos y rastreros, de color marrón blanquecino a oscuro o rojizo, volviéndose blanquecinos hacia el ápice, pruinosos; filopodios separados entre 0,5 y 9 cm. Escamas del rizoma dispersas, redondeadas, elípticas u ovadas, adpresas, peltadas, bicolores, de color marrón claro en los márgenes y marrón oscuro hacia el centro, con la base y el ápice redondeados a subagudos, adpresas, de márgenes erosos. Frondas de 6–50 cm de largo. Pecíolos de 1–23 cm de largo, subcilíndricos en la parte proximal, ligeramente sulcados en la distal, de color marrón claro a oscuro. | AA17: CO | AB17: Colombia | AC17: Native | AD17: Extant | AE17: 700 | AF17: 3700 | AG17: Neotropical | AH17: En Colombia, la especie se ha registrado en los departamentos Antioquia, Boyacá, Caldas, Cauca, Chocó, Cundinamarca, Huila, Magdalena, Meta, Nariño, Norte de Santander, Putumayo, Quindío, Risaralda, Santander, Tolima y Valle del Cauca; principalmente en bosques nublados. | AI17: Done | AJ17: Terrestrial | AK17: Suitable | AL17: 1.6, 1.9 | AM17: La especie ocurre en hábitats de bosques húmedos en tierras bajas (elevación menor a 1.000 msnm), y en bosques de tierras altas (elevación mayor a 1000 msnm) (Sanín et at. 2023). | AN17: La especie está fertil todo el año (Sanín et at. 2023), y posiblemente es dispersada por viento. No se cuenta con información publicada sobre la ecología de la especie. El área de hábitat calculada tiene un valor de 147.576 km2. | AO17: =CONCATENATE(AM17," ",AN17) -> La especie ocurre en hábitats de bosques húmedos en tierras bajas (elevación menor a 1.000 msnm), y en bosques de tierras altas (elevación mayor a 1000 msnm) (Sanín et at. 2023). La especie está fertil todo el año (Sanín et at. 2023), y posiblemente es dispersada por viento. No se cuenta con información publicada sobre la ecología de la especie. El área de hábitat calculada tiene un valor de 147.576 km2. | AP17: Viento | AR17: 50 | AS17: 150 | AT17: Serpocaulon levigatum | AU17: 352104 | AV17: 572 | AW17: 354288 | AX17: 572 | AY17: 80 | AZ17: 120 | BZ17: Parque Nacional Natural Sierra de la Macarena, Parque Nacional Natural Sierra Nevada de Santa Marta, Parque Nacional Natural Farallones de Cali, Parque Nacional Natural Tatama, Parque Natural Regional Serrania de Minas, Parque Natural Regional Ucumari, Santuario de Fauna y Flora Isla de la Corota, Santuario de Fauna y Flora Otun Quimbaya, Distrito de Conservacion de Suelos Barbas Bremen, Distrito de Conservacion de Suelos Campoalegre, Reserva Forestal Protectora Nacional Cuenca Alta del Rio Mocoa, Reserva Forestal Protectora Nacional Carauta, Reserva Forestal Protectora Nacional Rio Nare, Reserva Forestal Protectora Nacional de Urrao, Reserva Forestal Protectora Nacional Cuenca del Rio las Ceibas, Reserva Forestal Protectora Nacional Laguna La Cocha Cerro Patascoy, Reserva Forestal Protectora Nacional Cuenca Alta del Rio Cali, Reserva Forestal Protectora Nacional Paramo Grande, Reserva Forestal Protectora Nacional Bosque Oriental de Bogota, Reserva Forestal Protectora Nacional Rio Guadalajara, Distrito Regional de Manejo Integrado De la Cuenca Alta del Rio Quindio de Salento, Distrito Regional de Manejo Integrado Cuchilla Jardin Tamesis, Distrito Regional de Manejo Integrado Sistema de Paramos y Bosques Altoandinos del Noroccidente Medio Antioqueño, Distrito Regional de Manejo Integrado Paramos de Guantiva y la Rusia, Distrito Regional de Manejo Integrado Sector Salto del Tequendama y Cerro Manjui, Distrito Regional de Manejo Integrado Divisoria Valle de Aburra Rio Cauca, Distrito Regional de Manejo Integrado Serrania de Penas Blancas, Distrito Regional de Manejo Integrado Alto de Ventanas, Distrito Regional de Manejo Integrado Paramo de Vida Maitama - Sonson, Reserva Natural de la Sociedad Civil San Pedro Y El Recuerdo, Reserva Forestal Protectora Regional Sabinas, Reserva Forestal Protectora Nacional Rio Amaime
A18: Verónica Bedoya Calle | B18: 14 | C18: Plantae | D18: Tracheophyta | E18: Equisetopsida | F18: Polypodiales | G18: Polypodiaceae | H18: Serpocaulon | I18: loriceum | J18: (L.) A.R.Sm. | K18: Serpocaulon loriceum | L18: Taxon 55: 928 (2006) | M18: Goniophlebium loriceum (L.) J.Sm., Marginaria loricea (L.) C.Presl, Polypodium loriceum L., Goniophlebium arcuatum Fée, Goniophlebium pectinatum J.Sm., Goniophlebium punctulatum T.Moore, Goniophlebium ramosum (Lodd. ex Link) Fée, Marginaria falcata Fée, Polypodium chartaceum Baker, Polypodium elegans Cav. ex Sw., Polypodium karwinskianum E.J.Lowe, Polypodium lineare Houtt., Polypodium loriceum var. heterolepis Sodiro, Polypodium loriceum var. pectinatum (J.Sm.) Baker, Polypodium ramosum Lodd. ex Link | N18: Goniophlebium, Marginaria, Polypodium, Goniophlebium, Goniophlebium, Goniophlebium, Goniophlebium, Marginaria, Polypodium, Polypodium, Polypodium, Polypodium, Polypodium, Polypodium, Polypodium | O18: loriceum, loricea, loriceum, arcuatum, pectinatum, punctulatum, ramosum, falcata, chartaceum, elegans, karwinskianum, lineare, loriceum var. heterolepis, loriceum var. pectinatum, ramosum | P18: (L.) J.Sm., (L.) C.Presl, L., Fée, J.Sm., T.Moore, (Lodd. ex Link) Fée, Fée, Baker, Cav. ex Sw., E.J.Lowe, Houtt., Sodiro, (J.Sm.) Baker, Lodd. ex Link | Q18: N/A | R18: N/A | S18: N/A | T18: N/A | U18: TRUE | V18: No se han reportado usos para la especie. | W18: NO | X18: F, PT, E | Y18: Forb, Fern, Epiphyte | Z18: Plantas hemiepífitas o terrestres. Rizomas largos y rastreros, de color marrón oscuro, pruinosos; filopodios separados entre 1 y 8,5 cm. Escamas del rizoma dispersas, de forma redondeada a elíptica, adpresas, peltadas, bicoloras, de color marrón claro en los márgenes y marrón oscuro hacia el centro, con la base redondeada, el ápice redondeado a ampliamente agudo y adpreso, y los márgenes erosos. Frondas de 22–89 cm de largo. Pecíolos de 7,5–38 cm de largo, de color marrón oscuro, más claros en la parte distal. | AA18: CO | AB18: Colombia | AC18: Native | AD18: Extant | AE18: 150 | AF18: 3020 | AG18: Neotropical | AH18: En Colombia, la especie se ha registrado en los departamentos Antioquia, Chocó, Cundinamarca, Huila, Nariño, Norte de Santander y Putumayo; en bosques húmedos. | AI18: Done | AJ18: Terrestrial | AK18: Suitable | AL18: 1.6, 1.9 | AM18: La especie ocurre en hábitats de bosques húmedos en tierras bajas (elevación menor a 1.000 msnm), y en bosques de tierras altas (elevación mayor a 1000 msnm) (Sanín et at. 2023). | AN18: La especie está fértil casi todo el año, excepto en febrero (Sanín et at. 2023), y posiblemente es dispersada por viento. No se cuenta con información publicada sobre la ecología de la especie. El área de hábitat calculada tiene un valor de 107.449 km2. | AO18: =CONCATENATE(AM18," ",AN18) -> La especie ocurre en hábitats de bosques húmedos en tierras bajas (elevación menor a 1.000 msnm), y en bosques de tierras altas (elevación mayor a 1000 msnm) (Sanín et at. 2023). La especie está fértil casi todo el año, excepto en febrero (Sanín et at. 2023), y posiblemente es dispersada por viento. No se cuenta con información publicada sobre la ecología de la especie. El área de hábitat calculada tiene un valor de 107.449 km2. | AP18: Viento | AR18: 50 | AS18: 150 | AT18: Serpocaulon loriceum | AU18: 182314 | AV18: 32 | AW18: 183341* | AX18: 32* | AY18: 8 | AZ18: 8* | BA18: 37 | BC18: 47 | BZ18: Parque Nacional Natural Las Orquideas, Distrito Regional de Manejo Integrado Serrania de Penas Blancas
A19: Verónica Bedoya Calle | B19: 15 | C19: Plantae | D19: Tracheophyta | E19: Equisetopsida | F19: Polypodiales | G19: Polypodiaceae | H19: Serpocaulon | I19: maritimum | J19: (Hieron.) A.R.Sm. | K19: Serpocaulon maritimum | L19: Taxon 55: 928 (2006) | M19: Polypodium maritimum Hieron., Polypodium beyerianum Rosenst. | N19: Polypodium, Polypodium | O19: maritimum, beyerianum | P19: Hieron., Rosenst. | Q19: N/A | R19: N/A | S19: N/A | T19: N/A | U19: TRUE | V19: No se han reportado usos para la especie. | W19: NO | X19: F, PT, E | Y19: Forb, Fern, Epiphyte | Z19: Plantas hemiepífitas o terrestres. Rizomas largos y rastreros, de color marrón oscuro, pruinosos; filopodios separados entre 1 y 8,5 cm. Escamas del rizoma dispersas, de forma redondeada a elíptica, adpresas, peltadas, bicoloras, de color marrón claro en los márgenes y marrón oscuro hacia el centro, con la base redondeada, el ápice redondeado a ampliamente agudo y adpreso, y los márgenes erosos. Frondas de 22–89 cm de largo. Pecíolos de 7,5–38 cm de largo, de color marrón oscuro, más claros en la parte distal. | AA19: CO | AB19: Colombia | AC19: Native | AD19: Extant | AE19: 50 | AF19: 1600 | AG19: Neotropical | AH19: En Colombia, la especie se ha registrado en los departamentos Antioquia, Chocó, Guajira, Magdalena, Nariño y Valle del Cauca; en bosques húmedos. | AI19: Done | AJ19: Terrestrial | AK19: Suitable | AL19: 1.6 | AM19: La especie ocurre en hábitats de bosques húmedos en tierras bajas (elevación menor a 1.000 msnm). | AN19: La especie está fértil casi todo el año, excepto en septiembre (Sanín et at. 2023), y posiblemente es dispersada por viento. No se cuenta con información publicada sobre la ecología de la especie. El área de hábitat calculada tiene un valor de 90.590 km2. | AO19: =CONCATENATE(AM19," ",AN19) -> La especie ocurre en hábitats de bosques húmedos en tierras bajas (elevación menor a 1.000 msnm). La especie está fértil casi todo el año, excepto en septiembre (Sanín et at. 2023), y posiblemente es dispersada por viento. No se cuenta con información publicada sobre la ecología de la especie. El área de hábitat calculada tiene un valor de 90.590 km2. | AP19: Viento | AR19: 50 | AS19: 150 | AT19: Serpocaulon maritimum | AU19: 180554 | AV19: 52 | AW19: 5344464 | AX19: 52 | AY19: 12 | AZ19: 12 | BC19: 24 | BZ19: Parque Nacional Natural Farallones de Cali, Parque Nacional Natural Macuira, Parque Nacional Natural Tayrona, Reserva Forestal Protectora Nacional De Urrao, Reserva Forestal Protectora Nacional Rio Anchicaya
A20: Verónica Bedoya Calle | B20: 16 | C20: Plantae | D20: Tracheophyta | E20: Equisetopsida | F20: Polypodiales | G20: Polypodiaceae | H20: Serpocaulon | I20: nanegalense | J20: (Sodiro) A.R.Sm. | K20: Serpocaulon nanegalense | L20: Taxon 55: 928 (2006) | M20: Polypodium nanegalense Sodiro | N20: Polypodium | O20: nanegalense | P20: Sodiro | Q20: N/A | R20: N/A | S20: N/A | T20: N/A | U20: TRUE | V20: No se han reportado usos para la especie. | W20: NO | X20: F, PT, E | Y20: Forb, Fern, Epiphyte | Z20: Plantas hemiepífitas, epífitas o terrestres. Rizomas largos y rastreros, de color marrón oscuro a rojizo, generalmente sin pruina; filopodios separados entre 2,5 y 8 cm. Escamas del rizoma densas o dispersas de forma escasa a lo largo de los rizomas, lanceoladas a subuladas, adpresas, subpeltadas, bicolores, de color marrón claro en los márgenes y de marrón oscuro a rojizo hacia el centro, con la base redondeada, el ápice largamente acuminado y patente, y los márgenes dentados. Frondas de 20-100 cm de largo. Pecíolos de 10-35 cm de largo, subteretes en la parte proximal, sulcados en la distal, de color marrón oscuro y lustrosos. | AA20: CO | AB20: Colombia | AC20: Native | AD20: Extant | AE20: 2170 | AF20: 3500 | AG20: Neotropical | AH20: En Colombia, la especie se ha registrado en los departamentos Antioquia, Boyacá, Cauca, Cundinamarca, Nariño, Norte de Santander, Putumayo, Quindío, Risaralda y Valle del Cauca. La especie está presente en bosques nublados y bosques tropicales de montaña hasta el subpáramo. | AI20: Done | AJ20: Terrestrial | AK20: Suitable | AL20: 1.9 | AM20: La especie ocurre en hábitats de bosques húmedos en tierras altas (elevación mayor a 1000 msnm) (Sanín et at. 2023). | AN20: La especie está fértil casi todo el año, excepto en noviembre (Sanín et at. 2023), y posiblemente es dispersada por viento. No se cuenta con información publicada sobre la ecología de la especie. El área de hábitat calculada tiene un valor de 31.821 km2. | AO20: =CONCATENATE(AM20," ",AN20) -> La especie ocurre en hábitats de bosques húmedos en tierras altas (elevación mayor a 1000 msnm) (Sanín et at. 2023). La especie está fértil casi todo el año, excepto en noviembre (Sanín et at. 2023), y posiblemente es dispersada por viento. No se cuenta con información publicada sobre la ecología de la especie. El área de hábitat calculada tiene un valor de 31.821 km2. | AP20: Viento | AR20: 50 | AS20: 150 | AT20: Serpocaulon nanegalense | AU20: 151428 | AV20: 104 | AW20: 150772 | AX20: 100 | AY20: 17 | AZ20: 19
A21: Verónica Bedoya Calle | B21: 17 | C21: Plantae | D21: Tracheophyta | E21: Equisetopsida | F21: Polypodiales | G21: Polypodiaceae | H21: Serpocaulon | I21: patentissimum | J21: (Mett.) A.R.Sm. | K21: Serpocaulon patentissimum | L21: Taxon 55: 928 (2006) | M21: Ctenopteris patentissima (Mett.) Copel., Polypodium patentissimum Mett., Polypodium manabyanum Baker | N21: Ctenopteris, Polypodium, Polypodium | O21: patentissima, patentissimum, manabyanum | P21: (Mett.) Copel., Mett., Baker | Q21: Yashpilla in Azuay, Ecuador (Steyermark 52684, F). | R21: South American Indian (Other) | S21: TRUE | T21: N/A | U21: TRUE | V21: No se han reportado usos para la especie. | W21: NO | X21: F, PT, E | Y21: Forb, Fern, Epiphyte | Z21: Plantas hemiepífitas, rara vez terrestres (solo en las primeras etapas de crecimiento). Rizomas largos y rastreros, de color marrón claro a oscuro, ligeramente pruinosos; filopodios separados entre 1 y 6 cm. Escamas del rizoma dispersas, escasas, de forma ovado-lanceolada a triangular o deltada, con la base adpresada y el ápice patente, peltadas, algo bicolores, de color marrón claro a amarillento en los márgenes y de amarillo oscuro a dorado oscuro hacia el centro. Frondas de 16–39 cm de largo. Pecíolos de 1,5–5 cm de largo, subteretes en la parte proximal, con alas de 1 mm de ancho, confluentes con el tejido laminar, de color pajizo, marrón oscuro o rojizo en la parte proximal, y marrón claro en la parte distal. | AA21: CO | AB21: Colombia | AC21: Native | AD21: Extant | AE21: 450 | AF21: 2400 | AG21: Neotropical | AH21: En Colombia, la especie se ha registrado en los departamentos Antioquia, Nariño y Valle del Cauca; en bosques húmedos de altitud baja a media. | AI21: Done | AJ21: Terrestrial | AK21: Suitable | AL21: 1.6, 1.9 | AM21: La especie ocurre en hábitats de bosques húmedos en tierras bajas (elevación menor a 1.000 msnm), y en bosques de tierras altas (elevación mayor a 1000 msnm) (Sanín et at. 2023). | AN21: La especie está fertil todo el año (Sanín et at. 2023), y posiblemente es dispersada por viento. No se cuenta con información publicada sobre la ecología de la especie. El área de hábitat calculada tiene un valor de 25.741 km2. | AO21: =CONCATENATE(AM21," ",AN21) -> La especie ocurre en hábitats de bosques húmedos en tierras bajas (elevación menor a 1.000 msnm), y en bosques de tierras altas (elevación mayor a 1000 msnm) (Sanín et at. 2023). La especie está fertil todo el año (Sanín et at. 2023), y posiblemente es dispersada por viento. No se cuenta con información publicada sobre la ecología de la especie. El área de hábitat calculada tiene un valor de 25.741 km2. | AP21: Viento | AR21: 50 | AS21: 150 | AT21: Serpocaulon patentissimum | AU21: 30224 | AV21: 36 | AW21: 29790 | AX21: 32 | AY21: 4 | AZ21: 5
A22: Verónica Bedoya Calle | B22: 18 | C22: Plantae | D22: Tracheophyta | E22: Equisetopsida | F22: Polypodiales | G22: Polypodiaceae | H22: Serpocaulon | I22: psychotrium | J22: Mostacero, D.Sanín & A.R.Sm. | K22: Serpocaulon psychotrium | L22: Amer. Fern J. 111: 69 (2021) | M22: N/A | N22: N/A | O22: N/A | P22: N/A | Q22: Uap-hia in Zulia Province, Venezuela (Matos & Arias 1270, CAR). | R22: South American Indian (Other) | S22: TRUE | T22: N/A | U22: TRUE | V22: No se han reportado usos para la especie. | W22: NO | X22: F, PT, E | Y22: Forb, Fern, Epiphyte | Z22: Plantas epífitas, hemiepífitas y, ocasionalmente, terrestres. Rizomas largos y rastreros, de color marrón oscuro y mate, gris verdoso cuando están frescos, sin pruina, que se oxidan al cortarlos; filopodios separados entre 1 y 4,5 cm. Escamas del rizoma densas, subuladas, patentes, bicolores en la base, de color marrón claro en los márgenes y marrón oscuro hacia el centro; bases ovadas a redondeadas, adpresas y peltadas; ápices reduciéndose bruscamente a una punta larga y estrecha. Frondas de 28–150 cm de largo. Pecíolos de (8–)17–50(–70) cm de largo, subteretes en la parte proximal, ligeramente sulcados en la distal, generalmente de color pajizo. | AA22: CO | AB22: Colombia | AC22: Native | AD22: Extant | AE22: 150 | AF22: 2000 | AG22: Neotropical | AH22: En Colombia, la especie se ha registrado en los departamentos Amazonas, Antioquia, Boyacá, Caquetá, Cesar, Cundinamarca, Guaviare y Huila; principalmente en las estribaciones andino-amazónicas, en bosques premontanos húmedos. | AI22: Done | AJ22: Terrestrial | AK22: Suitable | AL22: 1.6, 1.9 | AM22: La especie ocurre en hábitats de bosques húmedos en tierras bajas (elevación menor a 1.000 msnm), y en bosques de tierras altas (elevación mayor a 1000 msnm) (Sanín et at. 2023). | AN22: La especie está fertil todo el año (Sanín et at. 2023), y posiblemente es dispersada por viento. No se cuenta con información publicada sobre la ecología de la especie. El área de hábitat calculada tiene un valor de 270.332 km2. | AO22: =CONCATENATE(AM22," ",AN22) -> La especie ocurre en hábitats de bosques húmedos en tierras bajas (elevación menor a 1.000 msnm), y en bosques de tierras altas (elevación mayor a 1000 msnm) (Sanín et at. 2023). La especie está fertil todo el año (Sanín et at. 2023), y posiblemente es dispersada por viento. No se cuenta con información publicada sobre la ecología de la especie. El área de hábitat calculada tiene un valor de 270.332 km2. | AP22: Viento | AR22: 50 | AS22: 150 | AT22: Serpocaulon psychotrium | AU22: 442709 | AV22: 80 | AW22: 429306 | AX22: 80 | AY22: 17 | AZ22: 18
A23: Verónica Bedoya Calle | B23: 19 | C23: Plantae | D23: Tracheophyta | E23: Equisetopsida | F23: Polypodiales | G23: Polypodiaceae | H23: Serpocaulon | I23: ptilorhizon | J23: (Christ) A.R.Sm. | K23: Serpocaulon ptilorhizon | L23: Taxon 55: 929 (2006) | M23: Polypodium ptilorhizon Christ | N23: Polypodium | O23: ptilorhizon | P23: Christ | Q23: N/A | R23: N/A | S23: N/A | T23: N/A | U23: TRUE | V23: No se han reportado usos para la especie. | W23: NO | X23: F, PT, E, L | Y23: Forb, Fern, Epiphyte, Lithophyte | Z23: Plantas hemiepífitas, epífitas o, en raras ocasiones, rupícolas. Rizomas largos y rastreros, de color marrón oscuro a amarillento, pruinosos; filopodios separados entre 1 y 5,5 cm. Escamas del rizoma dispersas, redondeadas a elípticas, adpresas, peltadas, bicolores, de color marrón claro en los márgenes y marrón oscuro hacia el centro, con la base y el ápice redondeados a ampliamente agudos y adpresos, y los márgenes erosos. Frondas de 6,5–38 cm de largo. Pecíolos de 1,5–17 cm de largo, subteretes en la parte proximal, ligeramente alados en la parte distal, de color marrón claro. Láminas de 5–21 × 2–8 cm, lanceoladas, pinnatisectas, truncadas en la parte proximal, con ápices que se estrechan gradualmente. | AA23: CO | AB23: Colombia | AC23: Native | AD23: Extant | AE23: 650 | AF23: 2680 | AG23: Neotropical | AH23: En Colombia, se ha registrado en el departamento de Antioquia, en bosques nublados. | AI23: Done | AJ23: Terrestrial | AK23: Suitable | AL23: 1.6, 1.9 | AM23: La especie ocurre en hábitats de bosques húmedos en tierras bajas (elevación menor a 1.000 msnm), y en bosques de tierras altas (elevación mayor a 1000 msnm) (Sanín et at. 2023). | AN23: La especie está fertil todo el año (Sanín et at. 2023), y posiblemente es dispersada por viento. No se cuenta con información publicada sobre la ecología de la especie. El área de hábitat calculada tiene un valor de 1.552 km2. | AO23: =CONCATENATE(AM23," ",AN23) -> La especie ocurre en hábitats de bosques húmedos en tierras bajas (elevación menor a 1.000 msnm), y en bosques de tierras altas (elevación mayor a 1000 msnm) (Sanín et at. 2023). La especie está fertil todo el año (Sanín et at. 2023), y posiblemente es dispersada por viento. No se cuenta con información publicada sobre la ecología de la especie. El área de hábitat calculada tiene un valor de 1.552 km2. | AP23: Viento | AR23: 50 | AS23: 150 | AT23: Serpocaulon ptilorhizon | AU23: 3128 | AV23: 36 | AW23: 3065 | AX23: 32 | AY23: 5 | AZ23: 7 | BA23: 80 | BC23: 98 | BD23: NO
A24: Verónica Bedoya Calle | C24: Plantae | D24: Tracheophyta | E24: Equisetopsida | F24: Polypodiales | G24: Polypodiaceae | H24: Serpocaulon | I24: richardii | K24: Serpocaulon richardii | Q24: N/A | R24: N/A | S24: N/A | T24: N/A | U24: TRUE | V24: No se han reportado usos para la especie. | W24: NO | X24: F, PT, E, L | Y24: Forb, Fern, Epiphyte, Lithophyte | Z24: Plantas hemiepífitas, epífitas, terrestres o, en raras ocasiones, rupícolas. Rizomas largos y rastreros, de color marrón oscuro a rojizo, sin pruina; filopodios separados entre 2 y 5 cm. Escamas del rizoma densas, con la base peltada, los ápices patentes a reflejos, bicoloros, de color marrón claro en los márgenes y de marrón oscuro a rojizo hacia el centro, la base redondeada a obtusa, los ápices acuminados y con una larga cola, los márgenes erosos a ligeramente dentados. Frondas de 45–120 cm de largo. Pecíolos de 15–58 cm de largo, subteretes en la parte proximal, ligeramente sulcados en la distal, de color marrón claro a marrón oscuro, mate. | AA24: CO | AB24: Colombia | AC24: Native | AD24: Extant | AE24: 235 | AF24: 2225 | AG24: Neotropical | AH24: En Colombia, la especie se ha registrado en los departamentos Boyacá, Cundinamarca y Putumayo; principalmente en los bosques premontanos de la zona de transición entre la Amazonía y los Andes. | AI24: Done | AJ24: Terrestrial | AK24: Suitable | AL24: 1.6, 1.9 | AM24: La especie ocurre en hábitats de bosques húmedos en tierras bajas (elevación menor a 1.000 msnm), y en bosques de tierras altas (elevación mayor a 1000 msnm) (Sanín et at. 2023). | AN24: La especie está fertil todo el año (Sanín et at. 2023), y posiblemente es dispersada por viento. No se cuenta con información publicada sobre la ecología de la especie. El área de hábitat calculada tiene un valor de 108.520 km2. El área de hábitat calculada tiene un valor de 1.524 km2. | AO24: =CONCATENATE(AM24," ",AN24) -> La especie ocurre en hábitats de bosques húmedos en tierras bajas (elevación menor a 1.000 msnm), y en bosques de tierras altas (elevación mayor a 1000 msnm) (Sanín et at. 2023). La especie está fertil todo el año (Sanín et at. 2023), y posiblemente es dispersada por viento. No se cuenta con información publicada sobre la ecología de la especie. El área de hábitat calculada tiene un valor de 108.520 km2. El área de hábitat calculada tiene un valor de 1.524 km2. | AP24: Viento | AR24: 50 | AS24: 150 | AT24: Serpocaulon richardii** | AU24: 5131 | AV24: 12 | AW24: 4426 | AX24: 12 | AY24: 3 | AZ24: 3 | BA24: 0 | BC24: 41 | BD24: NO
A25: Verónica Bedoya Calle | B25: 20 | C25: Plantae | D25: Tracheophyta | E25: Equisetopsida | F25: Polypodiales | G25: Polypodiaceae | H25: Serpocaulon | I25: sessilifolium | J25: (Desv.) A.R.Sm. | K25: Serpocaulon sessilifolium | L25: Taxon 55: 929 (2006) | M25: Polypodium sessilifolium Desv., Goniophlebium acuminatum Fée, Goniophlebium surucuchense (Hook.) T.Moore, Polypodium andinum H.Karst., Polypodium antillense Maxon, Polypodium biauriculatum Hook., Polypodium chacapoyense Hook., Polypodium pseudofraternum A.C.Sm., Polypodium remotum Baker, Polypodium rimbachii Sodiro, Polypodium sessilifolium var. lobulatum E.Fourn., Polypodium sessilifolium var. surucuchensis Mille, Polypodium surucuchense Hook., Polypodium uniseriale C.Chr., Serpocaulon acuminatum (Fée) Christenh., Serpocaulon antillense (Maxon) A.R.Sm. Serpocaulon chacapoyense (Hook.) A.R.Sm. | N25: Polypodium, Goniophlebium, Goniophlebium, Polypodium, Polypodium, Polypodium, Polypodium, Polypodium, Polypodium, Polypodium, Polypodium, Polypodium, Polypodium, Polypodium, Serpocaulon, Serpocaulon, Serpocaulon | O25: sessilifolium, acuminatum, surucuchense, andinum, antillense, biauriculatum, chacapoyense, pseudofraternum, remotum, rimbachii, sessilifolium var. lobulatum, sessilifolium var. surucuchensis, surucuchense, uniseriale, acuminatum, antillense, chacapoyense | P25: Desv., Fée, (Hook.) T.Moore, H.Karst., Maxon, Hook., Hook., A.C.Sm., Baker, Sodiro, var. lobulatum E.Fourn., var. surucuchensis Mille, Hook., C.Chr., (Fée) Christenh., (Maxon) A.R.Sm., (Hook.) A.R.Sm. | Q25: N/A | R25: N/A | S25: N/A | T25: N/A | U25: TRUE | V25: No se han reportado usos para la especie. | W25: NO | X25: F, PT, E, L | Y25: Forb, Fern, Epiphyte, Lithophyte | Z25: Plantas epífitas, rara vez terrestres o rupícolas. Rizomas cortos y rastreros, de color marrón oscuro en la parte distal, marrón claro hacia el ápice, pruinosos; filopodios separados entre 1 y 2,6 cm. Escamas del rizoma densas, aciculares-lanceoladas, concoloras, marrón oscuro, iridiscentes, con la base truncada a redondeada y adpresa, auriculadas y a menudo superpuestas, con el ápice largamente acuminado y patente. Frondas de 9–135 cm de largo. Pecíolos de 2–53 cm de largo, subteretes en la parte proximal, ligeramente sulcados en la parte distal, de color marrón oscuro a claro. | AA25: CO | AB25: Colombia | AC25: Native | AD25: Extant | AE25: 950 | AF25: 4000 | AG25: Neotropical | AH25: En Colombia, la especie se ha registrado en los departamentos Antioquia, Boyacá, Caldas, Cauca, Cundinamarca, Huila, Nariño, Quindío, Risaralda, Santander, Tolima y Valle del Cauca; crece en bosques nubosos de alta montaña y subpáramos en el continente, y en altitudes más bajas en las islas del Caribe. | AI25: Done | AJ25: Terrestrial | AK25: Suitable | AL25: 1.6, 1.9 | AM25: La especie ocurre en hábitats de bosques húmedos en tierras bajas (elevación menor a 1.000 msnm), y en bosques de tierras altas (elevación mayor a 1000 msnm) (Sanín et at. 2023). | AN25: La especie está fertil todo el año (Sanín et at. 2023), y posiblemente es dispersada por viento. No se cuenta con información publicada sobre la ecología de la especie. El área de hábitat calculada tiene un valor de 108.520 km2. | AO25: =CONCATENATE(AM25," ",AN25) -> La especie ocurre en hábitats de bosques húmedos en tierras bajas (elevación menor a 1.000 msnm), y en bosques de tierras altas (elevación mayor a 1000 msnm) (Sanín et at. 2023). La especie está fertil todo el año (Sanín et at. 2023), y posiblemente es dispersada por viento. No se cuenta con información publicada sobre la ecología de la especie. El área de hábitat calculada tiene un valor de 108.520 km2. | AP25: Viento | AR25: 50 | AS25: 150 | AT25: Serpocaulon sessilifolium | AU25: 195947 | AV25: 160 | AW25: 196810 | AX25: 160 | AY25: 28 | AZ25: 31
A26: Verónica Bedoya Calle | B26: 21 | C26: Plantae | D26: Tracheophyta | E26: Equisetopsida | F26: Polypodiales | G26: Polypodiaceae | H26: Serpocaulon | I26: subandinum | J26: (Sodiro) A.R.Sm. | K26: Serpocaulon subandinum | L26: Taxon 55: 929 (2006) | M26: Polypodium subandinum Sodiro | N26: Polypodium | O26: subandinum | P26: Sodiro | Q26: N/A | R26: N/A | S26: N/A | T26: N/A | U26: TRUE | V26: No se han reportado usos para la especie. | W26: NO | X26: F, PT, E, L | Y26: Forb, Fern, Epiphyte, Lithophyte | Z26: Plantas hemiepífitas, epífitas, en raras ocasiones rupícolas o terrestres. Rizomas largos y rastreros, de color marrón claro a amarillento o, en raras ocasiones, de marrón oscuro a rojizo, pruinosos; filopodios separados entre 0,3 y 11 cm. Escamas del rizoma dispersas, densas hacia el ápice, ovado-lanceoladas, lanceoladas a triangulares, adpresas, bicolores, de color marrón claro a amarillento en los márgenes y de marrón oscuro a amarillo oscuro hacia el centro; bases truncadas a redondeadas; ápices agudos a largamente acuminados; márgenes ciliados. Frondas de 13-76 cm de largo. Pecíolo de 2-28 cm de largo, subterete en la parte proximal, sulcado en la distal, de color marrón oscuro a claro. | AA26: CO | AB26: Colombia | AC26: Native | AD26: Extant | AE26: 1450 | AF26: 4150 | AG26: Neotropical | AH26: En Colombia, la especie se ha registrado en los departamentos Antioquia, Boyacá, Caldas, Cauca, Cesar, Cundinamarca, Magdalena, Nariño, Norte de Santander, Quindío, Risaralda y Tolima; principalmente en ecosistemas premontanos, montanos y de subpáramo andinos. | AI26: Done | AJ26: Terrestrial | AK26: Suitable | AL26: 1.9 | AM26: La especie ocurre en hábitats de bosques húmedos en tierras altas (elevación mayor a 1000 msnm) (Sanín et at. 2023). | AN26: La especie está fertil todo el año (Sanín et at. 2023), y posiblemente es dispersada por viento. No se cuenta con información publicada sobre la ecología de la especie. El área de hábitat calculada tiene un valor de 127.381 km2. | AO26: =CONCATENATE(AM26," ",AN26) -> La especie ocurre en hábitats de bosques húmedos en tierras altas (elevación mayor a 1000 msnm) (Sanín et at. 2023). La especie está fertil todo el año (Sanín et at. 2023), y posiblemente es dispersada por viento. No se cuenta con información publicada sobre la ecología de la especie. El área de hábitat calculada tiene un valor de 127.381 km2. | AP26: Viento | AR26: 50 | AS26: 150 | AT26: Serpocaulon subandinum | AU26: 236335 | AV26: 152 | AW26: 238241 | AX26: 152 | AY26: 29 | AZ26: 38
A27: Verónica Bedoya Calle | B27: 22 | C27: Plantae | D27: Tracheophyta | E27: Equisetopsida | F27: Polypodiales | G27: Polypodiaceae | H27: Serpocaulon | I27: triseriale | J27: (Sw.) A.R.Sm. | K27: Serpocaulon triseriale | L27: Taxon 55: 929 (2006) | M27: Goniophlebium triseriale (Sw.) Wherry, Polypodium triseriale Sw., Goniophlebium ampliatum Maxon, Goniophlebium brasiliense Farw., Goniophlebium brasiliense var. preslianum Farw., Goniophlebium gladiatum (C.Presl) Fée, Goniophlebium haenkei C.Presl, Goniophlebium intermedium Fée, Goniophlebium neriifolium (Schkuhr) Hook., Goniophlebium xiphophorum (Kunze ex Mett.) Fée, Marginaria gladiata C.Presl, Marginaria neriifolia (Schkuhr) C.Presl, Marginaria rhoifolia C.Presl, Polypodium ampliatum (Maxon) Proctor, Polypodium brasiliense Poir., Polypodium brasiliense var. gladiatum Kuhn, Polypodium brasiliense var. neriifolium (Schkuhr) Baker, Polypodium brasiliense var. subcordatum Christ ex Duss, Polypodium campylopodum Klotzsch, Polypodium ensiforme Vell., Polypodium gladiatum Kunze, Polypodium haenkei (C.Presl) Liebm., Polypodium longifolium C.Presl, Polypodium lucens Schrad., Polypodium neriifolium Schkuhr, Polypodium neriifolium var. acuminatissimum Kuntze, Polypodium neriifolium var. heterophyllum Kuntze, Polypodium palma Vell., Polypodium palmatum Vell., Polypodium preslianum Spreng., Polypodium preslianum var. immersum Rosenst., Polypodium subalatum Klotzsch, Polypodium triseriale var. gladiatum (Kuhn) Proctor, Polypodium variolatum Willd., Polypodium xiphophoron Kunze ex Mett. | N27: Goniophlebium, Polypodium, Goniophlebium, Goniophlebium, Goniophlebium, Goniophlebium, Goniophlebium, Goniophlebium, Goniophlebium, Goniophlebium, Marginaria, Marginaria, Marginaria, Polypodium, Polypodium, Polypodium, Polypodium, Polypodium, Polypodium, Polypodium, Polypodium, Polypodium, Polypodium, Polypodium, Polypodium, Polypodium, Polypodium, Polypodium, Polypodium, Polypodium, Polypodium, Polypodium, Polypodium, Polypodium, Polypodium, | O27: triseriale, triseriale, ampliatum, brasiliense, brasiliense var. preslianum, gladiatum, haenkei, intermedium, neriifolium, xiphophorum, gladiata, neriifolia, rhoifolia, ampliatum, brasiliense, brasiliense var. gladiatum, brasiliense var. neriifolium, brasiliense var. subcordatum, campylopodum, ensiforme, gladiatum, haenkei, longifolium, lucens, neriifolium, neriifolium var. acuminatissimum, neriifolium var. heterophyllum, palma, palmatum, preslianum, preslianum var. immersum, subalatum, triseriale var. gladiatum, variolatum, xiphophoron, | P27: (Sw.) Wherry, Sw., Maxon, Farw., Farw., (C.Presl) Fée, C.Presl, Fée, (Schkuhr) Hook., (Kunze ex Mett.) Fée, C.Presl, (Schkuhr) C.Presl, C.Presl, (Maxon) Proctor, Poir., Kuhn, (Schkuhr) Baker, Christ ex Duss, Klotzsch, Vell., Kunze, (C.Presl) Liebm., C.Presl, Schrad., Schkuhr, Kuntze, Kuntze, Vell., Vell., Spreng., Rosenst., Klotzsch, (Kuhn) Proctor, Willd., Kunze ex Mett. | Q27: Calaguala in Honduras (Gómez 55, F). | R27: South American Indian (Other) | S27: TRUE | T27: N/A | U27: TRUE | V27: Silva et al. (2011) reportaron que la especie Serpocaulon triseriale se utilizaba como planta ornamental que sirve de refugio a la fauna autóctona en Bahía (Brasil). | W27: NO | X27: F, PT, E, L | Y27: Forb, Fern, Epiphyte, Lithophyte | Z27: Plantas epífitas, terrestres, rara vez subterráneas o rupícolas. Rizomas cortos y rastreros, de color marrón oscuro, a menudo pruinosos; filopodios separados entre 1 y 12 cm. Escamas del rizoma densas, de forma ovado-lanceolada a lanceolada, patentes, subpeltadas, con un punto de inserción prominente, bicolores, de color marrón claro o naranja en los márgenes y de naranja a marrón oscuro hacia el centro, bases redondeadas a obtusas, ápices acuminados a largamente decurrentes y patentes, márgenes erosos a dentados. Frondas de 15–126 cm de largo. Pecíolos de 5,5–49 cm de largo, subteretes en la parte proximal, ligeramente sulcados en la distal, de color marrón claro a oscuro. | AA27: CO | AB27: Colombia | AC27: Native | AD27: Extant | AE27: 0 | AF27: 2500 | AG27: Neotropical | AH27: En Colombia, la especie se ha registrado en los departamentos Amazonas, Antioquia, Boyacá, Caldas, Caquetá, Cauca, Chocó, Cundinamarca, Guainía, Guaviare, Huila, Magdalena, Meta, Putumayo, Quindío, Risaralda, Santander, Tolima, Valle del Cauca, Vaupés y Vichada. Esta especie presenta una amplia distribución en ecosistemas de tierras bajas a premontanos, desde los 0 hasta los 2500 m, en bosques secos o húmedos, con o sin perturbaciones. | AI27: Done | AJ27: Terrestrial | AK27: Suitable | AL27: 1.6, 1.9 | AM27: La especie ocurre en hábitats de bosques húmedos en tierras bajas (elevación menor a 1.000 msnm), y en bosques de tierras altas (elevación mayor a 1000 msnm) (Sanín et at. 2023). | AN27: La especie está fertil todo el año (Sanín et at. 2023), y posiblemente es dispersada por viento. No se cuenta con información publicada sobre la ecología de la especie. El área de hábitat calculada tiene un valor de 675.077 km2. | AO27: =CONCATENATE(AM27," ",AN27) -> La especie ocurre en hábitats de bosques húmedos en tierras bajas (elevación menor a 1.000 msnm), y en bosques de tierras altas (elevación mayor a 1000 msnm) (Sanín et at. 2023). La especie está fertil todo el año (Sanín et at. 2023), y posiblemente es dispersada por viento. No se cuenta con información publicada sobre la ecología de la especie. El área de hábitat calculada tiene un valor de 675.077 km2. | AP27: Viento | AR27: 50 | AS27: 150 | AT27: Serpocaulon triseriale | AU27: 991875 | AV27: 364 | AW27: 992143 | AX27: 364 | AY27: 76 | AZ27: 79
A28: Verónica Bedoya Calle | B28: 23 | C28: Plantae | D28: Tracheophyta | E28: Equisetopsida | F28: Polypodiales | G28: Polypodiaceae | H28: Serpocaulon | I28: wagneri | J28: (Mett.) A.R.Sm. | K28: Serpocaulon wagneri | L28: Taxon 55: 929 (2006) | M28: Polypodium wagneri Mett., Goniophlebium pectinatum J.Sm., Polypodium costaricense Christ, Polypodium kuhlmannii A.Samp., Polypodium panorense C.Chr., Polypodium pectinatum var. wagneri Jenman, Serpocaulon panorense (C.Chr.) A.R.Sm. | N28: Polypodium, Goniophlebium, Polypodium, Polypodium, Polypodium, Polypodium, Serpocaulon | O28: wagneri, pectinatum, costaricense, kuhlmannii, panorense, pectinatum var. Wagneri, panorense | P28: Mett., J.Sm., Christ, A.Samp., C.Chr., Jenman, (C.Chr.) A.R.Sm. | Q28: The Chacobo from the Amazonian province of Vaca Díez, Bolivia, has used two names: xëqui jahëhua (Boom 4380, LPB, NY) and mitaisa (Boom 5050, LPB, NY) | R28: South American Indian (Other) | S28: TRUE | T28: N/A | U28: TRUE | V28: No se han reportado usos para la especie. | W28: NO | X28: PT, E | Y28: Fern, Epiphyte | Z28: Plantas epífitas. Rizomas cortos y rastreros, de color marrón oscuro a rojizo, ligeramente pruinosos; filopodios separados entre 3,6 y 6,5 cm. Escamas del rizoma densas, subuladas, subapresadas, peltadas, bicolores, de color marrón claro en los márgenes y marrón rojizo oscuro hacia el centro, con la base redondeada y el ápice de caudado a acuminado. Frondas de 29–66 cm de largo. Pecíolos de 4–5,5 cm de largo, subteretes en la parte proximal, ligeramente alados en la parte distal, sobre todo en la unión con la lámina, de color marrón claro a marrón opaco. | AA28: CO | AB28: Colombia | AC28: Native | AD28: Extant | AE28: 10 | AF28: 2550 | AG28: Neotropical | AH28: En Colombia, la especie se ha registrado en los departamentos Antioquia, Chocó, Cundinamarca y Norte de Santander; en las tierras bajas de los bosques húmedos. | AI28: Done | AJ28: Terrestrial | AK28: Suitable | AL28: 1.6, 1.9 | AM28: La especie ocurre en hábitats de bosques húmedos en tierras bajas (elevación menor a 1.000 msnm), y en bosques de tierras altas (elevación mayor a 1000 msnm) (Sanín et at. 2023). | AN28: La especie está fertil todo el año (Sanín et at. 2023), y posiblemente es dispersada por viento. No se cuenta con información publicada sobre la ecología de la especie. El área de hábitat calculada tiene un valor de 54.533 km2. | AO28: =CONCATENATE(AM28," ",AN28) -> La especie ocurre en hábitats de bosques húmedos en tierras bajas (elevación menor a 1.000 msnm), y en bosques de tierras altas (elevación mayor a 1000 msnm) (Sanín et at. 2023). La especie está fertil todo el año (Sanín et at. 2023), y posiblemente es dispersada por viento. No se cuenta con información publicada sobre la ecología de la especie. El área de hábitat calculada tiene un valor de 54.533 km2. | AP28: Viento | AR28: 50 | AS28: 150 | AT28: Serpocaulon wagneri | AU28: 91473 | AV28: 28 | AW28: 91865 | AX28: 28 | AY28: 6 | AZ28: 6
B29: 24
B30: 25
B31: 26
B32: 27
B33: 28
B34: 29
B35: 30
B36: 31
B37: 32
B38: 33
B39: 34
B40: 35
... B44: 39
B45: 37
B46: 38
B47: 39
B48: 40
B49: 41
B50: 42
B51: 43
B52: 44
B53: 45
B54: 46
B55: 47
B56: 48
... B208: 200

Sheet references
A1: campo | B1: Reference_type | C1: access_date | D1: alternate_title | E1: author | F1: date | G1: edition | H1: externalBibCode | I1: internal_taxon_id | J1: isbnissn | K1: keywords | L1: number | M1: number_of_volumes | N1: pages | O1: place_published | P1: publisher | Q1: secondary_author | R1: secondary_title | S1: section | T1: short_title | U1: submission_type | V1: title | W1: type | X1: url | Y1: volume | Z1: year
A2: OJO: Antes de crear la csv, copie esta hoja en otra de excel y BORRE la Columna A y las Filas 2 a la 5 (todo lo que esta con fondo cafecito y letra roja). Este texto rojo NO debe ir en el archivo .csv final que se va a subir al SIS connect | B2: OBLIGATORIO. Declarar (según las opciones del SIS/ en inglés/ como aparece acá abajo)/ el tipo de recurso bibliográfico. Opciones= Assessment : este debe ser el tipo de la mayoría de los recursos bibliográficos/ que son los usados para la evaluación/ de donde de recopiló información para la especie de su ecología/ estado de conservación/ etc. Taxonomy : este tipo es SOLO para las referencias bibliográficas que tengan que ver con soluciones a problemas nomenclaturales de la especie. | C2: Condicional. Si es un recurso de internet/ es OBLIGATORIO especificar la fecha en que se visitó de la página web. Formato: dd-mm-yyyy (día-mes-año). Si no es un recurso de internet/ dejar la celda vacía. | D2: Opcional, llenar celda con N/A | E2: CAMPO OBLIGATORIO. Especificar el autor(es) del recurso bibliográfico. Si son varios autores, separar por comas. Cada autor debe citarce solamente con su Apellido + Inicial(es) del nombre con punto final sin espacio. Si son varias iniciales, separarlas por puntos, sin espacios, con punto final. Si se desean usar dos apellidos, separarlos con guión medio y sin espacios. Evite usar tildes u otros caracteres que no se usan en inglés. Si son mas de dos autores deben usar un "y" para publicaciones en Español o "and" para publicaciones en inglés, antes del último autor. Ejemplos: Lopez-Gallego C. Lopez-Gallego C., Morales P.A. y Taborda D. | F2: Opcional, Dejar celda vacia | G2: Opcional, Dejar celda vacia | H2: Opcional, Dejar celda vacia | I2: CAMPO OBLIGATORIO. Número interno del proyecto asignado para la especie/ el que le corresponde en la pestaña "BASE MAESTRA". | J2: Opcional, Dejar celda vacia | K2: Opcional, Dejar celda vacia | L2: Incluir en esta celda el número de volumen en el caso de árticulos de revista (Journal Article) | M2: Opcional, Dejar celda vacia | N2: Especifique el rango de páginas usadas del recurso bibliográfico. Formato: página inicial + guión medio + página final (sin espacios/ sin puntos ni comas). Si esto no aplica para el recurso bibliográfico, diligenciar la celda con N/A | O2: CAMPO OBLIGATORIO. Especifique el país de publicación del recurso bibliográfico (sin puntos ni comas). | P2: CAMPO OBLIGATORIO. Especifique el nombre de la editorial o quien publica el recurso bibliográfico (sin puntos ni comas). | Q2: Celda OBLIGATORIO para el caso de capítulos de libro, opcional para el caso de libros. Ingresar aquí los editores del libro. De lo contrario diligenciar celda con N/A El formato es inverso a la casilla de autor: Ejemplo: R. Bernal, M. Celis y R. Gradstein | R2: Campo Obligatorio para los articulos de revista, poner aca el nombre de la revista, evite abreviaturas. En el caso de "book section" (capítulo de libro) usar para titulo principal del libro. En el caso de "book" usar para titulo secundario. Para otro tipo de fuentes bibliográficas, diligenciar celda con N/A | S2: Opcional, Dejar celda vacia | T2: Opcional, Dejar celda vacia | U2: CAMPO OBLIGATORIO. Declar (según las opciones del SIS/ en inglés/ como aparece acá abajo) el estado de la publicación. Elegir sólo una opción. Opciones= Published / In press / Submitted / In prep | V2: CAMPO OBLIGATORIO. Especificar el título de la publicación. Use el texto más sencillo posible (si puede tener signos de puntuación). | W2: CAMPO OBLIGATORIO Declarar (según las opciones del SIS/ en inglés/ como aparece acá abajo) el tipo de publicación. Elegir sólo una opción. Opciones= book/ book section/ computer program/ conference paper/ conference proceedings/ edited book/ electronic source/ journal/ journal article/ magazine article/ manuscript/ newspaper article/ other/ report/ rldb/ thesis | X2: Campo obligatorio para los recursos electrónicos. Sin embargo es deseable incluirlo si los otros tipos de referencias lo tienen. Especificar la URL o la página web de acceso al recurso, para artículos de revista usar enlace DOI (No usar páginas de baja credibilidad como Wikipedia o enlaces que incluyan Sci-Hub) Si no es un recurso de internet/ dejar la celda vacía. | Y2: En el caso de que aplique (como para artículos de revista)/ especifique el número del volumen de la publicación. Si esto no aplica, diligenciar la celda con N/A | Z2: CAMPO OBLIGATORIO. Especifique el año de publicación del recurso bibliográfico, sin puntos ni comas. Para las páginas web usar la fecha de actualización.
A3: EJEMPLO (para una especie con # como internal_taxon_id) BORRAR estas filas del ejemplo. Este texto marrón NO debe ir en al archivo -csv | B3: Assessment | C3: 19-11-2019 | E3: Lopez-Gallego C. | I3: 1 | N3: 41-43 | O3: Colombia | P3: Instituto de Investigaciones Biológicas Alexander von Humboldt | U3: Published | V3: Plan de conservacion para las Zamias plantas de Colombia | W3: book | Z3: 2015
B4: Assessment | C4: 19-11-2019 | E4: Lopez-Gallego C., Morales P.A. y Taborda D. | I4: 1 | N4: 1022-1031 | O4: Colombia | P4: ATBC Press | R4: Biotropica | U4: Published | V4: Population dynamics of Zamia chigua in a gradient of habitat disturbance | W4: journal article | Y4: 68 | Z4: 2017
B5: Assessment | C5: 19-11-2019 | E5: IUCN | I5: 1 | O5: Colombia | P5: IUCN | U5: Published | V5: Red List of species | W5: electronic source | X5: https://www.iucnredlist.org/ | Z5: 2019

Sheet credits
A1: campo | B1: order | C1: affiliation | D1: credit_type | E1: email | F1: firstName | G1: initials | H1: internal_taxon_id | I1: lastName | J1: nickname | K1: user_id
